Workbook

Sheet README_Architecture
A1: README Architecture
A2: Synthetic Hackfest Test Data - v2 focused on Talent360i Auto Assessment Generation with SME approval and scheduling
A3: item | B3: details
A4: Dataset name | B4: Talent360i Auto Assessment Generation Hackfest Dataset v2
A5: Purpose | B5: Privacy-safe relational dataset for demonstrating auto assessment generation, SME approval, scheduling, synthetic assessment results, current level and TNI recommendations.
A6: Core workflow | B6: Role/JD + skill definitions + role-skill map + approved questions -> AI agent drafts question bank -> SME approves/edits/rejects -> scheduler launches assessment -> synthetic results calculate current level and TNI.
A7: MVP boundary | B7: Focused on Talent360i assessment generation. Broader SkillPath evidence submission, manager validation, readiness and succession signals are acknowledged as roadmap only.
A8: Source basis | B8: Actual FinOps role profiles, JDs, skill dictionaries, role-to-skill matrices, approved AP/T&E assessment and skill gap/training materials were analyzed.
A9: Privacy label | B9: All people, assignment, results, current-level and movement records are Synthetic Hackfest Test Data.
A10: Included towers | B10: R2R, AP/P2P, O2C
A11: Selected roles | B11: Banking Preparer Job (Preparation + Cash Posting), GA Preparer Job (Preparation-only), Consolidation Preparer Job (Execution + Pack Prep), P2P Lead, P2P Senior Associate, T&E Lead, Billing Team Lead, Associate Revenue Controller, Senior Revenue Associate
A12: Synthetic population | B12: 36 synthetic users, 4 per selected role
A13: Human-in-loop rule | B13: No AI-generated question is eligible for scheduling unless SME review status is Approved.
A15: Workbook structure
A16: # | B16: Sheet | C16: Rows | D16: Columns
A17: 1 | B17: README_Architecture | C17: 10 | D17: 2
A18: 2 | B18: Source_Analysis | C18: 13 | D18: 7
A19: 3 | B19: Data_Dictionary | C19: 260 | D19: 5
A20: 4 | B20: Relationship_Map | C20: 13 | D20: 6
A21: 5 | B21: Role_Master | C21: 9 | D21: 12
A22: 6 | B22: Role_Descriptions | C22: 12 | D22: 10
A23: 7 | B23: Skill_Master | C23: 28 | D23: 12
A24: 8 | B24: Proficiency_Levels | C24: 6 | D24: 5
A25: 9 | B25: Role_Skill_Map | C25: 90 | D25: 15
A26: 10 | B26: Training_Catalogue | C26: 31 | D26: 10
A27: 11 | B27: Training_Skill_Map | C27: 43 | D27: 10
A28: 12 | B28: Assessment_Blueprints | C28: 9 | D28: 14
... A42: 26 | B42: Validation_Checks | C42: 8 | D42: 4

Sheet Source_Analysis
A1: Source Analysis
A3: source_id | B3: source_name | C3: data_used | D3: dataset_usage | E3: notes | F3: source_file | G3: data_label
A4: SRC-01 | B4: R2R role profiles PPT | C4: R2R selected role summaries, responsibilities, outputs, tools and top critical skills | D4: Used for role descriptions and assessment prompt context | E4: Directly supports R2R Banking Preparer, GA Preparer and Consolidation Preparer | F4: R2R_Role_Profiles_ALL43 04 Mar(1).pptx | G4: Source lineage - no employee data
A5: SRC-02 | B5: R2R role-to-skill mapping XLSX | C5: R2R skill dictionary, proficiency indicators and role-to-skill target levels | D5: Used for Skill_Master, Role_Skill_Map and AI question generation | E5: Actual framework structure; no employee data | F5: RTR_Roles_to_Skills_Mapping_Updated_2701.xlsx | G5: Source lineage - no employee data
A6: SRC-03 | B6: AP role profiles PPT | C6: AP/P2P B3/B4 role summaries, outputs and top skills | D6: Used for role descriptions and assessment prompt context | E6: Supports P2P Lead, P2P Senior Associate and T&E Lead | F6: AP_Role_Profiles_18Roles 24Feb(2).pptx | G6: Source lineage - no employee data
A7: SRC-04 | B7: AP roles matrix XLSX | C7: AP skill dictionary, proficiency indicators and role-to-skill target levels | D7: Used for Skill_Master and Role_Skill_Map | E7: Actual framework structure; no employee data | F7: AP_Roles_v1.0_UPDATED_with_Matrix -0128.xlsx | G7: Source lineage - no employee data
A8: SRC-05 | B8: AP/T&E Lead hiring assessment DOCX | C8: 24 case-based MCQs, pass criteria, critical fail rules | D8: Loaded into Assessment_QBank as approved source questions | E8: Used as approved content where available | F8: AP and T&E Lead B4 P4 hiring assessment 30 Mar.docx | G8: Source lineage - no employee data
A9: SRC-06 | B9: P2P Associate JD DOCX | C9: Position summary, responsibilities and qualification/skill cues | D9: Analyzed as reference-only B2 source; not selected for B3/B4 synthetic users | E9: Useful for lower-level assessment expansion | F9: RD044 - P2P Associate 27Mar.docx | G9: Source lineage - no employee data
A10: SRC-07 | B10: O2C role matrix XLSX | C10: O2C skill dictionary, proficiency indicators and role-to-skill target levels | D10: Used for Skill_Master and Role_Skill_Map | E10: Actual framework structure; no employee data | F10: NIQ_O2C_Skills_Dictionary_with_Role_Matrix_Mapped.xlsx | G10: Source lineage - no employee data
A11: SRC-08 | B11: Associate Revenue Controller JD DOCX | C11: Revenue controller role summary, controls, reconciliation and evidence requirements | D11: Used for O2C P4 role context and question generation | E11: P4 specialist included as adjacent to B4 capability layer | F11: Associate Revenue Controller (P4) JD 30Mar.docx | G11: Source lineage - no employee data
A12: SRC-09 | B12: Credit Controller JD DOCX | C12: Collections outreach, case management, dispute routing, SLA and documentation cues | D12: Analyzed as reference-only source | E12: Useful for later B2 expansion | F12: Credit Controller JD 31Mar.docx | G12: Source lineage - no employee data
A13: SRC-10 | B13: Cash Application Associate JD DOCX | C13: Receipt posting, remittance matching, documentation and SLA cues | D13: Analyzed as reference-only source | E13: Useful for later B2 expansion | F13: RD152 - Cash application associate JD 31Mar.docx | G13: Source lineage - no employee data
A14: SRC-11 | B14: Skill Gap Analysis XLSX | C14: Training topics, level groups, risk, capability gaps and training assessment log | D14: Used for Training_Catalogue, Training_Skill_Map and TNI recommendations | E14: Training/TNI structure; no employee data | F14: Skill Gap analysis V1.0.xlsx | G14: Source lineage - no employee data
... A16: SRC-13 | B16: Project SkillPath AI document | C16: Human-in-the-loop, role-skill-learning-evidence-validation design principles | D16: Used for guardrails and architecture framing | E16: Broad SkillPath items kept as roadmap only | F16: Project SkillPath AI.docx | G16: Source lineage - no employee data

Sheet Data_Dictionary
A1: Data Dictionary
A3: sheet_name | B3: field_name | C3: definition | D3: data_classification | E3: notes
A4: README_Architecture | B4: item | C4: Item. | D4: Control / metadata
A5: README_Architecture | B5: details | C5: Details. | D5: Control / metadata
A6: Source_Analysis | B6: source_id | C6: Source id. | D6: Control / metadata
A7: Source_Analysis | B7: source_name | C7: Source name. | D7: Control / metadata
A8: Source_Analysis | B8: data_used | C8: Data used. | D8: Control / metadata
A9: Source_Analysis | B9: dataset_usage | C9: Dataset usage. | D9: Control / metadata
A10: Source_Analysis | B10: notes | C10: Notes. | D10: Control / metadata
A11: Source_Analysis | B11: source_file | C11: Source file. | D11: Control / metadata
A12: Source_Analysis | B12: data_label | C12: Classification label indicating source-derived framework or synthetic hackfest data. | D12: Control / metadata
A13: Role_Master | B13: role_id | C13: Unique role key generated from actual role title. | D13: Actual FinOps Framework Structure - no employee data
A14: Role_Master | B14: data_label | C14: Classification label indicating source-derived framework or synthetic hackfest data. | D14: Actual FinOps Framework Structure - no employee data
A15: Role_Master | B15: tower | C15: Tower. | D15: Actual FinOps Framework Structure - no employee data
... A154: Assessment_Schedules | B154: formula_check_note | C154: Formula check note. | D154: Control / metadata
A155: Users_Teams | B155: user_id | C155: Synthetic user key. No real employee ID. | D155: Synthetic Hackfest Test Data | E155: Do not use for production decisions.
A156: Users_Teams | B156: synthetic_name | C156: Synthetic display name only. | D156: Synthetic Hackfest Test Data | E156: Do not use for production decisions.
A157: Users_Teams | B157: data_label | C157: Classification label indicating source-derived framework or synthetic hackfest data. | D157: Synthetic Hackfest Test Data | E157: Do not use for production decisions.
A158: Users_Teams | B158: tower | C158: Tower. | D158: Synthetic Hackfest Test Data | E158: Do not use for production decisions.
A159: Users_Teams | B159: team_id | C159: Team id. | D159: Synthetic Hackfest Test Data | E159: Do not use for production decisions.
A160: Users_Teams | B160: role_id | C160: Unique role key generated from actual role title. | D160: Synthetic Hackfest Test Data | E160: Do not use for production decisions.
A161: Users_Teams | B161: role_name | C161: Role name. | D161: Synthetic Hackfest Test Data | E161: Do not use for production decisions.
A162: Users_Teams | B162: role_grade | C162: Role grade. | D162: Synthetic Hackfest Test Data | E162: Do not use for production decisions.
A163: Users_Teams | B163: synthetic_manager_id | C163: Synthetic manager id. | D163: Synthetic Hackfest Test Data | E163: Do not use for production decisions.
A164: Users_Teams | B164: cohort | C164: Cohort. | D164: Synthetic Hackfest Test Data | E164: Do not use for production decisions.
A165: Users_Teams | B165: person_data_note | C165: Person data note. | D165: Synthetic Hackfest Test Data | E165: Do not use for production decisions.
A166: Users_Teams | B166: team_name | C166: Team name. | D166: Synthetic Hackfest Test Data | E166: Do not use for production decisions.
... A241: Test_Personas | B241: expected_demo_outcome | C241: Expected demo outcome. | D241: Synthetic Hackfest Test Data | E241: Do not use for production decisions.
A242: MVP_Acceptance | B242: scenario_id | C242: Scenario id. | D242: Control / metadata
A243: MVP_Acceptance | B243: feature | C243: Feature. | D243: Control / metadata
A244: MVP_Acceptance | B244: sheets_used | C244: Sheets used. | D244: Control / metadata
A245: MVP_Acceptance | B245: acceptance_criteria | C245: Acceptance criteria. | D245: Control / metadata
A246: MVP_Acceptance | B246: status | C246: Status. | D246: Control / metadata
A247: Relationship_Map | B247: from_table | C247: From table. | D247: Control / metadata
A248: Relationship_Map | B248: from_field | C248: From field. | D248: Control / metadata
A249: Relationship_Map | B249: relationship | C249: Relationship. | D249: Control / metadata
A250: Relationship_Map | B250: to_table | C250: To table. | D250: Control / metadata
A251: Relationship_Map | B251: to_field | C251: To field. | D251: Control / metadata
A252: Relationship_Map | B252: purpose | C252: Purpose. | D252: Control / metadata
A253: Privacy_RAI | B253: topic | C253: Topic. | D253: Control / metadata
... A263: Validation_Checks | B263: details | C263: Details. | D263: Control / metadata

Sheet Relationship_Map
A1: Relationship Map
A3: from_table | B3: from_field | C3: relationship | D3: to_table | E3: to_field | F3: purpose
A4: Role_Master | B4: role_id | C4: 1-to-many | D4: Role_Skill_Map | E4: role_id | F4: Defines target skills by role
A5: Skill_Master | B5: skill_id | C5: 1-to-many | D5: Role_Skill_Map | E5: skill_id | F5: Provides definition and indicators
A6: Role_Master | B6: role_id | C6: 1-to-many | D6: Assessment_Blueprints | E6: role_id | F6: One blueprint per selected role
A7: Assessment_Blueprints | B7: blueprint_id | C7: 1-to-many | D7: Assessment_QBank | E7: blueprint_id | F7: Questions generated under blueprint
A8: Assessment_QBank | B8: question_id | C8: 1-to-many | D8: SME_Review_Workflow | E8: question_id | F8: SME reviews generated questions
A9: Assessment_Blueprints | B9: blueprint_id | C9: 1-to-many | D9: Assessment_Schedules | E9: blueprint_id | F9: Approved blueprints get scheduled
A10: Assessment_Schedules | B10: schedule_id | C10: 1-to-many | D10: Assessment_Assignments | E10: schedule_id | F10: Synthetic users get assigned
A11: Assessment_Assignments | B11: assignment_id | C11: 1-to-one | D11: Assessment_Results | E11: assignment_id | F11: Attempts create score/result
A12: Assessment_Results | B12: result_id | C12: 1-to-many | D12: User_Skill_Assessments | E12: source_result_id | F12: Score informs skill level recommendation
A13: User_Skill_Assessments | B13: user_skill_assessment_id | C13: 1-to-one | D13: Skill_Gaps_TNI | E13: derived from user+skill | F13: Gap-to-target drives TNI
A14: Training_Catalogue | B14: course_id | C14: 1-to-many | D14: Training_Skill_Map | E14: course_id | F14: Courses mapped to skills
... A16: Users_Teams | B16: user_id | C16: 1-to-many | D16: Assessment_Assignments | E16: user_id | F16: Synthetic cohort assignments

Sheet Role_Master
A1: Role Master
A3: role_id | B3: data_label | C3: tower | D3: process_group | E3: role_name | F3: role_grade | G3: level_group | H3: mvp_use | I3: synthetic_users_per_role | J3: source_role_id | K3: source_file | L3: source_sheet
A4: R2R_banking_preparer_job_preparation_cash_posting | B4: Actual FinOps Framework Structure - no employee data | C4: R2R | D4: Banking | E4: Banking Preparer Job (Preparation + Cash Posting) | F4: B3/B4/P3 | G4: B3/B4 selected | H4: Talent360i assessment blueprint source | I4: 4 | J4: BNK-J1 | K4: RTR_Roles_to_Skills_Mapping_Updated_2701.xlsx | L4: Banking
A5: R2R_ga_preparer_job_preparation_only | B5: Actual FinOps Framework Structure - no employee data | C5: R2R | D5: GA | E5: GA Preparer Job (Preparation-only) | F5: B3/B4/P3 | G5: B3/B4 selected | H5: Talent360i assessment blueprint source | I5: 4 | J5: GA-J1 | K5: RTR_Roles_to_Skills_Mapping_Updated_2701.xlsx | L5: GA
A6: R2R_consolidation_preparer_job_execution_pack_prep | B6: Actual FinOps Framework Structure - no employee data | C6: R2R | D6: Consolidation | E6: Consolidation Preparer Job (Execution + Pack Prep) | F6: P3/P4 | G6: P4 specialist included | H6: Talent360i assessment blueprint source | I6: 4 | J6: CONSOL-J1 | K6: RTR_Roles_to_Skills_Mapping_Updated_2701.xlsx | L6: Consolidation
A7: AP_p2p_lead | B7: Actual FinOps Framework Structure - no employee data | C7: AP | D7: P2P / AP | E7: P2P Lead | F7: B4 | G7: B3/B4 selected | H7: Talent360i assessment blueprint source | I7: 4 | J7: B4 | K7: AP_Roles_v1.0_UPDATED_with_Matrix -0128.xlsx | L7: AP Matrix RolesxSkills
A8: AP_p2p_senior_associate | B8: Actual FinOps Framework Structure - no employee data | C8: AP | D8: P2P / AP | E8: P2P Senior Associate | F8: B3 | G8: B3/B4 selected | H8: Talent360i assessment blueprint source | I8: 4 | J8: B3 | K8: AP_Roles_v1.0_UPDATED_with_Matrix -0128.xlsx | L8: AP Matrix RolesxSkills
A9: AP_t_e_lead | B9: Actual FinOps Framework Structure - no employee data | C9: AP | D9: P2P / AP | E9: T&E Lead | F9: B4 | G9: B3/B4 selected | H9: Talent360i assessment blueprint source | I9: 4 | J9: B4 | K9: AP_Roles_v1.0_UPDATED_with_Matrix -0128.xlsx | L9: AP Matrix RolesxSkills
A10: O2C_billing_team_lead | B10: Actual FinOps Framework Structure - no employee data | C10: O2C | D10: Billing / Revenue / Cash | E10: Billing Team Lead | F10: B4 | G10: B3/B4 selected | H10: Talent360i assessment blueprint source | I10: 4 | J10: B4 | K10: NIQ_O2C_Skills_Dictionary_with_Role_Matrix_Mapped.xlsx | L10: O2C Role Skill Matrix
A11: O2C_associate_revenue_controller | B11: Actual FinOps Framework Structure - no employee data | C11: O2C | D11: Billing / Revenue / Cash | E11: Associate Revenue Controller | F11: P4 | G11: P4 specialist included | H11: Talent360i assessment blueprint source | I11: 4 | J11: P4 | K11: NIQ_O2C_Skills_Dictionary_with_Role_Matrix_Mapped.xlsx | L11: O2C Role Skill Matrix
A12: O2C_senior_revenue_associate | B12: Actual FinOps Framework Structure - no employee data | C12: O2C | D12: Billing / Revenue / Cash | E12: Senior Revenue Associate | F12: B3 | G12: B3/B4 selected | H12: Talent360i assessment blueprint source | I12: 4 | J12: B3 | K12: NIQ_O2C_Skills_Dictionary_with_Role_Matrix_Mapped.xlsx | L12: O2C Role Skill Matrix

Sheet Role_Descriptions
A1: Role Descriptions
A3: role_id | B3: role_name | C3: source_file | D3: source_type | E3: role_summary_or_positioning | F3: responsibility_extract | G3: output_or_success_measure_extract | H3: skills_or_capabilities_extract | I3: selection_status | J3: data_label
A4: R2R_banking_preparer_job_preparation_cash_posting | B4: Banking Preparer Job (Preparation + Cash Posting) | C4: R2R_Role_Profiles_ALL43 04 Mar(1).pptx | D4: Role profile PPT | E4: Executes bank reconciliations end-to-end, ensuring bank-to-GL matching is accurate, reconciling items are identified and supported, and reconciliations are completed on time with clean evidence in line with RTR banking SOPs. | F4: Perform daily/periodic bank-to-GL reconciliations; identify and document reconciling items; execute SOP-compliant cash postings/clearing with evidence; maintain open-item aging and escalate blockers. | G4: On-time bank reconciliations; traceable SOX/IPE evidence; reduced aged reconciling items; improved cash integrity and close readiness. | H4: Reconciliations & Clearing; First Time Right; Fixed Assets & Banking / cash context; Time Management; Productivity Tools; Attention to Detail; Controls / Compliance / Audit; ERP / Finance Tools. | I4: Selected for B3/B4/P4 Hackfest test data | J4: Source-derived role context - no employee data
A5: R2R_ga_preparer_job_preparation_only | B5: GA Preparer Job (Preparation-only) | C5: R2R_Role_Profiles_ALL43 04 Mar(1).pptx | D5: Role profile PPT | E5: Executes end-to-end General Accounting activities including journal entry preparation and balance sheet reconciliations with SOX/IPE-compliant evidence aligned to NIQ SOPs and OneStream governance. | F5: Post accruals/reclasses with correct coding, support and approvals; prepare OneStream balance sheet reconciliations; evidence balances and resolve ageing items. | G5: Accurate close execution; clean journal entries; complete reconciliable balance sheet accounts; reduced aged recon items; audit-ready documentation. | H5: Attention to Detail; Reconciliations & Clearing; SLA / Governance / Metrics; Productivity Tools; ERP / Finance Tools; First Time Right; R2R Close & Journals. | I5: Selected for B3/B4/P4 Hackfest test data | J5: Source-derived role context - no employee data
A6: R2R_consolidation_preparer_job_execution_pack_prep | B6: Consolidation Preparer Job (Execution + Pack Prep) | C6: R2R_Role_Profiles_ALL43 04 Mar(1).pptx | D6: Role profile PPT | E6: Executes end-to-end consolidation cycle activities, ensuring entity submissions, eliminations, adjustments, FX translation, system loads and group reporting packs are accurate, complete and supported by SOX/IPE evidence under OneStream governance. | F6: Track entity submissions; manage eliminations, FX translation and system loads; validate balances, mappings and tie-outs; prepare group reporting packs. | G6: Entity submission tracker; elimination and adjustment support; FX translation evidence; load validation logs; group reporting pack; SOX/IPE evidence pack. | H6: Attention to Detail; Reconciliations & Clearing; Financial Reporting; Consolidation; SLA / Governance / Metrics; Productivity Tools; ERP / Finance Tools. | I6: Selected for B3/B4/P4 Hackfest test data | J6: Source-derived role context - no employee data
A7: AP_p2p_lead | B7: P2P Lead | C7: AP_Role_Profiles_18Roles 24Feb(2).pptx | D7: Role profile PPT | E7: Team-level execution ownership and first-line control for invoice processing and payment execution within assigned region/scope. | F7: Own AP invoice processing and payment execution; allocate work and manage queues; resolve exceptions; ensure 3-way match, GR/IR and month-end readiness; ensure controls, SOX compliance and accurate SAP execution. | G7: Queue allocation reports; exception resolution logs; RCA documentation; month-end readiness checklist; SLA/KPI dashboard. | H7: PO-Based Invoice Processing; Non-PO Invoice Processing; 3-Way Match; Payment Processing; Month-End Support; SLA / Metrics / Reporting; Controls / SOX / Audit Support; Queue Allocation; RCA; Stakeholder Communication. | I7: Selected for B3/B4/P4 Hackfest test data | J7: Source-derived role context - no employee data
A8: AP_p2p_senior_associate | B8: P2P Senior Associate | C8: AP_Role_Profiles_18Roles 24Feb(2).pptx | D8: Role profile PPT | E8: Accurate and timely execution of AP invoice processing with strong exception handling and compliance adherence. | F8: Process PO and Non-PO invoices in SAP; validate tax, compliance and approvals; resolve holds/exceptions; support GR/IR and open-item follow-ups; support month-end processing. | G8: Invoice productivity and accuracy metrics; exception resolution log; GR/IR follow-up tracker; approval evidence pack; aging reduction proof. | H8: 3-Way Match & Exception Governance; Payments Execution Oversight; AP Reconciliations; Controls / Compliance / Audit Readiness; SLA / Governance / Metrics; Work Intake & Prioritization; RCA / CAPA; Stakeholder Management. | I8: Selected for B3/B4/P4 Hackfest test data | J8: Source-derived role context - no employee data
A9: AP_t_e_lead | B9: T&E Lead | C9: AP_Role_Profiles_18Roles 24Feb(2).pptx | D9: Role profile PPT | E9: Leads day-to-day execution and control of T&E and P-Card operations, ensuring queue management, resolution of complex claims and exceptions, policy compliance, audit readiness and SLA/KPI performance. | F9: Lead daily T&E and P-Card operations; resolve complex claims and exceptions; coordinate across teams and stakeholders; drive audit readiness and SLA/KPI performance. | G9: T&E queue health reports; exception/violation logs; claims aging and TAT reports; policy compliance and audit check results; month-end checklists. | H9: End-to-end T&E operations ownership; complex exception management; policy enforcement; SLA/KPI performance; stakeholder coordination; audit and close support; continuous improvement; T&E systems expertise. | I9: Selected for B3/B4/P4 Hackfest test data | J9: Source-derived role context - no employee data
A10: O2C_associate_revenue_controller | B10: Associate Revenue Controller | C10: Associate Revenue Controller (P4) JD 30Mar.docx | D10: JD DOCX | E10: The Associate Revenue Controller provides specialist support for revenue and billing accuracy by executing targeted control and assurance activities across billing-to-revenue processes. This role focuses on reviewing high-risk transactions, validating billing rules, supporting reconciliations, and ensuring audit readiness through strong documentation and evidence discipline. The role plays a key part in maintaining control effectiveness by identifying exceptions, supporting investigations, and contributing to improved process compliance and financial accuracy. | F10: High-Risk Item Review & Validation; Review high-risk billing and revenue items against contracts, policies, and SOPs; Validate billing rules, pricing logic, and revenue recognition alignment; Identify discrepancies and escalate issues for resolution; Ensure accuracy and compliance in transaction processing; Control Checks & Assurance Support; Perform billing-to-revenue and first-line control checks; Support execution of control activities across O2C processes; Validate adherence to defined control frameworks; Assist in monitoring control effectiveness | G10: Accurate control check evidence and validation results; High-quality reconciliation support and variance explanations; Risk and exception reports with actionable insights; Complete and audit-ready documentation (PBC packs, evidence folders); Effective tracking of control breaches and resolution status; Strong adherence to SOPs and control frameworks; Improved accuracy and reduced high-risk errors; Key Stakeholders; Internal; Sales / Commercial | H10: Basic to intermediate understanding of revenue and billing processes; Knowledge of control frameworks and compliance requirements; Strong analytical and attention-to-detail skills; Ability to review transactions and identify discrepancies; Good understanding of reconciliations and financial data; Digital fluency (ERP systems, Excel, reporting tools); Strong documentation and organizational skills; Effective communication and coordination skills; Qualifications & Experience; –4 years of experience in finance operations, billing, or revenue processes | I10: Selected for B3/B4/P4 Hackfest test data | J10: Source-derived role context - no employee data
A11: O2C_senior_revenue_associate | B11: Senior Revenue Associate | C11: NIQ_O2C_Skills_Dictionary_with_Role_Matrix_Mapped.xlsx | D11: Role matrix XLSX | E11: Senior Revenue Associate role selected from O2C role-skill matrix as a B3 revenue role. No separate JD was provided in this upload; role-skill expectations are taken from the O2C role matrix and skill dictionary. | F11: Use O2C matrix target skills for billing, revenue assurance, compliance, close/reporting, ownership and delivery. | G11: Assessment blueprint validates role-level O2C skills mapped in the source matrix. | H11: O2C role-skill matrix and skill dictionary. | I11: Selected for B3/B4 Hackfest test data - JD not in attachments | J11: Source-derived role context - no employee data
A12: O2C_billing_team_lead | B12: Billing Team Lead | C12: NIQ_O2C_Skills_Dictionary_with_Role_Matrix_Mapped.xlsx | D12: Role matrix XLSX | E12: Billing Team Lead role selected from O2C role-skill matrix as a B4 role. No separate JD was provided in this upload; role-skill expectations are taken from the O2C role matrix and skill dictionary. | F12: Use O2C matrix target skills for order validation, billing setup, invoicing, credit notes, revenue controls, compliance and team-level delivery. | G12: Assessment blueprint validates billing/revenue operations skills mapped in the source matrix. | H12: O2C role-skill matrix and skill dictionary. | I12: Selected for B3/B4 Hackfest test data - JD not in attachments | J12: Source-derived role context - no employee data
A13: REF_p2p_associate | B13: P2P Associate | C13: RD044 - P2P Associate 27Mar.docx | D13: JD DOCX | E13: The P2P Associate is responsible for executing day-to-day invoice processing activities with accuracy and timeliness, following defined SOPs and internal controls within the Accounts Payable function. | F13: Process PO and Non-PO invoices in ERP systems (e.g., SAP); Perform basic 3-way matching (PO, invoice, GR); Validate invoice details including tax, coding, and approvals; Route invoices for approval and follow up on pending items; Maintain accurate documentation and audit trail; Monitor assigned queues and ensure SLA adherence; Support payment runs with required inputs; Escalate exceptions or complex discrepancies | H13: –3 years experience in AP / Invoice Processing; Basic knowledge of invoice lifecycle and controls; Familiarity with SAP / ERP systems; High attention to detail and accuracy | I13: Reference-only JD analyzed; not part of selected B3/B4 synthetic user cohort | J13: Source-derived role context - no employee data
A14: REF_credit_controller | B14: Credit Controller | C14: Credit Controller JD 31Mar.docx | D14: JD DOCX | E14: The Credit Controller is responsible for executing standard collections activities, including dunning and customer outreach, while maintaining accurate case documentation and ensuring adherence to Cash Collection SOPs and SLAs. This role focuses on transactional execution, including follow-ups, case updates, and routing disputes and escalations to appropriate teams. It plays a key role in maintaining process discipline, documentation accuracy, and timely completion of collection activities. | F14: Dunning & Outreach Execution; Execute collections activities including:; Calls; Emails; Letters; Follow defined scripts, cadence, and communication guidelines; Ensure timely follow-ups based on aging and priority; Case Management & Documentation; Update case notes promptly and accurately in collections systems/ERP; Maintain detailed records of: | G14: Completed collections activities (calls, emails, outreach logs); Accurate and up-to-date case notes and customer contact history; Properly routed disputes with complete information; Timely escalations based on defined triggers; SLA adherence (follow-ups, routing, completion rate); Complete audit trail and documentation; Reduced rework through accurate execution; Key Stakeholders; Internal; Sales / Commercial | H14: Basic understanding of collections and receivables processes; Strong attention to detail and documentation discipline; Ability to follow SOPs and structured workflows; Good communication skills for customer interaction; Ability to manage repetitive tasks with accuracy; Basic analytical skills (identifying issues and exceptions); Digital fluency (ERP systems, collections tools, Excel); Time management and prioritization skills; Qualifications & Experience; –3 years of experience in collections, customer service, or finance operations | I14: Reference-only JD analyzed; not part of selected B3/B4 synthetic user cohort | J14: Source-derived role context - no employee data
A15: REF_cash_application_associate | B15: Cash Application Associate | C15: RD152 - Cash application associate JD 31Mar.docx | D15: JD DOCX | E15: The Cash Application Associate is responsible for executing transaction processing activities related to cash posting, including accurate and timely posting of receipts, remittance matching, and maintaining complete audit trail documentation in line with Cash Application SOPs. The role focuses on execution accuracy, adherence to work instructions, and timely completion of tasks while supporting reconciliation activities and escalation of mismatches. This refines the current JD by positioning the role as transaction execution + matching + documentation, rather than investigation or process ownership. | F15: Receipt Posting & Processing; Post client receipts accurately in ERP systems as per work instructions; Ensure timely processing of payments across bank accounts; Follow defined procedures for transaction processing; Maintain accuracy and completeness of postings; Remittance Matching; Match remittances to invoices with correct allocation; Ensure supporting documentation is complete and accurate; Identify unmatched or partially matched items; Follow defined rules for allocation and matching | G15: Completed postings with daily throughput targets met; High accuracy in receipt application and matching; Clean audit trail (documentation attached and traceable); Reduced unapplied/on-account cash; Proper escalation logs with complete evidence; Bank reconciliation support logs; Strong SLA adherence for posting and matching; Key Stakeholders; Internal; Sales / Commercial | H15: Basic understanding of cash application and AR processes; Strong attention to detail and accuracy; Ability to follow SOPs and structured workflows; Basic analytical skills (identifying mismatches); Digital fluency (ERP systems, Excel); Strong documentation discipline; Ability to manage repetitive tasks efficiently; Good time management and prioritization skills; Qualifications & Experience; –2 years of experience in finance operations, AR, or data processing roles | I15: Reference-only JD analyzed; not part of selected B3/B4 synthetic user cohort | J15: Source-derived role context - no employee data

Sheet Skill_Master
A1: Skill Master
A3: skill_id | B3: data_label | C3: tower | D3: skill | E3: capability | F3: L1_indicator | G3: L2_indicator | H3: L3_indicator | I3: L4_indicator | J3: L5_indicator | K3: source_file | L3: source_sheet
A4: AP_first_time_right_quality | B4: Actual FinOps Framework Structure - no employee data | C4: AP | D4: First Time Right (Quality) | E4: Technical Expertise | F4: Basic understanding of AP quality requirements; follows checklists and review steps with guidance. | G4: Applies self-checks (coding, approvals, attachments); reduces repeat errors; flags recurring defects. | H4: Independently delivers right-first-time processing; prevents defects; improves rework and rejection rates. | I4: Consulted for quality issues; designs quality gates and sampling checks; mentors others. | J4: Strategic authority on AP quality standards; sets enterprise quality measures and drives quality culture. | K4: AP_Roles_v1.0_UPDATED_with_Matrix -0128.xlsx | L4: Skills Dictionary
A5: AP_invoice_processing_po_non_po | B5: Actual FinOps Framework Structure - no employee data | C5: AP | D5: Invoice Processing (PO & Non-PO) | E5: Technical Expertise | F5: Familiarity with invoice capture and required fields; processes simple invoices under review. | G5: Performs standard PO/non-PO invoice processing; routes for approval; follows coding standards. | H5: Independently resolves exceptions (price/qty/GR issues); optimizes cycle time; ensures accurate postings. | I5: Go-to for complex invoice scenarios; standardizes handling rules; trains team on exception playbooks. | J5: Defines enterprise invoice processing strategy (standardization, e-invoicing); drives outcomes at scale. | K5: AP_Roles_v1.0_UPDATED_with_Matrix -0128.xlsx | L5: Skills Dictionary
A6: AP_3_way_match_exception_handling | B6: Actual FinOps Framework Structure - no employee data | C6: AP | D6: 3-Way Match & Exception Handling | E6: Technical Expertise | F6: Understands basic match concepts; escalates mismatches per SOP. | G6: Performs routine exception resolution with guidance; documents reasons and actions. | H6: Independently investigates match breaks; coordinates with Procurement/Receiving; closes root causes. | I6: Consulted for complex match disputes; sets exception thresholds and best practices. | J6: Sets enterprise match policy and governance; drives upstream process fixes and supplier compliance. | K6: AP_Roles_v1.0_UPDATED_with_Matrix -0128.xlsx | L6: Skills Dictionary
A7: AP_payments_execution_runs_methods | B7: Actual FinOps Framework Structure - no employee data | C7: AP | D7: Payments Execution (Runs/Methods) | E7: Technical Expertise | F7: Familiarity with payment methods and calendar; supports run preparation with guidance. | G7: Executes standard payment run steps; validates batches; follows approvals and controls. | H7: Independently manages payment execution; resolves payment failures; ensures on-time, accurate disbursements. | I7: Go-to for payment issues and bank file exceptions; strengthens controls; mentors others. | J7: Defines enterprise payments strategy (controls, bank connectivity, fraud prevention) and performance. | K7: AP_Roles_v1.0_UPDATED_with_Matrix -0128.xlsx | L7: Skills Dictionary
A8: AP_t_e_p_card_audit_compliance | B8: Actual FinOps Framework Structure - no employee data | C8: AP | D8: T&E / P-Card Audit & Compliance | E8: Technical Expertise | F8: Understands basic policy rules; reviews simple claims/transactions with guidance. | G8: Applies policy checks (receipts, limits, categories); flags non-compliance; supports employee queries. | H8: Independently audits complex claims; identifies patterns of misuse; recommends corrective actions. | I8: Consulted for sensitive/escalated cases; improves policy controls and training; coaches approvers. | J8: Shapes enterprise T&E/P-card compliance strategy; drives governance and risk posture. | K8: AP_Roles_v1.0_UPDATED_with_Matrix -0128.xlsx | L8: Skills Dictionary
A9: AP_tax_withholding_regulatory_basics | B9: Actual FinOps Framework Structure - no employee data | C9: AP | D9: Tax / Withholding & Regulatory Basics | E9: Technical Expertise | F9: Familiarity with VAT/GST/withholding concepts; follows standard coding guidance. | G9: Applies standard tax codes; identifies missing tax data; escalates exceptions. | H9: Independently validates tax treatment for non-routine invoices; partners with Tax/Finance for resolution. | I9: Recognized specialist; sets tax coding guidance and controls; trains team on common risks. | J9: Defines enterprise AP tax compliance approach; influences policy and system configuration. | K9: AP_Roles_v1.0_UPDATED_with_Matrix -0128.xlsx | L9: Skills Dictionary
A10: AP_ap_reconciliations_subledger_gl_vendor_statements | B10: Actual FinOps Framework Structure - no employee data | C10: AP | D10: AP Reconciliations (Subledger/GL, Vendor Statements) | E10: Technical Expertise | F10: Understands reconciliation purpose; supports data gathering under guidance. | G10: Completes standard reconciliations (subledger to GL, vendor statement) using templates; documents variances. | H10: Independently resolves discrepancies; improves reconciliation quality and cycle time; maintains evidence trail. | I10: Consulted for complex recon issues; sets reconciliation standards; mentors others. | J10: Defines enterprise reconciliation approach for AP; drives control effectiveness and audit readiness. | K10: AP_Roles_v1.0_UPDATED_with_Matrix -0128.xlsx | L10: Skills Dictionary
A11: AP_close_activities_accruals_cutoff_gr_ir | B11: Actual FinOps Framework Structure - no employee data | C11: AP | D11: Close Activities (Accruals, Cutoff, GR/IR) | E11: Technical Expertise | F11: Aware of month-end timelines; supports accrual inputs with guidance. | G11: Performs standard cutoff checks and accrual preparation using SOPs; escalates anomalies. | H11: Independently manages AP close tasks; resolves GR/IR and cutoff issues; improves timeliness. | I11: Go-to for close challenges; standardizes close playbooks and controls; trains teams. | J11: Defines enterprise AP close strategy and cadence; drives close performance across regions. | K11: AP_Roles_v1.0_UPDATED_with_Matrix -0128.xlsx | L11: Skills Dictionary
A12: AP_controls_compliance_audit_ap | B12: Actual FinOps Framework Structure - no employee data | C12: AP | D12: Controls / Compliance / Audit (AP) | E12: Technical Expertise | F12: Familiarity with control requirements (SoD, approvals); follows evidence rules with guidance. | G12: Executes assigned controls; retains evidence; supports audit requests using standard packs. | H12: Independently owns control execution; explains evidence; supports remediation and prevention actions. | I12: Consulted for control design and audit readiness; strengthens control framework; mentors others. | J12: Defines enterprise AP control strategy; leads major remediation and audit outcomes. | K12: AP_Roles_v1.0_UPDATED_with_Matrix -0128.xlsx | L12: Skills Dictionary
A13: AP_ownership_delivery | B13: Actual FinOps Framework Structure - no employee data | C13: AP | D13: Ownership & Delivery | E13: Process Governance | F13: Understands tasks and deadlines; delivers with support; escalates when instructed. | G13: Owns end-to-end tasks; meets deadlines; escalates risks/issues early with context. | H13: Independently owns outcomes; manages exceptions and handoffs; accountable for results. | I13: Leads delivery across teams; builds routines and resilience; balances priorities at scale. | J13: Sets delivery model and accountability; drives enterprise performance and operating rhythm. | K13: AP_Roles_v1.0_UPDATED_with_Matrix -0128.xlsx | L13: Skills Dictionary
A14: AP_sla_governance_metrics | B14: Actual FinOps Framework Structure - no employee data | C14: AP | D14: SLA / Governance / Metrics | E14: Process Governance | F14: Aware of SLAs/KPIs (cycle time, backlog); updates trackers as instructed. | G14: Tracks SLAs and productivity; reports status; supports governance routines. | H14: Independently monitors KPIs; drives actions to recover SLA/backlog; improves reporting. | I14: Designs governance cadence; leads performance reviews; improves metric definitions and actions. | J14: Defines enterprise governance model and KPI strategy; drives performance accountability. | K14: AP_Roles_v1.0_UPDATED_with_Matrix -0128.xlsx | L14: Skills Dictionary
... A31: O2C_communication_skills | B31: Actual FinOps Framework Structure - no employee data | C31: O2C | D31: Communication Skills | E31: Stakeholder Influence | F31: Clear written/verbal updates in routine situations; uses standard templates. | G31: Produces structured updates; escalates clearly with context; tailors messages to audience. | H31: Independently communicates complex issues/decisions; influences outcomes with clarity. | I31: Leads communication in escalations; coaches others; improves comms standards. | J31: Shapes enterprise narrative; influences decisions through communication; represents function credibly. | K31: NIQ_O2C_Skills_Dictionary_with_Role_Matrix_Mapped.xlsx | L31: Skills Dictionary

Sheet Proficiency_Levels
A1: Proficiency Levels
A3: level | B3: level_name | C3: behavior_indicator | D3: assessment_design_interpretation | E3: source_mapping
A4: 0 | B4: Not assessed / not required | C4: No assessment yet or role does not require the skill | D4: Do not generate role-level assessment unless requested | E4: Capability360 uses a shared 6-level taxonomy; FinOps matrices use L1-L5. Level 0 added only for not-required/not-assessed states.
A5: 1 | B5: Awareness | C5: Understands the purpose and basic concepts; needs close guidance | D5: AI questions validate recognition and basic concept understanding | E5: Capability360 uses a shared 6-level taxonomy; FinOps matrices use L1-L5. Level 0 added only for not-required/not-assessed states.
A6: 2 | B6: Working Knowledge | C6: Performs standard tasks using SOPs with some guidance | D6: AI questions validate routine application and escalation understanding | E6: Capability360 uses a shared 6-level taxonomy; FinOps matrices use L1-L5. Level 0 added only for not-required/not-assessed states.
A7: 3 | B7: Proficient | C7: Works independently for standard and moderately complex scenarios | D7: AI questions validate role-ready judgment and control adherence | E7: Capability360 uses a shared 6-level taxonomy; FinOps matrices use L1-L5. Level 0 added only for not-required/not-assessed states.
A8: 4 | B8: Advanced | C8: Handles complex cases, mentors peers and improves practices | D8: AI questions validate complex scenario judgment and root-cause thinking | E8: Capability360 uses a shared 6-level taxonomy; FinOps matrices use L1-L5. Level 0 added only for not-required/not-assessed states.
A9: 5 | B9: Expert / Strategic | C9: Sets standards, governs outcomes and resolves enterprise risks | D9: AI questions validate policy design, governance and strategic decision-making | E9: Capability360 uses a shared 6-level taxonomy; FinOps matrices use L1-L5. Level 0 added only for not-required/not-assessed states.

Sheet Role_Skill_Map
A1: Role Skill Map
A3: role_skill_id | B3: data_label | C3: tower | D3: process_group | E3: role_id | F3: role_name | G3: role_grade | H3: skill_id | I3: skill | J3: capability | K3: target_proficiency_level | L3: target_band | M3: behavior_indicator | N3: source_file | O3: source_sheet
A4: RSM-0001 | B4: Actual FinOps Framework Structure - no employee data | C4: AP | D4: P2P / AP | E4: AP_p2p_lead | F4: P2P Lead | G4: B4 | H4: AP_first_time_right_quality | I4: First Time Right (Quality) | J4: Technical Expertise | K4: 3 | L4: Intermediate | M4: Independently delivers right-first-time processing; prevents defects; improves rework and rejection rates. | N4: AP_Roles_v1.0_UPDATED_with_Matrix -0128.xlsx | O4: AP Matrix RolesxSkills
A5: RSM-0002 | B5: Actual FinOps Framework Structure - no employee data | C5: AP | D5: P2P / AP | E5: AP_p2p_lead | F5: P2P Lead | G5: B4 | H5: AP_invoice_processing_po_non_po | I5: Invoice Processing (PO & Non-PO) | J5: Technical Expertise | K5: 3 | L5: Intermediate | M5: Independently resolves exceptions (price/qty/GR issues); optimizes cycle time; ensures accurate postings. | N5: AP_Roles_v1.0_UPDATED_with_Matrix -0128.xlsx | O5: AP Matrix RolesxSkills
A6: RSM-0003 | B6: Actual FinOps Framework Structure - no employee data | C6: AP | D6: P2P / AP | E6: AP_p2p_lead | F6: P2P Lead | G6: B4 | H6: AP_3_way_match_exception_handling | I6: 3-Way Match & Exception Handling | J6: Technical Expertise | K6: 3 | L6: Intermediate | M6: Independently investigates match breaks; coordinates with Procurement/Receiving; closes root causes. | N6: AP_Roles_v1.0_UPDATED_with_Matrix -0128.xlsx | O6: AP Matrix RolesxSkills
A7: RSM-0004 | B7: Actual FinOps Framework Structure - no employee data | C7: AP | D7: P2P / AP | E7: AP_p2p_lead | F7: P2P Lead | G7: B4 | H7: AP_payments_execution_runs_methods | I7: Payments Execution (Runs/Methods) | J7: Technical Expertise | K7: 3 | L7: Intermediate | M7: Independently manages payment execution; resolves payment failures; ensures on-time, accurate disbursements. | N7: AP_Roles_v1.0_UPDATED_with_Matrix -0128.xlsx | O7: AP Matrix RolesxSkills
A8: RSM-0005 | B8: Actual FinOps Framework Structure - no employee data | C8: AP | D8: P2P / AP | E8: AP_p2p_lead | F8: P2P Lead | G8: B4 | H8: AP_tax_withholding_regulatory_basics | I8: Tax / Withholding & Regulatory Basics | J8: Technical Expertise | K8: 3 | L8: Intermediate | M8: Independently validates tax treatment for non-routine invoices; partners with Tax/Finance for resolution. | N8: AP_Roles_v1.0_UPDATED_with_Matrix -0128.xlsx | O8: AP Matrix RolesxSkills
A9: RSM-0006 | B9: Actual FinOps Framework Structure - no employee data | C9: AP | D9: P2P / AP | E9: AP_p2p_lead | F9: P2P Lead | G9: B4 | H9: AP_ap_reconciliations_subledger_gl_vendor_statements | I9: AP Reconciliations (Subledger/GL, Vendor Statements) | J9: Technical Expertise | K9: 3 | L9: Intermediate | M9: Independently resolves discrepancies; improves reconciliation quality and cycle time; maintains evidence trail. | N9: AP_Roles_v1.0_UPDATED_with_Matrix -0128.xlsx | O9: AP Matrix RolesxSkills
A10: RSM-0007 | B10: Actual FinOps Framework Structure - no employee data | C10: AP | D10: P2P / AP | E10: AP_p2p_lead | F10: P2P Lead | G10: B4 | H10: AP_close_activities_accruals_cutoff_gr_ir | I10: Close Activities (Accruals, Cutoff, GR/IR) | J10: Technical Expertise | K10: 3 | L10: Intermediate | M10: Independently manages AP close tasks; resolves GR/IR and cutoff issues; improves timeliness. | N10: AP_Roles_v1.0_UPDATED_with_Matrix -0128.xlsx | O10: AP Matrix RolesxSkills
A11: RSM-0008 | B11: Actual FinOps Framework Structure - no employee data | C11: AP | D11: P2P / AP | E11: AP_p2p_lead | F11: P2P Lead | G11: B4 | H11: AP_controls_compliance_audit_ap | I11: Controls / Compliance / Audit (AP) | J11: Technical Expertise | K11: 3 | L11: Intermediate | M11: Independently owns control execution; explains evidence; supports remediation and prevention actions. | N11: AP_Roles_v1.0_UPDATED_with_Matrix -0128.xlsx | O11: AP Matrix RolesxSkills
A12: RSM-0009 | B12: Actual FinOps Framework Structure - no employee data | C12: AP | D12: P2P / AP | E12: AP_p2p_lead | F12: P2P Lead | G12: B4 | H12: AP_ownership_delivery | I12: Ownership & Delivery | J12: Process Governance | K12: 3 | L12: Intermediate | M12: Independently owns outcomes; manages exceptions and handoffs; accountable for results. | N12: AP_Roles_v1.0_UPDATED_with_Matrix -0128.xlsx | O12: AP Matrix RolesxSkills
A13: RSM-0010 | B13: Actual FinOps Framework Structure - no employee data | C13: AP | D13: P2P / AP | E13: AP_p2p_lead | F13: P2P Lead | G13: B4 | H13: AP_sla_governance_metrics | I13: SLA / Governance / Metrics | J13: Process Governance | K13: 3 | L13: Intermediate | M13: Independently monitors KPIs; drives actions to recover SLA/backlog; improves reporting. | N13: AP_Roles_v1.0_UPDATED_with_Matrix -0128.xlsx | O13: AP Matrix RolesxSkills
A14: RSM-0011 | B14: Actual FinOps Framework Structure - no employee data | C14: AP | D14: P2P / AP | E14: AP_p2p_senior_associate | F14: P2P Senior Associate | G14: B3 | H14: AP_first_time_right_quality | I14: First Time Right (Quality) | J14: Technical Expertise | K14: 3 | L14: Intermediate | M14: Independently delivers right-first-time processing; prevents defects; improves rework and rejection rates. | N14: AP_Roles_v1.0_UPDATED_with_Matrix -0128.xlsx | O14: AP Matrix RolesxSkills
A15: RSM-0012 | B15: Actual FinOps Framework Structure - no employee data | C15: AP | D15: P2P / AP | E15: AP_p2p_senior_associate | F15: P2P Senior Associate | G15: B3 | H15: AP_invoice_processing_po_non_po | I15: Invoice Processing (PO & Non-PO) | J15: Technical Expertise | K15: 3 | L15: Intermediate | M15: Independently resolves exceptions (price/qty/GR issues); optimizes cycle time; ensures accurate postings. | N15: AP_Roles_v1.0_UPDATED_with_Matrix -0128.xlsx | O15: AP Matrix RolesxSkills
... A63: RSM-0060 | B63: Actual FinOps Framework Structure - no employee data | C63: O2C | D63: Billing / Revenue / Cash | E63: O2C_senior_revenue_associate | F63: Senior Revenue Associate | G63: B3 | H63: O2C_communication_skills | I63: Communication Skills | J63: Stakeholder Influence | K63: 3 | L63: Intermediate | M63: Independently communicates complex issues/decisions; influences outcomes with clarity. | N63: NIQ_O2C_Skills_Dictionary_with_Role_Matrix_Mapped.xlsx | O63: O2C Role Skill Matrix
A64: RSM-0061 | B64: Actual FinOps Framework Structure - no employee data | C64: R2R | D64: Banking | E64: R2R_banking_preparer_job_preparation_cash_posting | F64: Banking Preparer Job (Preparation + Cash Posting) | G64: B3/B4/P3 | H64: R2R_first_time_right_quality_sox_icfr_ready | I64: First Time Right (Quality, SOX/ICFR-ready) | K64: 3 | L64: Intermediate | N64: RTR_Roles_to_Skills_Mapping_Updated_2701.xlsx | O64: Banking
A65: RSM-0062 | B65: Actual FinOps Framework Structure - no employee data | C65: R2R | D65: Banking | E65: R2R_banking_preparer_job_preparation_cash_posting | F65: Banking Preparer Job (Preparation + Cash Posting) | G65: B3/B4/P3 | H65: R2R_attention_to_detail_sox_evidence_trail_documentation | I65: Attention to Detail (SOX evidence trail / documentation) | K65: 4 | L65: Advanced | N65: RTR_Roles_to_Skills_Mapping_Updated_2701.xlsx | O65: Banking
A66: RSM-0063 | B66: Actual FinOps Framework Structure - no employee data | C66: R2R | D66: Banking | E66: R2R_banking_preparer_job_preparation_cash_posting | F66: Banking Preparer Job (Preparation + Cash Posting) | G66: B3/B4/P3 | H66: R2R_r2r_close_journals_us_gaap_ifrs | I66: R2R Close & Journals (US GAAP / IFRS) | K66: 3 | L66: Intermediate | N66: RTR_Roles_to_Skills_Mapping_Updated_2701.xlsx | O66: Banking
A67: RSM-0064 | B67: Actual FinOps Framework Structure - no employee data | C67: R2R | D67: Banking | E67: R2R_banking_preparer_job_preparation_cash_posting | F67: Banking Preparer Job (Preparation + Cash Posting) | G67: B3/B4/P3 | H67: R2R_reconciliations_clearing_sox_ipe_balance_sheet_recs | I67: Reconciliations & Clearing (SOX/IPE balance sheet recs) | K67: 4 | L67: Advanced | N67: RTR_Roles_to_Skills_Mapping_Updated_2701.xlsx | O67: Banking
A68: RSM-0065 | B68: Actual FinOps Framework Structure - no employee data | C68: R2R | D68: Banking | E68: R2R_banking_preparer_job_preparation_cash_posting | F68: Banking Preparer Job (Preparation + Cash Posting) | G68: B3/B4/P3 | H68: R2R_fixed_assets_banking_ias_16_ias_36_asc_360 | I68: Fixed Assets & Banking (IAS 16 / IAS 36 / ASC 360) | K68: 3 | L68: Intermediate | N68: RTR_Roles_to_Skills_Mapping_Updated_2701.xlsx | O68: Banking
A69: RSM-0066 | B69: Actual FinOps Framework Structure - no employee data | C69: R2R | D69: Banking | E69: R2R_banking_preparer_job_preparation_cash_posting | F69: Banking Preparer Job (Preparation + Cash Posting) | G69: B3/B4/P3 | H69: R2R_time_management | I69: Time Management | K69: 4 | L69: Advanced | N69: RTR_Roles_to_Skills_Mapping_Updated_2701.xlsx | O69: Banking
A70: RSM-0067 | B70: Actual FinOps Framework Structure - no employee data | C70: R2R | D70: Banking | E70: R2R_banking_preparer_job_preparation_cash_posting | F70: Banking Preparer Job (Preparation + Cash Posting) | G70: B3/B4/P3 | H70: R2R_productivity_tools_excel_ppt | I70: Productivity Tools (Excel/PPT) | K70: 4 | L70: Advanced | N70: RTR_Roles_to_Skills_Mapping_Updated_2701.xlsx | O70: Banking
A71: RSM-0068 | B71: Actual FinOps Framework Structure - no employee data | C71: R2R | D71: Banking | E71: R2R_banking_preparer_job_preparation_cash_posting | F71: Banking Preparer Job (Preparation + Cash Posting) | G71: B3/B4/P3 | H71: R2R_erp_finance_tools_sap_oracle_blackline_onestream_sox_controls_in_systems | I71: ERP / Finance Tools (SAP/Oracle/BlackLine/OneStream) (SOX controls-in-systems) | K71: 4 | L71: Advanced | N71: RTR_Roles_to_Skills_Mapping_Updated_2701.xlsx | O71: Banking
A72: RSM-0069 | B72: Actual FinOps Framework Structure - no employee data | C72: R2R | D72: Banking | E72: R2R_banking_preparer_job_preparation_cash_posting | F72: Banking Preparer Job (Preparation + Cash Posting) | G72: B3/B4/P3 | H72: R2R_professional_conduct | I72: Professional Conduct | K72: 4 | L72: Advanced | N72: RTR_Roles_to_Skills_Mapping_Updated_2701.xlsx | O72: Banking
A73: RSM-0070 | B73: Actual FinOps Framework Structure - no employee data | C73: R2R | D73: Banking | E73: R2R_banking_preparer_job_preparation_cash_posting | F73: Banking Preparer Job (Preparation + Cash Posting) | G73: B3/B4/P3 | H73: R2R_teamwork_collaboration | I73: Teamwork / Collaboration | K73: 4 | L73: Advanced | N73: RTR_Roles_to_Skills_Mapping_Updated_2701.xlsx | O73: Banking
A74: RSM-0071 | B74: Actual FinOps Framework Structure - no employee data | C74: R2R | D74: Consolidation | E74: R2R_consolidation_preparer_job_execution_pack_prep | F74: Consolidation Preparer Job (Execution + Pack Prep) | G74: P3/P4 | H74: R2R_first_time_right_quality_sox_icfr_ready | I74: First Time Right (Quality, SOX/ICFR-ready) | K74: 3 | L74: Intermediate | N74: RTR_Roles_to_Skills_Mapping_Updated_2701.xlsx | O74: Consolidation
A75: RSM-0072 | B75: Actual FinOps Framework Structure - no employee data | C75: R2R | D75: Consolidation | E75: R2R_consolidation_preparer_job_execution_pack_prep | F75: Consolidation Preparer Job (Execution + Pack Prep) | G75: P3/P4 | H75: R2R_attention_to_detail_sox_evidence_trail_documentation | I75: Attention to Detail (SOX evidence trail / documentation) | K75: 4 | L75: Advanced | N75: RTR_Roles_to_Skills_Mapping_Updated_2701.xlsx | O75: Consolidation
... A93: RSM-0090 | B93: Actual FinOps Framework Structure - no employee data | C93: R2R | D93: GA | E93: R2R_ga_preparer_job_preparation_only | F93: GA Preparer Job (Preparation-only) | G93: B3/B4/P3 | H93: R2R_teamwork_collaboration | I93: Teamwork / Collaboration | K93: 4 | L93: Advanced | N93: RTR_Roles_to_Skills_Mapping_Updated_2701.xlsx | O93: GA

Sheet Training_Catalogue
A1: Training Catalogue
A3: course_id | B3: data_label | C3: tower | D3: course_title | E3: delivery_type | F3: level_group | G3: risk_level | H3: spoc_role | I3: source_file | J3: source_sheet
A4: TRN-0001 | B4: Actual FinOps training/gap structure where source-mapped; otherwise synthetic remediation placeholder | C4: AP | D4: Goods Receipt (GRN) | E4: Scenario Lab / Microlearning / Coaching | F4: Beginner | G4: Medium | H4: P2P SDL | I4: Skill Gap analysis V1.0.xlsx | J4: Training Assessment Gap Log
A5: TRN-0002 | B5: Actual FinOps training/gap structure where source-mapped; otherwise synthetic remediation placeholder | C5: AP | D5: How to trace a break across PO → GRN → Invoice → ERP workflow | E5: Scenario Lab / Microlearning / Coaching | F5: Beginner & Intermediate | G5: High | H5: P2P SDL | I5: Skill Gap analysis V1.0.xlsx | J5: Training Assessment Gap Log
A6: TRN-0003 | B6: Actual FinOps training/gap structure where source-mapped; otherwise synthetic remediation placeholder | C6: AP | D6: Duplicate payment, late payments, vendor query L2 | E6: Scenario Lab / Microlearning / Coaching | F6: Intermediate | G6: High | H6: P2P SDL | I6: Skill Gap analysis V1.0.xlsx | J6: Training Assessment Gap Log
A7: TRN-0004 | B7: Actual FinOps training/gap structure where source-mapped; otherwise synthetic remediation placeholder | C7: AP | D7: Role-based assessment remediation for Close Activities (Accruals, Cutoff, GR/IR) | E7: Scenario Lab / Microlearning / Coaching | F7: Generated from gap-to-target | G7: Medium | H7: Capability Team + SME | I7: Generated from role-skill gap where no mapped training topic was found | J7: Generated
A8: TRN-0005 | B8: Actual FinOps training/gap structure where source-mapped; otherwise synthetic remediation placeholder | C8: AP | D8: Role-based assessment remediation for Continuous Improvement (Lean/Six Sigma) | E8: Scenario Lab / Microlearning / Coaching | F8: Generated from gap-to-target | G8: Medium | H8: Capability Team + SME | I8: Generated from role-skill gap where no mapped training topic was found | J8: Generated
A9: TRN-0006 | B9: Actual FinOps training/gap structure where source-mapped; otherwise synthetic remediation placeholder | C9: AP | D9: Role-based assessment remediation for Controls / Compliance / Audit (AP) | E9: Scenario Lab / Microlearning / Coaching | F9: Generated from gap-to-target | G9: Medium | H9: Capability Team + SME | I9: Generated from role-skill gap where no mapped training topic was found | J9: Generated
A10: TRN-0007 | B10: Actual FinOps training/gap structure where source-mapped; otherwise synthetic remediation placeholder | C10: AP | D10: Role-based assessment remediation for First Time Right (Quality) | E10: Scenario Lab / Microlearning / Coaching | F10: Generated from gap-to-target | G10: Medium | H10: Capability Team + SME | I10: Generated from role-skill gap where no mapped training topic was found | J10: Generated
A11: TRN-0008 | B11: Actual FinOps training/gap structure where source-mapped; otherwise synthetic remediation placeholder | C11: AP | D11: Role-based assessment remediation for Invoice Processing (PO & Non-PO) | E11: Scenario Lab / Microlearning / Coaching | F11: Generated from gap-to-target | G11: Medium | H11: Capability Team + SME | I11: Generated from role-skill gap where no mapped training topic was found | J11: Generated
A12: TRN-0009 | B12: Actual FinOps training/gap structure where source-mapped; otherwise synthetic remediation placeholder | C12: AP | D12: Role-based assessment remediation for Ownership & Delivery | E12: Scenario Lab / Microlearning / Coaching | F12: Generated from gap-to-target | G12: Medium | H12: Capability Team + SME | I12: Generated from role-skill gap where no mapped training topic was found | J12: Generated
A13: TRN-0010 | B13: Actual FinOps training/gap structure where source-mapped; otherwise synthetic remediation placeholder | C13: AP | D13: Role-based assessment remediation for Payments Execution (Runs/Methods) | E13: Scenario Lab / Microlearning / Coaching | F13: Generated from gap-to-target | G13: Medium | H13: Capability Team + SME | I13: Generated from role-skill gap where no mapped training topic was found | J13: Generated
A14: TRN-0011 | B14: Actual FinOps training/gap structure where source-mapped; otherwise synthetic remediation placeholder | C14: AP | D14: Role-based assessment remediation for Problem Solving (RCA/CAPA) | E14: Scenario Lab / Microlearning / Coaching | F14: Generated from gap-to-target | G14: Medium | H14: Capability Team + SME | I14: Generated from role-skill gap where no mapped training topic was found | J14: Generated
... A33: TRN-0030 | B33: Actual FinOps training/gap structure where source-mapped; otherwise synthetic remediation placeholder | C33: O2C | D33: Awareness: SLA/KPI/Volume Metrics | E33: Scenario Lab / Microlearning / Coaching | F33: Intermediate & Advanced | G33: High | H33: O2C SDL | I33: Skill Gap analysis V1.0.xlsx | J33: Training Assessment Gap Log
A34: TRN-0031 | B34: Actual FinOps training/gap structure where source-mapped; otherwise synthetic remediation placeholder | D34: Role-based assessment remediation for | E34: Scenario Lab / Microlearning / Coaching | F34: Generated from gap-to-target | G34: Medium | H34: Capability Team + SME | I34: Generated from role-skill gap where no mapped training topic was found | J34: Generated

Sheet Training_Skill_Map
A1: Training Skill Map
A3: training_skill_map_id | B3: data_label | C3: course_id | D3: tower | E3: skill_id | F3: skill | G3: capability | H3: level_group | I3: mapping_confidence | J3: source_file
A4: TSM-0001 | B4: Training-to-skill relationship for hackfest prototype | C4: TRN-0001 | D4: AP | E4: AP_3_way_match_exception_handling | F4: 3-Way Match & Exception Handling | G4: Technical Expertise | H4: Beginner | I4: High | J4: Skill Gap analysis V1.0.xlsx
A5: TSM-0002 | B5: Training-to-skill relationship for hackfest prototype | C5: TRN-0002 | D5: AP | E5: AP_3_way_match_exception_handling | F5: 3-Way Match & Exception Handling | G5: Technical Expertise | H5: Beginner & Intermediate | I5: High | J5: Skill Gap analysis V1.0.xlsx
A6: TSM-0003 | B6: Training-to-skill relationship for hackfest prototype | C6: TRN-0003 | D6: AP | E6: AP_ap_reconciliations_subledger_gl_vendor_statements | F6: AP Reconciliations (Subledger/GL, Vendor Statements) | G6: Technical Expertise | H6: Intermediate | I6: High | J6: Skill Gap analysis V1.0.xlsx
A7: TSM-0004 | B7: Training-to-skill relationship for hackfest prototype | C7: TRN-0004 | D7: AP | E7: AP_close_activities_accruals_cutoff_gr_ir | F7: Close Activities (Accruals, Cutoff, GR/IR) | G7: Technical Expertise | H7: Generated from gap-to-target | I7: Medium - generated placeholder | J7: Generated from role-skill gap where no mapped training topic was found
A8: TSM-0005 | B8: Training-to-skill relationship for hackfest prototype | C8: TRN-0005 | D8: AP | E8: AP_continuous_improvement_lean_six_sigma | F8: Continuous Improvement (Lean/Six Sigma) | G8: Process Governance | H8: Generated from gap-to-target | I8: Medium - generated placeholder | J8: Generated from role-skill gap where no mapped training topic was found
A9: TSM-0006 | B9: Training-to-skill relationship for hackfest prototype | C9: TRN-0006 | D9: AP | E9: AP_controls_compliance_audit_ap | F9: Controls / Compliance / Audit (AP) | G9: Technical Expertise | H9: Generated from gap-to-target | I9: Medium - generated placeholder | J9: Generated from role-skill gap where no mapped training topic was found
A10: TSM-0007 | B10: Training-to-skill relationship for hackfest prototype | C10: TRN-0007 | D10: AP | E10: AP_first_time_right_quality | F10: First Time Right (Quality) | G10: Technical Expertise | H10: Generated from gap-to-target | I10: Medium - generated placeholder | J10: Generated from role-skill gap where no mapped training topic was found
A11: TSM-0008 | B11: Training-to-skill relationship for hackfest prototype | C11: TRN-0008 | D11: AP | E11: AP_invoice_processing_po_non_po | F11: Invoice Processing (PO & Non-PO) | G11: Technical Expertise | H11: Generated from gap-to-target | I11: Medium - generated placeholder | J11: Generated from role-skill gap where no mapped training topic was found
A12: TSM-0009 | B12: Training-to-skill relationship for hackfest prototype | C12: TRN-0009 | D12: AP | E12: AP_ownership_delivery | F12: Ownership & Delivery | G12: Process Governance | H12: Generated from gap-to-target | I12: Medium - generated placeholder | J12: Generated from role-skill gap where no mapped training topic was found
A13: TSM-0010 | B13: Training-to-skill relationship for hackfest prototype | C13: TRN-0010 | D13: AP | E13: AP_payments_execution_runs_methods | F13: Payments Execution (Runs/Methods) | G13: Technical Expertise | H13: Generated from gap-to-target | I13: Medium - generated placeholder | J13: Generated from role-skill gap where no mapped training topic was found
A14: TSM-0011 | B14: Training-to-skill relationship for hackfest prototype | C14: TRN-0011 | D14: AP | E14: AP_problem_solving_rca_capa | F14: Problem Solving (RCA/CAPA) | G14: Process Governance | H14: Generated from gap-to-target | I14: Medium - generated placeholder | J14: Generated from role-skill gap where no mapped training topic was found
... A33: TSM-0030 | B33: Training-to-skill relationship for hackfest prototype | C33: TRN-0030 | D33: O2C | E33: O2C_sla_governance_metrics_dso_backlog_accuracy | F33: SLA / Governance / Metrics (DSO, Backlog, Accuracy) | G33: Process Governance | H33: Intermediate & Advanced | I33: High | J33: Skill Gap analysis V1.0.xlsx
A34: TSM-0031 | B34: Training-to-skill relationship for hackfest prototype | C34: TRN-0031 | E34: R2R_attention_to_detail_sox_evidence_trail_documentation | H34: Generated from gap-to-target | I34: Medium - generated placeholder | J34: Generated from role-skill gap where no mapped training topic was found
A35: TSM-0032 | B35: Training-to-skill relationship for hackfest prototype | C35: TRN-0032 | E35: R2R_consolidation_ifrs_10_ifrs_3_ias_21_asc_810 | H35: Generated from gap-to-target | I35: Medium - generated placeholder | J35: Generated from role-skill gap where no mapped training topic was found
A36: TSM-0033 | B36: Training-to-skill relationship for hackfest prototype | C36: TRN-0033 | E36: R2R_erp_finance_tools_sap_oracle_blackline_onestream_sox_controls_in_systems | H36: Generated from gap-to-target | I36: Medium - generated placeholder | J36: Generated from role-skill gap where no mapped training topic was found
A37: TSM-0034 | B37: Training-to-skill relationship for hackfest prototype | C37: TRN-0034 | E37: R2R_financial_reporting_ifrs_us_gaap | H37: Generated from gap-to-target | I37: Medium - generated placeholder | J37: Generated from role-skill gap where no mapped training topic was found
A38: TSM-0035 | B38: Training-to-skill relationship for hackfest prototype | C38: TRN-0035 | E38: R2R_first_time_right_quality_sox_icfr_ready | H38: Generated from gap-to-target | I38: Medium - generated placeholder | J38: Generated from role-skill gap where no mapped training topic was found
A39: TSM-0036 | B39: Training-to-skill relationship for hackfest prototype | C39: TRN-0036 | E39: R2R_fixed_assets_banking_ias_16_ias_36_asc_360 | H39: Generated from gap-to-target | I39: Medium - generated placeholder | J39: Generated from role-skill gap where no mapped training topic was found
A40: TSM-0037 | B40: Training-to-skill relationship for hackfest prototype | C40: TRN-0037 | E40: R2R_ownership_delivery | H40: Generated from gap-to-target | I40: Medium - generated placeholder | J40: Generated from role-skill gap where no mapped training topic was found
A41: TSM-0038 | B41: Training-to-skill relationship for hackfest prototype | C41: TRN-0038 | E41: R2R_productivity_tools_excel_ppt | H41: Generated from gap-to-target | I41: Medium - generated placeholder | J41: Generated from role-skill gap where no mapped training topic was found
A42: TSM-0039 | B42: Training-to-skill relationship for hackfest prototype | C42: TRN-0039 | E42: R2R_professional_conduct | H42: Generated from gap-to-target | I42: Medium - generated placeholder | J42: Generated from role-skill gap where no mapped training topic was found
A43: TSM-0040 | B43: Training-to-skill relationship for hackfest prototype | C43: TRN-0040 | E43: R2R_r2r_close_journals_us_gaap_ifrs | H43: Generated from gap-to-target | I43: Medium - generated placeholder | J43: Generated from role-skill gap where no mapped training topic was found
A44: TSM-0041 | B44: Training-to-skill relationship for hackfest prototype | C44: TRN-0041 | E44: R2R_reconciliations_clearing_sox_ipe_balance_sheet_recs | H44: Generated from gap-to-target | I44: Medium - generated placeholder | J44: Generated from role-skill gap where no mapped training topic was found
A45: TSM-0042 | B45: Training-to-skill relationship for hackfest prototype | C45: TRN-0042 | E45: R2R_teamwork_collaboration | H45: Generated from gap-to-target | I45: Medium - generated placeholder | J45: Generated from role-skill gap where no mapped training topic was found
A46: TSM-0043 | B46: Training-to-skill relationship for hackfest prototype | C46: TRN-0043 | E46: R2R_time_management | H46: Generated from gap-to-target | I46: Medium - generated placeholder | J46: Generated from role-skill gap where no mapped training topic was found

Sheet Assessment_Blueprints
A1: Assessment Blueprints
A3: blueprint_id | B3: data_label | C3: tower | D3: role_id | E3: role_name | F3: role_grade | G3: assessment_name | H3: assessment_purpose | I3: duration_minutes | J3: target_question_count | K3: skill_count | L3: generation_basis | M3: human_in_loop | N3: mvp_scope
A4: BP-001 | B4: Talent360i Hackfest Blueprint - no employee data | C4: R2R | D4: R2R_banking_preparer_job_preparation_cash_posting | E4: Banking Preparer Job (Preparation + Cash Posting) | F4: B3/B4/P3 | G4: R2R Banking Preparer Job (Preparation + Cash Posting) Skill Assessment | H4: Auto-generate role/skill questions and route for SME approval before scheduling | I4: 35 | J4: 20 | K4: 10 | L4: JD / role profile + skill dictionary + role-skill matrix + existing approved question bank where available | M4: SME must approve before assessment can be scheduled | N4: Core Talent360i auto assessment generation
A5: BP-002 | B5: Talent360i Hackfest Blueprint - no employee data | C5: R2R | D5: R2R_ga_preparer_job_preparation_only | E5: GA Preparer Job (Preparation-only) | F5: B3/B4/P3 | G5: R2R GA Preparer Job (Preparation-only) Skill Assessment | H5: Auto-generate role/skill questions and route for SME approval before scheduling | I5: 35 | J5: 20 | K5: 10 | L5: JD / role profile + skill dictionary + role-skill matrix + existing approved question bank where available | M5: SME must approve before assessment can be scheduled | N5: Core Talent360i auto assessment generation
A6: BP-003 | B6: Talent360i Hackfest Blueprint - no employee data | C6: R2R | D6: R2R_consolidation_preparer_job_execution_pack_prep | E6: Consolidation Preparer Job (Execution + Pack Prep) | F6: P3/P4 | G6: R2R Consolidation Preparer Job (Execution + Pack Prep) Skill Assessment | H6: Auto-generate role/skill questions and route for SME approval before scheduling | I6: 35 | J6: 20 | K6: 10 | L6: JD / role profile + skill dictionary + role-skill matrix + existing approved question bank where available | M6: SME must approve before assessment can be scheduled | N6: Core Talent360i auto assessment generation
A7: BP-004 | B7: Talent360i Hackfest Blueprint - no employee data | C7: AP | D7: AP_p2p_lead | E7: P2P Lead | F7: B4 | G7: AP P2P Lead Skill Assessment | H7: Auto-generate role/skill questions and route for SME approval before scheduling | I7: 45 | J7: 20 | K7: 10 | L7: JD / role profile + skill dictionary + role-skill matrix + existing approved question bank where available | M7: SME must approve before assessment can be scheduled | N7: Core Talent360i auto assessment generation
A8: BP-005 | B8: Talent360i Hackfest Blueprint - no employee data | C8: AP | D8: AP_p2p_senior_associate | E8: P2P Senior Associate | F8: B3 | G8: AP P2P Senior Associate Skill Assessment | H8: Auto-generate role/skill questions and route for SME approval before scheduling | I8: 35 | J8: 20 | K8: 10 | L8: JD / role profile + skill dictionary + role-skill matrix + existing approved question bank where available | M8: SME must approve before assessment can be scheduled | N8: Core Talent360i auto assessment generation
A9: BP-006 | B9: Talent360i Hackfest Blueprint - no employee data | C9: AP | D9: AP_t_e_lead | E9: T&E Lead | F9: B4 | G9: AP T&E Lead Skill Assessment | H9: Auto-generate role/skill questions and route for SME approval before scheduling | I9: 45 | J9: 20 | K9: 10 | L9: JD / role profile + skill dictionary + role-skill matrix + existing approved question bank where available | M9: SME must approve before assessment can be scheduled | N9: Core Talent360i auto assessment generation
A10: BP-007 | B10: Talent360i Hackfest Blueprint - no employee data | C10: O2C | D10: O2C_billing_team_lead | E10: Billing Team Lead | F10: B4 | G10: O2C Billing Team Lead Skill Assessment | H10: Auto-generate role/skill questions and route for SME approval before scheduling | I10: 35 | J10: 20 | K10: 10 | L10: JD / role profile + skill dictionary + role-skill matrix + existing approved question bank where available | M10: SME must approve before assessment can be scheduled | N10: Core Talent360i auto assessment generation
A11: BP-008 | B11: Talent360i Hackfest Blueprint - no employee data | C11: O2C | D11: O2C_associate_revenue_controller | E11: Associate Revenue Controller | F11: P4 | G11: O2C Associate Revenue Controller Skill Assessment | H11: Auto-generate role/skill questions and route for SME approval before scheduling | I11: 35 | J11: 20 | K11: 10 | L11: JD / role profile + skill dictionary + role-skill matrix + existing approved question bank where available | M11: SME must approve before assessment can be scheduled | N11: Core Talent360i auto assessment generation
A12: BP-009 | B12: Talent360i Hackfest Blueprint - no employee data | C12: O2C | D12: O2C_senior_revenue_associate | E12: Senior Revenue Associate | F12: B3 | G12: O2C Senior Revenue Associate Skill Assessment | H12: Auto-generate role/skill questions and route for SME approval before scheduling | I12: 35 | J12: 20 | K12: 10 | L12: JD / role profile + skill dictionary + role-skill matrix + existing approved question bank where available | M12: SME must approve before assessment can be scheduled | N12: Core Talent360i auto assessment generation

Sheet Assessment_QBank
A1: Assessment QBank
A3: question_id | B3: blueprint_id | C3: data_label | D3: tower | E3: role_id | F3: role_name | G3: skill_id | H3: skill | I3: target_proficiency_level | J3: question_source | K3: source_question_reference | L3: question_type | M3: question_text | N3: option_a | O3: option_b | P3: option_c | Q3: option_d | R3: correct_option | S3: critical_flag | T3: difficulty | U3: ai_confidence | V3: sme_review_status | W3: sme_action_required | X3: approved_for_schedule | Y3: schedule_scope | Z3: generated_prompt_context | AA3: eligible_formula_note
A4: Q-0001 | B4: BP-004 | C4: Approved assessment content from source file - no employee data | D4: AP | E4: AP_p2p_lead | F4: P2P Lead | G4: AP_sla_governance_metrics | H4: SLA / Governance / Metrics | I4: 3 | J4: Approved source assessment | K4: AP and T&E Lead B4 P4 hiring assessment 30 Mar.docx / Q1 | L4: Multiple Choice - Scenario | M4: You have a backlog nearing SLA breach. Some invoices are pending validation. | N4: Process all to meet SLA | S4: No | T4: Role Ready | V4: Approved | W4: No | X4: =IF(V4="Approved","Yes","No") -> Yes | Y4: Core Selected Role | Z4: Existing approved question; not generated by AI. | AA4: Excel formula column in workbook checks SME status.
A5: Q-0002 | B5: BP-006 | C5: Approved assessment content from source file - no employee data | D5: AP | E5: AP_t_e_lead | F5: T&E Lead | G5: AP_sla_governance_metrics | H5: SLA / Governance / Metrics | I5: 3 | J5: Approved source assessment | K5: AP and T&E Lead B4 P4 hiring assessment 30 Mar.docx / Q1 | L5: Multiple Choice - Scenario | M5: You have a backlog nearing SLA breach. Some invoices are pending validation. | N5: Process all to meet SLA | S5: No | T5: Role Ready | V5: Approved | W5: No | X5: =IF(V5="Approved","Yes","No") -> Yes | Y5: Core Selected Role | Z5: Existing approved question; not generated by AI. | AA5: Excel formula column in workbook checks SME status.
A6: Q-0003 | B6: BP-004 | C6: Approved assessment content from source file - no employee data | D6: AP | E6: AP_p2p_lead | F6: P2P Lead | G6: AP_first_time_right_quality | H6: First Time Right (Quality) | I6: 3 | J6: Approved source assessment | K6: AP and T&E Lead B4 P4 hiring assessment 30 Mar.docx / Q2 | L6: Multiple Choice - Scenario | M6: One team member overloaded, others underutilized. | N6: Let them manage | S6: No | T6: Role Ready | V6: Approved | W6: No | X6: =IF(V6="Approved","Yes","No") -> Yes | Y6: Core Selected Role | Z6: Existing approved question; not generated by AI. | AA6: Excel formula column in workbook checks SME status.
A7: Q-0004 | B7: BP-006 | C7: Approved assessment content from source file - no employee data | D7: AP | E7: AP_t_e_lead | F7: T&E Lead | G7: AP_work_intake_prioritization_backlog_mgmt | H7: Work Intake & Prioritization (Backlog Mgmt) | I7: 3 | J7: Approved source assessment | K7: AP and T&E Lead B4 P4 hiring assessment 30 Mar.docx / Q2 | L7: Multiple Choice - Scenario | M7: One team member overloaded, others underutilized. | N7: Let them manage | S7: No | T7: Role Ready | V7: Approved | W7: No | X7: =IF(V7="Approved","Yes","No") -> Yes | Y7: Core Selected Role | Z7: Existing approved question; not generated by AI. | AA7: Excel formula column in workbook checks SME status.
A8: Q-0005 | B8: BP-004 | C8: Approved assessment content from source file - no employee data | D8: AP | E8: AP_p2p_lead | F8: P2P Lead | G8: AP_first_time_right_quality | H8: First Time Right (Quality) | I8: 3 | J8: Approved source assessment | K8: AP and T&E Lead B4 P4 hiring assessment 30 Mar.docx / Q3 | L8: Multiple Choice - Scenario | M8: Same issue recurring across multiple invoices. | N8: Resolve case by case | S8: No | T8: Role Ready | V8: Approved | W8: No | X8: =IF(V8="Approved","Yes","No") -> Yes | Y8: Core Selected Role | Z8: Existing approved question; not generated by AI. | AA8: Excel formula column in workbook checks SME status.
A9: Q-0006 | B9: BP-006 | C9: Approved assessment content from source file - no employee data | D9: AP | E9: AP_t_e_lead | F9: T&E Lead | G9: AP_first_time_right_quality | H9: First Time Right (Quality) | I9: 3 | J9: Approved source assessment | K9: AP and T&E Lead B4 P4 hiring assessment 30 Mar.docx / Q3 | L9: Multiple Choice - Scenario | M9: Same issue recurring across multiple invoices. | N9: Resolve case by case | S9: No | T9: Role Ready | V9: Approved | W9: No | X9: =IF(V9="Approved","Yes","No") -> Yes | Y9: Core Selected Role | Z9: Existing approved question; not generated by AI. | AA9: Excel formula column in workbook checks SME status.
A10: Q-0007 | B10: BP-004 | C10: Approved assessment content from source file - no employee data | D10: AP | E10: AP_p2p_lead | F10: P2P Lead | G10: AP_controls_compliance_audit_ap | H10: Controls / Compliance / Audit (AP) | I10: 3 | J10: Approved source assessment | K10: AP and T&E Lead B4 P4 hiring assessment 30 Mar.docx / Q4 | L10: Multiple Choice - Scenario | M10: Audit identifies missing approval documentation. | N10: Ignore | S10: No | T10: Role Ready | V10: Approved | W10: No | X10: =IF(V10="Approved","Yes","No") -> Yes | Y10: Core Selected Role | Z10: Existing approved question; not generated by AI. | AA10: Excel formula column in workbook checks SME status.
A11: Q-0008 | B11: BP-006 | C11: Approved assessment content from source file - no employee data | D11: AP | E11: AP_t_e_lead | F11: T&E Lead | G11: AP_controls_compliance_audit_ap | H11: Controls / Compliance / Audit (AP) | I11: 3 | J11: Approved source assessment | K11: AP and T&E Lead B4 P4 hiring assessment 30 Mar.docx / Q4 | L11: Multiple Choice - Scenario | M11: Audit identifies missing approval documentation. | N11: Ignore | S11: No | T11: Role Ready | V11: Approved | W11: No | X11: =IF(V11="Approved","Yes","No") -> Yes | Y11: Core Selected Role | Z11: Existing approved question; not generated by AI. | AA11: Excel formula column in workbook checks SME status.
A12: Q-0009 | B12: BP-004 | C12: Approved assessment content from source file - no employee data | D12: AP | E12: AP_p2p_lead | F12: P2P Lead | G12: AP_payments_execution_runs_methods | H12: Payments Execution (Runs/Methods) | I12: 3 | J12: Approved source assessment | K12: AP and T&E Lead B4 P4 hiring assessment 30 Mar.docx / Q5 | L12: Multiple Choice - Scenario | M12: Bank rejects payment batch. | N12: Ignore | S12: No | T12: Role Ready | V12: Approved | W12: No | X12: =IF(V12="Approved","Yes","No") -> Yes | Y12: Core Selected Role | Z12: Existing approved question; not generated by AI. | AA12: Excel formula column in workbook checks SME status.
A13: Q-0010 | B13: BP-006 | C13: Approved assessment content from source file - no employee data | D13: AP | E13: AP_t_e_lead | F13: T&E Lead | G13: AP_first_time_right_quality | H13: First Time Right (Quality) | I13: 3 | J13: Approved source assessment | K13: AP and T&E Lead B4 P4 hiring assessment 30 Mar.docx / Q5 | L13: Multiple Choice - Scenario | M13: Bank rejects payment batch. | N13: Ignore | S13: No | T13: Role Ready | V13: Approved | W13: No | X13: =IF(V13="Approved","Yes","No") -> Yes | Y13: Core Selected Role | Z13: Existing approved question; not generated by AI. | AA13: Excel formula column in workbook checks SME status.
A14: Q-0011 | B14: BP-004 | C14: Approved assessment content from source file - no employee data | D14: AP | E14: AP_p2p_lead | F14: P2P Lead | G14: AP_ap_reconciliations_subledger_gl_vendor_statements | H14: AP Reconciliations (Subledger/GL, Vendor Statements) | I14: 3 | J14: Approved source assessment | K14: AP and T&E Lead B4 P4 hiring assessment 30 Mar.docx / Q6 | L14: Multiple Choice - Scenario | M14: Aging >90 days increasing. | N14: Focus only on new invoices | S14: No | T14: Role Ready | V14: Approved | W14: No | X14: =IF(V14="Approved","Yes","No") -> Yes | Y14: Core Selected Role | Z14: Existing approved question; not generated by AI. | AA14: Excel formula column in workbook checks SME status.
A15: Q-0012 | B15: BP-006 | C15: Approved assessment content from source file - no employee data | D15: AP | E15: AP_t_e_lead | F15: T&E Lead | G15: AP_first_time_right_quality | H15: First Time Right (Quality) | I15: 3 | J15: Approved source assessment | K15: AP and T&E Lead B4 P4 hiring assessment 30 Mar.docx / Q6 | L15: Multiple Choice - Scenario | M15: Aging >90 days increasing. | N15: Focus only on new invoices | S15: No | T15: Role Ready | V15: Approved | W15: No | X15: =IF(V15="Approved","Yes","No") -> Yes | Y15: Core Selected Role | Z15: Existing approved question; not generated by AI. | AA15: Excel formula column in workbook checks SME status.
... A39: Q-0036 | B39: BP-004 | C39: Approved assessment content from source file - no employee data | D39: AP | E39: AP_p2p_lead | F39: Reference In-Market P3/P4 | G39: AP_first_time_right_quality | H39: First Time Right (Quality) | I39: 3 | J39: Approved source assessment | K39: AP and T&E Lead B4 P4 hiring assessment 30 Mar.docx / Q24 | L39: Multiple Choice - Scenario | M39: Recurring statutory non-compliance. | N39: Ignore | S39: No | T39: Role Ready | V39: Approved | W39: No | X39: =IF(V39="Approved","Yes","No") -> Yes | Y39: Reference - Not scheduled in selected B3/B4 cohort | Z39: Existing approved question; not generated by AI. | AA39: Excel formula column in workbook checks SME status.
A40: Q-0037 | B40: BP-004 | C40: Synthetic Hackfest Test Data - AI-generated draft question | D40: AP | E40: AP_p2p_lead | F40: P2P Lead | G40: AP_invoice_processing_po_non_po | H40: Invoice Processing (PO & Non-PO) | I40: 3 | J40: AI-generated from JD/role profile + skill definition | K40: Generated for Hackfest; SME must approve before scheduling | L40: Multiple Choice - Scenario | M40: For the role P2P Lead, which action best demonstrates Proficient capability in Invoice Processing (PO & Non-PO)? | N40: Follow the standard SOP only when instructed and wait for review before taking action. | O40: Apply the SOP, maintain evidence, escalate exceptions, and document the rationale for Invoice Processing (PO & Non-PO). | P40: Skip documentation to meet speed targets and update records after the close cycle. | Q40: Resolve the item informally without linking the action to controls, metrics or evidence. | R40: B | S40: No | T40: Role Ready | U40: 0.73 | V40: Pending SME Review | W40: Yes | X40: =IF(V40="Approved","Yes","No") -> No | Y40: Core Selected Role | Z40: Use role: P2P Lead; skill: Invoice Processing (PO & Non-PO); target L3; behavior: Independently resolves exceptions (price/qty/GR issues); optimizes cycle time; ensures accurate postings. | AA40: Excel formula column in workbook checks SME status.
A41: Q-0038 | B41: BP-004 | C41: Synthetic Hackfest Test Data - AI-generated draft question | D41: AP | E41: AP_p2p_lead | F41: P2P Lead | G41: AP_3_way_match_exception_handling | H41: 3-Way Match & Exception Handling | I41: 3 | J41: AI-generated from JD/role profile + skill definition | K41: Generated for Hackfest; SME must approve before scheduling | L41: Multiple Choice - Scenario | M41: For the role P2P Lead, which action best demonstrates Proficient capability in 3-Way Match & Exception Handling? | N41: Follow the standard SOP only when instructed and wait for review before taking action. | O41: Apply the SOP, maintain evidence, escalate exceptions, and document the rationale for 3-Way Match & Exception Handling. | P41: Skip documentation to meet speed targets and update records after the close cycle. | Q41: Resolve the item informally without linking the action to controls, metrics or evidence. | R41: B | S41: No | T41: Role Ready | U41: 0.77 | V41: Approved | W41: No | X41: =IF(V41="Approved","Yes","No") -> Yes | Y41: Core Selected Role | Z41: Use role: P2P Lead; skill: 3-Way Match & Exception Handling; target L3; behavior: Independently investigates match breaks; coordinates with Procurement/Receiving; closes root causes. | AA41: Excel formula column in workbook checks SME status.
A42: Q-0039 | B42: BP-004 | C42: Synthetic Hackfest Test Data - AI-generated draft question | D42: AP | E42: AP_p2p_lead | F42: P2P Lead | G42: AP_tax_withholding_regulatory_basics | H42: Tax / Withholding & Regulatory Basics | I42: 3 | J42: AI-generated from JD/role profile + skill definition | K42: Generated for Hackfest; SME must approve before scheduling | L42: Multiple Choice - Scenario | M42: For the role P2P Lead, which action best demonstrates Proficient capability in Tax / Withholding & Regulatory Basics? | N42: Follow the standard SOP only when instructed and wait for review before taking action. | O42: Apply the SOP, maintain evidence, escalate exceptions, and document the rationale for Tax / Withholding & Regulatory Basics. | P42: Skip documentation to meet speed targets and update records after the close cycle. | Q42: Resolve the item informally without linking the action to controls, metrics or evidence. | R42: B | S42: No | T42: Role Ready | U42: 0.86 | V42: Pending SME Review | W42: Yes | X42: =IF(V42="Approved","Yes","No") -> No | Y42: Core Selected Role | Z42: Use role: P2P Lead; skill: Tax / Withholding & Regulatory Basics; target L3; behavior: Independently validates tax treatment for non-routine invoices; partners with Tax/Finance for resolution. | AA42: Excel formula column in workbook checks SME status.
A43: Q-0040 | B43: BP-004 | C43: Synthetic Hackfest Test Data - AI-generated draft question | D43: AP | E43: AP_p2p_lead | F43: P2P Lead | G43: AP_close_activities_accruals_cutoff_gr_ir | H43: Close Activities (Accruals, Cutoff, GR/IR) | I43: 3 | J43: AI-generated from JD/role profile + skill definition | K43: Generated for Hackfest; SME must approve before scheduling | L43: Multiple Choice - Scenario | M43: For the role P2P Lead, which action best demonstrates Proficient capability in Close Activities (Accruals, Cutoff, GR/IR)? | N43: Follow the standard SOP only when instructed and wait for review before taking action. | O43: Apply the SOP, maintain evidence, escalate exceptions, and document the rationale for Close Activities (Accruals, Cutoff, GR/IR). | P43: Skip documentation to meet speed targets and update records after the close cycle. | Q43: Resolve the item informally without linking the action to controls, metrics or evidence. | R43: B | S43: No | T43: Role Ready | U43: 0.74 | V43: Pending SME Review | W43: Yes | X43: =IF(V43="Approved","Yes","No") -> No | Y43: Core Selected Role | Z43: Use role: P2P Lead; skill: Close Activities (Accruals, Cutoff, GR/IR); target L3; behavior: Independently manages AP close tasks; resolves GR/IR and cutoff issues; improves timeliness. | AA43: Excel formula column in workbook checks SME status.
A44: Q-0041 | B44: BP-004 | C44: Synthetic Hackfest Test Data - AI-generated draft question | D44: AP | E44: AP_p2p_lead | F44: P2P Lead | G44: AP_ownership_delivery | H44: Ownership & Delivery | I44: 3 | J44: AI-generated from JD/role profile + skill definition | K44: Generated for Hackfest; SME must approve before scheduling | L44: Multiple Choice - Scenario | M44: For the role P2P Lead, which action best demonstrates Proficient capability in Ownership & Delivery? | N44: Follow the standard SOP only when instructed and wait for review before taking action. | O44: Apply the SOP, maintain evidence, escalate exceptions, and document the rationale for Ownership & Delivery. | P44: Skip documentation to meet speed targets and update records after the close cycle. | Q44: Resolve the item informally without linking the action to controls, metrics or evidence. | R44: B | S44: No | T44: Role Ready | U44: 0.73 | V44: Approved | W44: No | X44: =IF(V44="Approved","Yes","No") -> Yes | Y44: Core Selected Role | Z44: Use role: P2P Lead; skill: Ownership & Delivery; target L3; behavior: Independently owns outcomes; manages exceptions and handoffs; accountable for results. | AA44: Excel formula column in workbook checks SME status.
A45: Q-0042 | B45: BP-005 | C45: Synthetic Hackfest Test Data - AI-generated draft question | D45: AP | E45: AP_p2p_senior_associate | F45: P2P Senior Associate | G45: AP_first_time_right_quality | H45: First Time Right (Quality) | I45: 3 | J45: AI-generated from JD/role profile + skill definition | K45: Generated for Hackfest; SME must approve before scheduling | L45: Multiple Choice - Scenario | M45: For the role P2P Senior Associate, which action best demonstrates Proficient capability in First Time Right (Quality)? | N45: Follow the standard SOP only when instructed and wait for review before taking action. | O45: Apply the SOP, maintain evidence, escalate exceptions, and document the rationale for First Time Right (Quality). | P45: Skip documentation to meet speed targets and update records after the close cycle. | Q45: Resolve the item informally without linking the action to controls, metrics or evidence. | R45: B | S45: No | T45: Role Ready | U45: 0.83 | V45: Approved | W45: No | X45: =IF(V45="Approved","Yes","No") -> Yes | Y45: Core Selected Role | Z45: Use role: P2P Senior Associate; skill: First Time Right (Quality); target L3; behavior: Independently delivers right-first-time processing; prevents defects; improves rework and rejection rates. | AA45: Excel formula column in workbook checks SME status.
A46: Q-0043 | B46: BP-005 | C46: Synthetic Hackfest Test Data - AI-generated draft question | D46: AP | E46: AP_p2p_senior_associate | F46: P2P Senior Associate | G46: AP_invoice_processing_po_non_po | H46: Invoice Processing (PO & Non-PO) | I46: 3 | J46: AI-generated from JD/role profile + skill definition | K46: Generated for Hackfest; SME must approve before scheduling | L46: Multiple Choice - Scenario | M46: For the role P2P Senior Associate, which action best demonstrates Proficient capability in Invoice Processing (PO & Non-PO)? | N46: Follow the standard SOP only when instructed and wait for review before taking action. | O46: Apply the SOP, maintain evidence, escalate exceptions, and document the rationale for Invoice Processing (PO & Non-PO). | P46: Skip documentation to meet speed targets and update records after the close cycle. | Q46: Resolve the item informally without linking the action to controls, metrics or evidence. | R46: B | S46: No | T46: Role Ready | U46: 0.76 | V46: Approved | W46: No | X46: =IF(V46="Approved","Yes","No") -> Yes | Y46: Core Selected Role | Z46: Use role: P2P Senior Associate; skill: Invoice Processing (PO & Non-PO); target L3; behavior: Independently resolves exceptions (price/qty/GR issues); optimizes cycle time; ensures accurate postings. | AA46: Excel formula column in workbook checks SME status.
A47: Q-0044 | B47: BP-005 | C47: Synthetic Hackfest Test Data - AI-generated draft question | D47: AP | E47: AP_p2p_senior_associate | F47: P2P Senior Associate | G47: AP_3_way_match_exception_handling | H47: 3-Way Match & Exception Handling | I47: 3 | J47: AI-generated from JD/role profile + skill definition | K47: Generated for Hackfest; SME must approve before scheduling | L47: Multiple Choice - Scenario | M47: For the role P2P Senior Associate, which action best demonstrates Proficient capability in 3-Way Match & Exception Handling? | N47: Follow the standard SOP only when instructed and wait for review before taking action. | O47: Apply the SOP, maintain evidence, escalate exceptions, and document the rationale for 3-Way Match & Exception Handling. | P47: Skip documentation to meet speed targets and update records after the close cycle. | Q47: Resolve the item informally without linking the action to controls, metrics or evidence. | R47: B | S47: No | T47: Role Ready | U47: 0.83 | V47: Pending SME Review | W47: Yes | X47: =IF(V47="Approved","Yes","No") -> No | Y47: Core Selected Role | Z47: Use role: P2P Senior Associate; skill: 3-Way Match & Exception Handling; target L3; behavior: Independently investigates match breaks; coordinates with Procurement/Receiving; closes root causes. | AA47: Excel formula column in workbook checks SME status.
A48: Q-0045 | B48: BP-005 | C48: Synthetic Hackfest Test Data - AI-generated draft question | D48: AP | E48: AP_p2p_senior_associate | F48: P2P Senior Associate | G48: AP_payments_execution_runs_methods | H48: Payments Execution (Runs/Methods) | I48: 3 | J48: AI-generated from JD/role profile + skill definition | K48: Generated for Hackfest; SME must approve before scheduling | L48: Multiple Choice - Scenario | M48: For the role P2P Senior Associate, which action best demonstrates Proficient capability in Payments Execution (Runs/Methods)? | N48: Follow the standard SOP only when instructed and wait for review before taking action. | O48: Apply the SOP, maintain evidence, escalate exceptions, and document the rationale for Payments Execution (Runs/Methods). | P48: Skip documentation to meet speed targets and update records after the close cycle. | Q48: Resolve the item informally without linking the action to controls, metrics or evidence. | R48: B | S48: No | T48: Role Ready | U48: 0.84 | V48: Approved | W48: No | X48: =IF(V48="Approved","Yes","No") -> Yes | Y48: Core Selected Role | Z48: Use role: P2P Senior Associate; skill: Payments Execution (Runs/Methods); target L3; behavior: Independently manages payment execution; resolves payment failures; ensures on-time, accurate disbursements. | AA48: Excel formula column in workbook checks SME status.
A49: Q-0046 | B49: BP-005 | C49: Synthetic Hackfest Test Data - AI-generated draft question | D49: AP | E49: AP_p2p_senior_associate | F49: P2P Senior Associate | G49: AP_tax_withholding_regulatory_basics | H49: Tax / Withholding & Regulatory Basics | I49: 3 | J49: AI-generated from JD/role profile + skill definition | K49: Generated for Hackfest; SME must approve before scheduling | L49: Multiple Choice - Scenario | M49: For the role P2P Senior Associate, which action best demonstrates Proficient capability in Tax / Withholding & Regulatory Basics? | N49: Follow the standard SOP only when instructed and wait for review before taking action. | O49: Apply the SOP, maintain evidence, escalate exceptions, and document the rationale for Tax / Withholding & Regulatory Basics. | P49: Skip documentation to meet speed targets and update records after the close cycle. | Q49: Resolve the item informally without linking the action to controls, metrics or evidence. | R49: B | S49: No | T49: Role Ready | U49: 0.72 | V49: Pending SME Review | W49: Yes | X49: =IF(V49="Approved","Yes","No") -> No | Y49: Core Selected Role | Z49: Use role: P2P Senior Associate; skill: Tax / Withholding & Regulatory Basics; target L3; behavior: Independently validates tax treatment for non-routine invoices; partners with Tax/Finance for resolution. | AA49: Excel formula column in workbook checks SME status.
A50: Q-0047 | B50: BP-005 | C50: Synthetic Hackfest Test Data - AI-generated draft question | D50: AP | E50: AP_p2p_senior_associate | F50: P2P Senior Associate | G50: AP_ap_reconciliations_subledger_gl_vendor_statements | H50: AP Reconciliations (Subledger/GL, Vendor Statements) | I50: 3 | J50: AI-generated from JD/role profile + skill definition | K50: Generated for Hackfest; SME must approve before scheduling | L50: Multiple Choice - Scenario | M50: For the role P2P Senior Associate, which action best demonstrates Proficient capability in AP Reconciliations (Subledger/GL, Vendor Statements)? | N50: Follow the standard SOP only when instructed and wait for review before taking action. | O50: Apply the SOP, maintain evidence, escalate exceptions, and document the rationale for AP Reconciliations (Subledger/GL, Vendor Statements). | P50: Skip documentation to meet speed targets and update records after the close cycle. | Q50: Resolve the item informally without linking the action to controls, metrics or evidence. | R50: B | S50: No | T50: Role Ready | U50: 0.87 | V50: Pending SME Review | W50: Yes | X50: =IF(V50="Approved","Yes","No") -> No | Y50: Core Selected Role | Z50: Use role: P2P Senior Associate; skill: AP Reconciliations (Subledger/GL, Vendor Statements); target L3; behavior: Independently resolves discrepancies; improves reconciliation quality and cycle time; maintains evidence trail. | AA50: Excel formula column in workbook checks SME status.
A51: Q-0048 | B51: BP-005 | C51: Synthetic Hackfest Test Data - AI-generated draft question | D51: AP | E51: AP_p2p_senior_associate | F51: P2P Senior Associate | G51: AP_close_activities_accruals_cutoff_gr_ir | H51: Close Activities (Accruals, Cutoff, GR/IR) | I51: 3 | J51: AI-generated from JD/role profile + skill definition | K51: Generated for Hackfest; SME must approve before scheduling | L51: Multiple Choice - Scenario | M51: For the role P2P Senior Associate, which action best demonstrates Proficient capability in Close Activities (Accruals, Cutoff, GR/IR)? | N51: Follow the standard SOP only when instructed and wait for review before taking action. | O51: Apply the SOP, maintain evidence, escalate exceptions, and document the rationale for Close Activities (Accruals, Cutoff, GR/IR). | P51: Skip documentation to meet speed targets and update records after the close cycle. | Q51: Resolve the item informally without linking the action to controls, metrics or evidence. | R51: B | S51: No | T51: Role Ready | U51: 0.75 | V51: Approved | W51: No | X51: =IF(V51="Approved","Yes","No") -> Yes | Y51: Core Selected Role | Z51: Use role: P2P Senior Associate; skill: Close Activities (Accruals, Cutoff, GR/IR); target L3; behavior: Independently manages AP close tasks; resolves GR/IR and cutoff issues; improves timeliness. | AA51: Excel formula column in workbook checks SME status.
... A118: Q-0115 | B118: BP-002 | C118: Synthetic Hackfest Test Data - AI-generated draft question | D118: R2R | E118: R2R_ga_preparer_job_preparation_only | F118: GA Preparer Job (Preparation-only) | G118: R2R_teamwork_collaboration | H118: Teamwork / Collaboration | I118: 4 | J118: AI-generated from JD/role profile + skill definition | K118: Generated for Hackfest; SME must approve before scheduling | L118: Multiple Choice - Scenario | M118: For the role GA Preparer Job (Preparation-only), which action best demonstrates Advanced/Specialist capability in Teamwork / Collaboration? | N118: Follow the standard SOP only when instructed and wait for review before taking action. | O118: Apply the SOP, maintain evidence, escalate exceptions, and document the rationale for Teamwork / Collaboration. | P118: Skip documentation to meet speed targets and update records after the close cycle. | Q118: Resolve the item informally without linking the action to controls, metrics or evidence. | R118: B | S118: No | T118: Advanced | U118: 0.84 | V118: Approved | W118: No | X118: =IF(V118="Approved","Yes","No") -> Yes | Y118: Core Selected Role | Z118: Use role: GA Preparer Job (Preparation-only); skill: Teamwork / Collaboration; target L4; behavior: | AA118: Excel formula column in workbook checks SME status.

Sheet SME_Review_Workflow
A1: SME Review Workflow
A3: review_id | B3: data_label | C3: question_id | D3: blueprint_id | E3: role_id | F3: skill_id | G3: sme_reviewer_role | H3: review_round | I3: sme_review_status | J3: sme_decision | K3: sme_comments_synthetic | L3: review_date_synthetic | M3: human_in_loop_gate
A4: SME-0001 | B4: Synthetic Hackfest Test Data - SME workflow placeholder | C4: Q-0001 | D4: BP-004 | E4: AP_p2p_lead | F4: AP_sla_governance_metrics | G4: Tower SME / Controller / Capability Owner placeholder | H4: 1 | I4: Approved | J4: Approve as-is | K4: Synthetic review note only - no real manager or SME comments | L4: 2026-09-06 | M4: Required before schedule
A5: SME-0002 | B5: Synthetic Hackfest Test Data - SME workflow placeholder | C5: Q-0002 | D5: BP-006 | E5: AP_t_e_lead | F5: AP_sla_governance_metrics | G5: Tower SME / Controller / Capability Owner placeholder | H5: 1 | I5: Approved | J5: Approve as-is | K5: Synthetic review note only - no real manager or SME comments | L5: 2026-09-07 | M5: Required before schedule
A6: SME-0003 | B6: Synthetic Hackfest Test Data - SME workflow placeholder | C6: Q-0003 | D6: BP-004 | E6: AP_p2p_lead | F6: AP_first_time_right_quality | G6: Tower SME / Controller / Capability Owner placeholder | H6: 1 | I6: Approved | J6: Approve as-is | K6: Synthetic review note only - no real manager or SME comments | L6: 2026-09-08 | M6: Required before schedule
A7: SME-0004 | B7: Synthetic Hackfest Test Data - SME workflow placeholder | C7: Q-0004 | D7: BP-006 | E7: AP_t_e_lead | F7: AP_work_intake_prioritization_backlog_mgmt | G7: Tower SME / Controller / Capability Owner placeholder | H7: 1 | I7: Approved | J7: Approve as-is | K7: Synthetic review note only - no real manager or SME comments | L7: 2026-09-09 | M7: Required before schedule
A8: SME-0005 | B8: Synthetic Hackfest Test Data - SME workflow placeholder | C8: Q-0005 | D8: BP-004 | E8: AP_p2p_lead | F8: AP_first_time_right_quality | G8: Tower SME / Controller / Capability Owner placeholder | H8: 1 | I8: Approved | J8: Approve as-is | K8: Synthetic review note only - no real manager or SME comments | L8: 2026-09-10 | M8: Required before schedule
A9: SME-0006 | B9: Synthetic Hackfest Test Data - SME workflow placeholder | C9: Q-0006 | D9: BP-006 | E9: AP_t_e_lead | F9: AP_first_time_right_quality | G9: Tower SME / Controller / Capability Owner placeholder | H9: 1 | I9: Approved | J9: Approve as-is | K9: Synthetic review note only - no real manager or SME comments | L9: 2026-09-11 | M9: Required before schedule
A10: SME-0007 | B10: Synthetic Hackfest Test Data - SME workflow placeholder | C10: Q-0007 | D10: BP-004 | E10: AP_p2p_lead | F10: AP_controls_compliance_audit_ap | G10: Tower SME / Controller / Capability Owner placeholder | H10: 1 | I10: Approved | J10: Approve as-is | K10: Synthetic review note only - no real manager or SME comments | L10: 2026-09-05 | M10: Required before schedule
A11: SME-0008 | B11: Synthetic Hackfest Test Data - SME workflow placeholder | C11: Q-0008 | D11: BP-006 | E11: AP_t_e_lead | F11: AP_controls_compliance_audit_ap | G11: Tower SME / Controller / Capability Owner placeholder | H11: 1 | I11: Approved | J11: Approve as-is | K11: Synthetic review note only - no real manager or SME comments | L11: 2026-09-06 | M11: Required before schedule
A12: SME-0009 | B12: Synthetic Hackfest Test Data - SME workflow placeholder | C12: Q-0009 | D12: BP-004 | E12: AP_p2p_lead | F12: AP_payments_execution_runs_methods | G12: Tower SME / Controller / Capability Owner placeholder | H12: 1 | I12: Approved | J12: Approve as-is | K12: Synthetic review note only - no real manager or SME comments | L12: 2026-09-07 | M12: Required before schedule
A13: SME-0010 | B13: Synthetic Hackfest Test Data - SME workflow placeholder | C13: Q-0010 | D13: BP-006 | E13: AP_t_e_lead | F13: AP_first_time_right_quality | G13: Tower SME / Controller / Capability Owner placeholder | H13: 1 | I13: Approved | J13: Approve as-is | K13: Synthetic review note only - no real manager or SME comments | L13: 2026-09-08 | M13: Required before schedule
A14: SME-0011 | B14: Synthetic Hackfest Test Data - SME workflow placeholder | C14: Q-0011 | D14: BP-004 | E14: AP_p2p_lead | F14: AP_ap_reconciliations_subledger_gl_vendor_statements | G14: Tower SME / Controller / Capability Owner placeholder | H14: 1 | I14: Approved | J14: Approve as-is | K14: Synthetic review note only - no real manager or SME comments | L14: 2026-09-09 | M14: Required before schedule
A15: SME-0012 | B15: Synthetic Hackfest Test Data - SME workflow placeholder | C15: Q-0012 | D15: BP-006 | E15: AP_t_e_lead | F15: AP_first_time_right_quality | G15: Tower SME / Controller / Capability Owner placeholder | H15: 1 | I15: Approved | J15: Approve as-is | K15: Synthetic review note only - no real manager or SME comments | L15: 2026-09-10 | M15: Required before schedule
... A118: SME-0115 | B118: Synthetic Hackfest Test Data - SME workflow placeholder | C118: Q-0115 | D118: BP-002 | E118: R2R_ga_preparer_job_preparation_only | F118: R2R_teamwork_collaboration | G118: Tower SME / Controller / Capability Owner placeholder | H118: 1 | I118: Approved | J118: Approve as-is | K118: Synthetic review note only - no real manager or SME comments | L118: 2026-09-08 | M118: Required before schedule

Sheet Assessment_Schedules
A1: Assessment Schedules
A3: schedule_id | B3: data_label | C3: blueprint_id | D3: tower | E3: role_id | F3: assessment_name | G3: approved_question_count | H3: target_question_count | I3: schedule_status | J3: planned_launch_date | K3: planned_close_date | L3: cohort_name | M3: scheduler_role | N3: formula_check_note
A4: SCH-001 | B4: Synthetic Hackfest Test Data - scheduling placeholder | C4: BP-001 | D4: R2R | E4: R2R_banking_preparer_job_preparation_cash_posting | F4: R2R Banking Preparer Job (Preparation + Cash Posting) Skill Assessment | G4: =COUNTIFS(Assessment_QBank!B:B,C4,Assessment_QBank!X:X,"Yes",Assessment_QBank!Y:Y,"Core Selected Role") -> 4 | H4: 20 | I4: Needs SME Approval | J4: 2026-09-20 | K4: 2026-09-30 | L4: Hackfest Synthetic Cohort - R2R Banking Preparer Job (Pr | M4: SME/Capability Owner schedules after approval | N4: Workbook formula version counts approved questions.
A5: SCH-002 | B5: Synthetic Hackfest Test Data - scheduling placeholder | C5: BP-002 | D5: R2R | E5: R2R_ga_preparer_job_preparation_only | F5: R2R GA Preparer Job (Preparation-only) Skill Assessment | G5: =COUNTIFS(Assessment_QBank!B:B,C5,Assessment_QBank!X:X,"Yes",Assessment_QBank!Y:Y,"Core Selected Role") -> 6 | H5: 20 | I5: Needs SME Approval | J5: 2026-09-20 | K5: 2026-09-30 | L5: Hackfest Synthetic Cohort - R2R GA Preparer Job (Prepara | M5: SME/Capability Owner schedules after approval | N5: Workbook formula version counts approved questions.
A6: SCH-003 | B6: Synthetic Hackfest Test Data - scheduling placeholder | C6: BP-003 | D6: R2R | E6: R2R_consolidation_preparer_job_execution_pack_prep | F6: R2R Consolidation Preparer Job (Execution + Pack Prep) Skill Assessment | G6: =COUNTIFS(Assessment_QBank!B:B,C6,Assessment_QBank!X:X,"Yes",Assessment_QBank!Y:Y,"Core Selected Role") -> 5 | H6: 20 | I6: Needs SME Approval | J6: 2026-09-20 | K6: 2026-09-30 | L6: Hackfest Synthetic Cohort - R2R Consolidation Preparer J | M6: SME/Capability Owner schedules after approval | N6: Workbook formula version counts approved questions.
A7: SCH-004 | B7: Synthetic Hackfest Test Data - scheduling placeholder | C7: BP-004 | D7: AP | E7: AP_p2p_lead | F7: AP P2P Lead Skill Assessment | G7: =COUNTIFS(Assessment_QBank!B:B,C7,Assessment_QBank!X:X,"Yes",Assessment_QBank!Y:Y,"Core Selected Role") -> 14 | H7: 20 | I7: Ready to Schedule | J7: 2026-09-20 | K7: 2026-09-30 | L7: Hackfest Synthetic Cohort - AP P2P Lead | M7: SME/Capability Owner schedules after approval | N7: Workbook formula version counts approved questions.
A8: SCH-005 | B8: Synthetic Hackfest Test Data - scheduling placeholder | C8: BP-005 | D8: AP | E8: AP_p2p_senior_associate | F8: AP P2P Senior Associate Skill Assessment | G8: =COUNTIFS(Assessment_QBank!B:B,C8,Assessment_QBank!X:X,"Yes",Assessment_QBank!Y:Y,"Core Selected Role") -> 5 | H8: 20 | I8: Needs SME Approval | J8: 2026-09-20 | K8: 2026-09-30 | L8: Hackfest Synthetic Cohort - AP P2P Senior Associate | M8: SME/Capability Owner schedules after approval | N8: Workbook formula version counts approved questions.
A9: SCH-006 | B9: Synthetic Hackfest Test Data - scheduling placeholder | C9: BP-006 | D9: AP | E9: AP_t_e_lead | F9: AP T&E Lead Skill Assessment | G9: =COUNTIFS(Assessment_QBank!B:B,C9,Assessment_QBank!X:X,"Yes",Assessment_QBank!Y:Y,"Core Selected Role") -> 13 | H9: 20 | I9: Ready to Schedule | J9: 2026-09-20 | K9: 2026-09-30 | L9: Hackfest Synthetic Cohort - AP T&E Lead | M9: SME/Capability Owner schedules after approval | N9: Workbook formula version counts approved questions.
A10: SCH-007 | B10: Synthetic Hackfest Test Data - scheduling placeholder | C10: BP-007 | D10: O2C | E10: O2C_billing_team_lead | F10: O2C Billing Team Lead Skill Assessment | G10: =COUNTIFS(Assessment_QBank!B:B,C10,Assessment_QBank!X:X,"Yes",Assessment_QBank!Y:Y,"Core Selected Role") -> 4 | H10: 20 | I10: Needs SME Approval | J10: 2026-09-20 | K10: 2026-09-30 | L10: Hackfest Synthetic Cohort - O2C Billing Team Lead | M10: SME/Capability Owner schedules after approval | N10: Workbook formula version counts approved questions.
A11: SCH-008 | B11: Synthetic Hackfest Test Data - scheduling placeholder | C11: BP-008 | D11: O2C | E11: O2C_associate_revenue_controller | F11: O2C Associate Revenue Controller Skill Assessment | G11: =COUNTIFS(Assessment_QBank!B:B,C11,Assessment_QBank!X:X,"Yes",Assessment_QBank!Y:Y,"Core Selected Role") -> 6 | H11: 20 | I11: Needs SME Approval | J11: 2026-09-20 | K11: 2026-09-30 | L11: Hackfest Synthetic Cohort - O2C Associate Revenue Contro | M11: SME/Capability Owner schedules after approval | N11: Workbook formula version counts approved questions.
A12: SCH-009 | B12: Synthetic Hackfest Test Data - scheduling placeholder | C12: BP-009 | D12: O2C | E12: O2C_senior_revenue_associate | F12: O2C Senior Revenue Associate Skill Assessment | G12: =COUNTIFS(Assessment_QBank!B:B,C12,Assessment_QBank!X:X,"Yes",Assessment_QBank!Y:Y,"Core Selected Role") -> 5 | H12: 20 | I12: Needs SME Approval | J12: 2026-09-20 | K12: 2026-09-30 | L12: Hackfest Synthetic Cohort - O2C Senior Revenue Associate | M12: SME/Capability Owner schedules after approval | N12: Workbook formula version counts approved questions.

Sheet Users_Teams
A1: Users Teams
A3: user_id | B3: synthetic_name | C3: data_label | D3: tower | E3: team_id | F3: role_id | G3: role_name | H3: role_grade | I3: synthetic_manager_id | J3: cohort | K3: person_data_note | L3: team_name | M3: synthetic_manager_name | N3: location
A4: SYN-U001 | B4: Synthetic Associate 001 | C4: Synthetic Hackfest Test Data | D4: R2R | E4: TEAM-R2R-BANKING_PREP | F4: R2R_banking_preparer_job_preparation_cash_posting | G4: Banking Preparer Job (Preparation + Cash Posting) | H4: B3/B4/P3 | I4: SYN-MGR-001 | J4: Hackfest Synthetic Cohort | K4: Synthetic Hackfest Test Data - not traceable to actual employees | L4: R2R Banking & Close | M4: Synthetic Manager 001 | N4: Synthetic Global Hub
A5: SYN-U002 | B5: Synthetic Associate 002 | C5: Synthetic Hackfest Test Data | D5: R2R | E5: TEAM-R2R-BANKING_PREP | F5: R2R_banking_preparer_job_preparation_cash_posting | G5: Banking Preparer Job (Preparation + Cash Posting) | H5: B3/B4/P3 | I5: SYN-MGR-001 | J5: Hackfest Synthetic Cohort | K5: Synthetic Hackfest Test Data - not traceable to actual employees | L5: R2R Banking & Close | M5: Synthetic Manager 001 | N5: Synthetic Global Hub
A6: SYN-U003 | B6: Synthetic Associate 003 | C6: Synthetic Hackfest Test Data | D6: R2R | E6: TEAM-R2R-BANKING_PREP | F6: R2R_banking_preparer_job_preparation_cash_posting | G6: Banking Preparer Job (Preparation + Cash Posting) | H6: B3/B4/P3 | I6: SYN-MGR-001 | J6: Hackfest Synthetic Cohort | K6: Synthetic Hackfest Test Data - not traceable to actual employees | L6: R2R Banking & Close | M6: Synthetic Manager 001 | N6: Synthetic Global Hub
A7: SYN-U004 | B7: Synthetic Associate 004 | C7: Synthetic Hackfest Test Data | D7: R2R | E7: TEAM-R2R-BANKING_PREP | F7: R2R_banking_preparer_job_preparation_cash_posting | G7: Banking Preparer Job (Preparation + Cash Posting) | H7: B3/B4/P3 | I7: SYN-MGR-001 | J7: Hackfest Synthetic Cohort | K7: Synthetic Hackfest Test Data - not traceable to actual employees | L7: R2R Banking & Close | M7: Synthetic Manager 001 | N7: Synthetic Global Hub
A8: SYN-U005 | B8: Synthetic Associate 005 | C8: Synthetic Hackfest Test Data | D8: R2R | E8: TEAM-R2R-GA_PREPARER_ | F8: R2R_ga_preparer_job_preparation_only | G8: GA Preparer Job (Preparation-only) | H8: B3/B4/P3 | I8: SYN-MGR-002 | J8: Hackfest Synthetic Cohort | K8: Synthetic Hackfest Test Data - not traceable to actual employees | L8: R2R Banking & Close | M8: Synthetic Manager 002 | N8: Synthetic Global Hub
A9: SYN-U006 | B9: Synthetic Associate 006 | C9: Synthetic Hackfest Test Data | D9: R2R | E9: TEAM-R2R-GA_PREPARER_ | F9: R2R_ga_preparer_job_preparation_only | G9: GA Preparer Job (Preparation-only) | H9: B3/B4/P3 | I9: SYN-MGR-002 | J9: Hackfest Synthetic Cohort | K9: Synthetic Hackfest Test Data - not traceable to actual employees | L9: R2R Banking & Close | M9: Synthetic Manager 002 | N9: Synthetic Global Hub
A10: SYN-U007 | B10: Synthetic Associate 007 | C10: Synthetic Hackfest Test Data | D10: R2R | E10: TEAM-R2R-GA_PREPARER_ | F10: R2R_ga_preparer_job_preparation_only | G10: GA Preparer Job (Preparation-only) | H10: B3/B4/P3 | I10: SYN-MGR-002 | J10: Hackfest Synthetic Cohort | K10: Synthetic Hackfest Test Data - not traceable to actual employees | L10: R2R Banking & Close | M10: Synthetic Manager 002 | N10: Synthetic Global Hub
A11: SYN-U008 | B11: Synthetic Associate 008 | C11: Synthetic Hackfest Test Data | D11: R2R | E11: TEAM-R2R-GA_PREPARER_ | F11: R2R_ga_preparer_job_preparation_only | G11: GA Preparer Job (Preparation-only) | H11: B3/B4/P3 | I11: SYN-MGR-002 | J11: Hackfest Synthetic Cohort | K11: Synthetic Hackfest Test Data - not traceable to actual employees | L11: R2R Banking & Close | M11: Synthetic Manager 002 | N11: Synthetic Global Hub
A12: SYN-U009 | B12: Synthetic Associate 009 | C12: Synthetic Hackfest Test Data | D12: R2R | E12: TEAM-R2R-CONSOLIDATIO | F12: R2R_consolidation_preparer_job_execution_pack_prep | G12: Consolidation Preparer Job (Execution + Pack Prep) | H12: P3/P4 | I12: SYN-MGR-003 | J12: Hackfest Synthetic Cohort | K12: Synthetic Hackfest Test Data - not traceable to actual employees | L12: R2R Banking & Close | M12: Synthetic Manager 003 | N12: Synthetic Global Hub
A13: SYN-U010 | B13: Synthetic Associate 010 | C13: Synthetic Hackfest Test Data | D13: R2R | E13: TEAM-R2R-CONSOLIDATIO | F13: R2R_consolidation_preparer_job_execution_pack_prep | G13: Consolidation Preparer Job (Execution + Pack Prep) | H13: P3/P4 | I13: SYN-MGR-003 | J13: Hackfest Synthetic Cohort | K13: Synthetic Hackfest Test Data - not traceable to actual employees | L13: R2R Banking & Close | M13: Synthetic Manager 003 | N13: Synthetic Global Hub
A14: SYN-U011 | B14: Synthetic Associate 011 | C14: Synthetic Hackfest Test Data | D14: R2R | E14: TEAM-R2R-CONSOLIDATIO | F14: R2R_consolidation_preparer_job_execution_pack_prep | G14: Consolidation Preparer Job (Execution + Pack Prep) | H14: P3/P4 | I14: SYN-MGR-003 | J14: Hackfest Synthetic Cohort | K14: Synthetic Hackfest Test Data - not traceable to actual employees | L14: R2R Banking & Close | M14: Synthetic Manager 003 | N14: Synthetic Global Hub
... A39: SYN-U036 | B39: Synthetic Associate 036 | C39: Synthetic Hackfest Test Data | D39: O2C | E39: TEAM-O2C-SENIOR_REVEN | F39: O2C_senior_revenue_associate | G39: Senior Revenue Associate | H39: B3 | I39: SYN-MGR-009 | J39: Hackfest Synthetic Cohort | K39: Synthetic Hackfest Test Data - not traceable to actual employees | L39: O2C Billing & Revenue Ops | M39: Synthetic Manager 009 | N39: Synthetic Global Hub

Sheet Assessment_Assignments
A1: Assessment Assignments
A3: assignment_id | B3: data_label | C3: user_id | D3: role_id | E3: blueprint_id | F3: schedule_id | G3: assigned_date | H3: due_date | I3: assignment_status | J3: notes
A4: ASG-0001 | B4: Synthetic Hackfest Test Data | C4: SYN-U001 | D4: R2R_banking_preparer_job_preparation_cash_posting | E4: BP-001 | F4: SCH-001 | G4: 2026-09-18 | H4: 2026-09-30 | I4: Completed | J4: Synthetic assignment only
A5: ASG-0002 | B5: Synthetic Hackfest Test Data | C5: SYN-U002 | D5: R2R_banking_preparer_job_preparation_cash_posting | E5: BP-001 | F5: SCH-001 | G5: 2026-09-18 | H5: 2026-09-30 | I5: Completed | J5: Synthetic assignment only
A6: ASG-0003 | B6: Synthetic Hackfest Test Data | C6: SYN-U003 | D6: R2R_banking_preparer_job_preparation_cash_posting | E6: BP-001 | F6: SCH-001 | G6: 2026-09-18 | H6: 2026-09-30 | I6: Not Started | J6: Synthetic assignment only
A7: ASG-0004 | B7: Synthetic Hackfest Test Data | C7: SYN-U004 | D7: R2R_banking_preparer_job_preparation_cash_posting | E7: BP-001 | F7: SCH-001 | G7: 2026-09-18 | H7: 2026-09-30 | I7: In Progress | J7: Synthetic assignment only
A8: ASG-0005 | B8: Synthetic Hackfest Test Data | C8: SYN-U005 | D8: R2R_ga_preparer_job_preparation_only | E8: BP-002 | F8: SCH-002 | G8: 2026-09-18 | H8: 2026-09-30 | I8: Completed | J8: Synthetic assignment only
A9: ASG-0006 | B9: Synthetic Hackfest Test Data | C9: SYN-U006 | D9: R2R_ga_preparer_job_preparation_only | E9: BP-002 | F9: SCH-002 | G9: 2026-09-18 | H9: 2026-09-30 | I9: Completed | J9: Synthetic assignment only
A10: ASG-0007 | B10: Synthetic Hackfest Test Data | C10: SYN-U007 | D10: R2R_ga_preparer_job_preparation_only | E10: BP-002 | F10: SCH-002 | G10: 2026-09-18 | H10: 2026-09-30 | I10: Completed | J10: Synthetic assignment only
A11: ASG-0008 | B11: Synthetic Hackfest Test Data | C11: SYN-U008 | D11: R2R_ga_preparer_job_preparation_only | E11: BP-002 | F11: SCH-002 | G11: 2026-09-18 | H11: 2026-09-30 | I11: In Progress | J11: Synthetic assignment only
A12: ASG-0009 | B12: Synthetic Hackfest Test Data | C12: SYN-U009 | D12: R2R_consolidation_preparer_job_execution_pack_prep | E12: BP-003 | F12: SCH-003 | G12: 2026-09-18 | H12: 2026-09-30 | I12: Completed | J12: Synthetic assignment only
A13: ASG-0010 | B13: Synthetic Hackfest Test Data | C13: SYN-U010 | D13: R2R_consolidation_preparer_job_execution_pack_prep | E13: BP-003 | F13: SCH-003 | G13: 2026-09-18 | H13: 2026-09-30 | I13: In Progress | J13: Synthetic assignment only
A14: ASG-0011 | B14: Synthetic Hackfest Test Data | C14: SYN-U011 | D14: R2R_consolidation_preparer_job_execution_pack_prep | E14: BP-003 | F14: SCH-003 | G14: 2026-09-18 | H14: 2026-09-30 | I14: In Progress | J14: Synthetic assignment only
... A39: ASG-0036 | B39: Synthetic Hackfest Test Data | C39: SYN-U036 | D39: O2C_senior_revenue_associate | E39: BP-009 | F39: SCH-009 | G39: 2026-09-18 | H39: 2026-09-30 | I39: Completed | J39: Synthetic assignment only

Sheet Assessment_Results
A1: Assessment Results
A3: result_id | B3: data_label | C3: assignment_id | D3: user_id | E3: role_id | F3: blueprint_id | G3: schedule_id | H3: score_pct | I3: pass_threshold_pct | J3: critical_fail_flag | K3: pass_fail_formula | L3: recommended_current_level | M3: result_status | N3: ai_result_note
A4: RST-0001 | B4: Synthetic Hackfest Test Data | C4: ASG-0001 | D4: SYN-U001 | E4: R2R_banking_preparer_job_preparation_cash_posting | F4: BP-001 | G4: SCH-001 | H4: 72 | I4: 75 | J4: No | K4: =IF(H4="","No Result",IF(AND(H4>=I4,J4<>"Yes"),"Pass","Fail")) -> Fail | L4: 2 | M4: Scored | N4: Synthetic score and current-level recommendation; SME may calibrate before use
A5: RST-0002 | B5: Synthetic Hackfest Test Data | C5: ASG-0002 | D5: SYN-U002 | E5: R2R_banking_preparer_job_preparation_cash_posting | F5: BP-001 | G5: SCH-001 | H5: 61 | I5: 75 | J5: Yes | K5: =IF(H5="","No Result",IF(AND(H5>=I5,J5<>"Yes"),"Pass","Fail")) -> Fail | L5: 2 | M5: Scored | N5: Synthetic score and current-level recommendation; SME may calibrate before use
A6: RST-0003 | B6: Synthetic Hackfest Test Data | C6: ASG-0003 | D6: SYN-U003 | E6: R2R_banking_preparer_job_preparation_cash_posting | F6: BP-001 | G6: SCH-001 | I6: 75 | K6: =IF(H6="","No Result",IF(AND(H6>=I6,J6<>"Yes"),"Pass","Fail")) -> No Result | M6: No Result Yet | N6: Synthetic score and current-level recommendation; SME may calibrate before use
A7: RST-0004 | B7: Synthetic Hackfest Test Data | C7: ASG-0004 | D7: SYN-U004 | E7: R2R_banking_preparer_job_preparation_cash_posting | F7: BP-001 | G7: SCH-001 | I7: 75 | K7: =IF(H7="","No Result",IF(AND(H7>=I7,J7<>"Yes"),"Pass","Fail")) -> No Result | M7: No Result Yet | N7: Synthetic score and current-level recommendation; SME may calibrate before use
A8: RST-0005 | B8: Synthetic Hackfest Test Data | C8: ASG-0005 | D8: SYN-U005 | E8: R2R_ga_preparer_job_preparation_only | F8: BP-002 | G8: SCH-002 | H8: 73 | I8: 75 | J8: No | K8: =IF(H8="","No Result",IF(AND(H8>=I8,J8<>"Yes"),"Pass","Fail")) -> Fail | L8: 2 | M8: Scored | N8: Synthetic score and current-level recommendation; SME may calibrate before use
A9: RST-0006 | B9: Synthetic Hackfest Test Data | C9: ASG-0006 | D9: SYN-U006 | E9: R2R_ga_preparer_job_preparation_only | F9: BP-002 | G9: SCH-002 | H9: 89 | I9: 75 | J9: No | K9: =IF(H9="","No Result",IF(AND(H9>=I9,J9<>"Yes"),"Pass","Fail")) -> Pass | L9: 4 | M9: Scored | N9: Synthetic score and current-level recommendation; SME may calibrate before use
A10: RST-0007 | B10: Synthetic Hackfest Test Data | C10: ASG-0007 | D10: SYN-U007 | E10: R2R_ga_preparer_job_preparation_only | F10: BP-002 | G10: SCH-002 | H10: 66 | I10: 75 | J10: No | K10: =IF(H10="","No Result",IF(AND(H10>=I10,J10<>"Yes"),"Pass","Fail")) -> Fail | L10: 2 | M10: Scored | N10: Synthetic score and current-level recommendation; SME may calibrate before use
A11: RST-0008 | B11: Synthetic Hackfest Test Data | C11: ASG-0008 | D11: SYN-U008 | E11: R2R_ga_preparer_job_preparation_only | F11: BP-002 | G11: SCH-002 | I11: 75 | K11: =IF(H11="","No Result",IF(AND(H11>=I11,J11<>"Yes"),"Pass","Fail")) -> No Result | M11: No Result Yet | N11: Synthetic score and current-level recommendation; SME may calibrate before use
A12: RST-0009 | B12: Synthetic Hackfest Test Data | C12: ASG-0009 | D12: SYN-U009 | E12: R2R_consolidation_preparer_job_execution_pack_prep | F12: BP-003 | G12: SCH-003 | H12: 73 | I12: 75 | J12: No | K12: =IF(H12="","No Result",IF(AND(H12>=I12,J12<>"Yes"),"Pass","Fail")) -> Fail | L12: 2 | M12: Scored | N12: Synthetic score and current-level recommendation; SME may calibrate before use
A13: RST-0010 | B13: Synthetic Hackfest Test Data | C13: ASG-0010 | D13: SYN-U010 | E13: R2R_consolidation_preparer_job_execution_pack_prep | F13: BP-003 | G13: SCH-003 | I13: 75 | K13: =IF(H13="","No Result",IF(AND(H13>=I13,J13<>"Yes"),"Pass","Fail")) -> No Result | M13: No Result Yet | N13: Synthetic score and current-level recommendation; SME may calibrate before use
A14: RST-0011 | B14: Synthetic Hackfest Test Data | C14: ASG-0011 | D14: SYN-U011 | E14: R2R_consolidation_preparer_job_execution_pack_prep | F14: BP-003 | G14: SCH-003 | I14: 75 | K14: =IF(H14="","No Result",IF(AND(H14>=I14,J14<>"Yes"),"Pass","Fail")) -> No Result | M14: No Result Yet | N14: Synthetic score and current-level recommendation; SME may calibrate before use
A15: RST-0012 | B15: Synthetic Hackfest Test Data | C15: ASG-0012 | D15: SYN-U012 | E15: R2R_consolidation_preparer_job_execution_pack_prep | F15: BP-003 | G15: SCH-003 | H15: 64 | I15: 75 | J15: No | K15: =IF(H15="","No Result",IF(AND(H15>=I15,J15<>"Yes"),"Pass","Fail")) -> Fail | L15: 2 | M15: Scored | N15: Synthetic score and current-level recommendation; SME may calibrate before use
A16: RST-0013 | B16: Synthetic Hackfest Test Data | C16: ASG-0013 | D16: SYN-U013 | E16: AP_p2p_lead | F16: BP-004 | G16: SCH-004 | H16: 84 | I16: 75 | J16: No | K16: =IF(H16="","No Result",IF(AND(H16>=I16,J16<>"Yes"),"Pass","Fail")) -> Pass | L16: 3 | M16: Scored | N16: Synthetic score and current-level recommendation; SME may calibrate before use
A17: RST-0014 | B17: Synthetic Hackfest Test Data | C17: ASG-0014 | D17: SYN-U014 | E17: AP_p2p_lead | F17: BP-004 | G17: SCH-004 | H17: 61 | I17: 75 | J17: No | K17: =IF(H17="","No Result",IF(AND(H17>=I17,J17<>"Yes"),"Pass","Fail")) -> Fail | L17: 2 | M17: Scored | N17: Synthetic score and current-level recommendation; SME may calibrate before use
A18: RST-0015 | B18: Synthetic Hackfest Test Data | C18: ASG-0015 | D18: SYN-U015 | E18: AP_p2p_lead | F18: BP-004 | G18: SCH-004 | I18: 75 | K18: =IF(H18="","No Result",IF(AND(H18>=I18,J18<>"Yes"),"Pass","Fail")) -> No Result | M18: No Result Yet | N18: Synthetic score and current-level recommendation; SME may calibrate before use
A19: RST-0016 | B19: Synthetic Hackfest Test Data | C19: ASG-0016 | D19: SYN-U016 | E19: AP_p2p_lead | F19: BP-004 | G19: SCH-004 | H19: 83 | I19: 75 | J19: No | K19: =IF(H19="","No Result",IF(AND(H19>=I19,J19<>"Yes"),"Pass","Fail")) -> Pass | L19: 3 | M19: Scored | N19: Synthetic score and current-level recommendation; SME may calibrate before use
A20: RST-0017 | B20: Synthetic Hackfest Test Data | C20: ASG-0017 | D20: SYN-U017 | E20: AP_p2p_senior_associate | F20: BP-005 | G20: SCH-005 | H20: 64 | I20: 75 | J20: Yes | K20: =IF(H20="","No Result",IF(AND(H20>=I20,J20<>"Yes"),"Pass","Fail")) -> Fail | L20: 2 | M20: Scored | N20: Synthetic score and current-level recommendation; SME may calibrate before use
A21: RST-0018 | B21: Synthetic Hackfest Test Data | C21: ASG-0018 | D21: SYN-U018 | E21: AP_p2p_senior_associate | F21: BP-005 | G21: SCH-005 | H21: 86 | I21: 75 | J21: No | K21: =IF(H21="","No Result",IF(AND(H21>=I21,J21<>"Yes"),"Pass","Fail")) -> Pass | L21: 4 | M21: Scored | N21: Synthetic score and current-level recommendation; SME may calibrate before use
A22: RST-0019 | B22: Synthetic Hackfest Test Data | C22: ASG-0019 | D22: SYN-U019 | E22: AP_p2p_senior_associate | F22: BP-005 | G22: SCH-005 | H22: 69 | I22: 75 | J22: Yes | K22: =IF(H22="","No Result",IF(AND(H22>=I22,J22<>"Yes"),"Pass","Fail")) -> Fail | L22: 2 | M22: Scored | N22: Synthetic score and current-level recommendation; SME may calibrate before use
A23: RST-0020 | B23: Synthetic Hackfest Test Data | C23: ASG-0020 | D23: SYN-U020 | E23: AP_p2p_senior_associate | F23: BP-005 | G23: SCH-005 | H23: 62 | I23: 75 | J23: Yes | K23: =IF(H23="","No Result",IF(AND(H23>=I23,J23<>"Yes"),"Pass","Fail")) -> Fail | L23: 2 | M23: Scored | N23: Synthetic score and current-level recommendation; SME may calibrate before use
A24: RST-0021 | B24: Synthetic Hackfest Test Data | C24: ASG-0021 | D24: SYN-U021 | E24: AP_t_e_lead | F24: BP-006 | G24: SCH-006 | I24: 75 | K24: =IF(H24="","No Result",IF(AND(H24>=I24,J24<>"Yes"),"Pass","Fail")) -> No Result | M24: No Result Yet | N24: Synthetic score and current-level recommendation; SME may calibrate before use
A25: RST-0022 | B25: Synthetic Hackfest Test Data | C25: ASG-0022 | D25: SYN-U022 | E25: AP_t_e_lead | F25: BP-006 | G25: SCH-006 | H25: 61 | I25: 75 | J25: No | K25: =IF(H25="","No Result",IF(AND(H25>=I25,J25<>"Yes"),"Pass","Fail")) -> Fail | L25: 2 | M25: Scored | N25: Synthetic score and current-level recommendation; SME may calibrate before use
A26: RST-0023 | B26: Synthetic Hackfest Test Data | C26: ASG-0023 | D26: SYN-U023 | E26: AP_t_e_lead | F26: BP-006 | G26: SCH-006 | H26: 58 | I26: 75 | J26: No | K26: =IF(H26="","No Result",IF(AND(H26>=I26,J26<>"Yes"),"Pass","Fail")) -> Fail | L26: 1 | M26: Scored | N26: Synthetic score and current-level recommendation; SME may calibrate before use
A27: RST-0024 | B27: Synthetic Hackfest Test Data | C27: ASG-0024 | D27: SYN-U024 | E27: AP_t_e_lead | F27: BP-006 | G27: SCH-006 | I27: 75 | K27: =IF(H27="","No Result",IF(AND(H27>=I27,J27<>"Yes"),"Pass","Fail")) -> No Result | M27: No Result Yet | N27: Synthetic score and current-level recommendation; SME may calibrate before use
A28: RST-0025 | B28: Synthetic Hackfest Test Data | C28: ASG-0025 | D28: SYN-U025 | E28: O2C_billing_team_lead | F28: BP-007 | G28: SCH-007 | I28: 75 | K28: =IF(H28="","No Result",IF(AND(H28>=I28,J28<>"Yes"),"Pass","Fail")) -> No Result | M28: No Result Yet | N28: Synthetic score and current-level recommendation; SME may calibrate before use
A29: RST-0026 | B29: Synthetic Hackfest Test Data | C29: ASG-0026 | D29: SYN-U026 | E29: O2C_billing_team_lead | F29: BP-007 | G29: SCH-007 | H29: 89 | I29: 75 | J29: No | K29: =IF(H29="","No Result",IF(AND(H29>=I29,J29<>"Yes"),"Pass","Fail")) -> Pass | L29: 4 | M29: Scored | N29: Synthetic score and current-level recommendation; SME may calibrate before use
A30: RST-0027 | B30: Synthetic Hackfest Test Data | C30: ASG-0027 | D30: SYN-U027 | E30: O2C_billing_team_lead | F30: BP-007 | G30: SCH-007 | H30: 83 | I30: 75 | J30: No | K30: =IF(H30="","No Result",IF(AND(H30>=I30,J30<>"Yes"),"Pass","Fail")) -> Pass | L30: 3 | M30: Scored | N30: Synthetic score and current-level recommendation; SME may calibrate before use
A31: RST-0028 | B31: Synthetic Hackfest Test Data | C31: ASG-0028 | D31: SYN-U028 | E31: O2C_billing_team_lead | F31: BP-007 | G31: SCH-007 | I31: 75 | K31: =IF(H31="","No Result",IF(AND(H31>=I31,J31<>"Yes"),"Pass","Fail")) -> No Result | M31: No Result Yet | N31: Synthetic score and current-level recommendation; SME may calibrate before use
A32: RST-0029 | B32: Synthetic Hackfest Test Data | C32: ASG-0029 | D32: SYN-U029 | E32: O2C_associate_revenue_controller | F32: BP-008 | G32: SCH-008 | H32: 58 | I32: 75 | J32: No | K32: =IF(H32="","No Result",IF(AND(H32>=I32,J32<>"Yes"),"Pass","Fail")) -> Fail | L32: 1 | M32: Scored | N32: Synthetic score and current-level recommendation; SME may calibrate before use
A33: RST-0030 | B33: Synthetic Hackfest Test Data | C33: ASG-0030 | D33: SYN-U030 | E33: O2C_associate_revenue_controller | F33: BP-008 | G33: SCH-008 | H33: 87 | I33: 75 | J33: No | K33: =IF(H33="","No Result",IF(AND(H33>=I33,J33<>"Yes"),"Pass","Fail")) -> Pass | L33: 4 | M33: Scored | N33: Synthetic score and current-level recommendation; SME may calibrate before use
A34: RST-0031 | B34: Synthetic Hackfest Test Data | C34: ASG-0031 | D34: SYN-U031 | E34: O2C_associate_revenue_controller | F34: BP-008 | G34: SCH-008 | H34: 93 | I34: 75 | J34: No | K34: =IF(H34="","No Result",IF(AND(H34>=I34,J34<>"Yes"),"Pass","Fail")) -> Pass | L34: 4 | M34: Scored | N34: Synthetic score and current-level recommendation; SME may calibrate before use
A35: RST-0032 | B35: Synthetic Hackfest Test Data | C35: ASG-0032 | D35: SYN-U032 | E35: O2C_associate_revenue_controller | F35: BP-008 | G35: SCH-008 | H35: 89 | I35: 75 | J35: No | K35: =IF(H35="","No Result",IF(AND(H35>=I35,J35<>"Yes"),"Pass","Fail")) -> Pass | L35: 4 | M35: Scored | N35: Synthetic score and current-level recommendation; SME may calibrate before use
A36: RST-0033 | B36: Synthetic Hackfest Test Data | C36: ASG-0033 | D36: SYN-U033 | E36: O2C_senior_revenue_associate | F36: BP-009 | G36: SCH-009 | H36: 76 | I36: 75 | J36: No | K36: =IF(H36="","No Result",IF(AND(H36>=I36,J36<>"Yes"),"Pass","Fail")) -> Pass | L36: 3 | M36: Scored | N36: Synthetic score and current-level recommendation; SME may calibrate before use
A37: RST-0034 | B37: Synthetic Hackfest Test Data | C37: ASG-0034 | D37: SYN-U034 | E37: O2C_senior_revenue_associate | F37: BP-009 | G37: SCH-009 | H37: 61 | I37: 75 | J37: No | K37: =IF(H37="","No Result",IF(AND(H37>=I37,J37<>"Yes"),"Pass","Fail")) -> Fail | L37: 2 | M37: Scored | N37: Synthetic score and current-level recommendation; SME may calibrate before use
A38: RST-0035 | B38: Synthetic Hackfest Test Data | C38: ASG-0035 | D38: SYN-U035 | E38: O2C_senior_revenue_associate | F38: BP-009 | G38: SCH-009 | H38: 78 | I38: 75 | J38: No | K38: =IF(H38="","No Result",IF(AND(H38>=I38,J38<>"Yes"),"Pass","Fail")) -> Pass | L38: 3 | M38: Scored | N38: Synthetic score and current-level recommendation; SME may calibrate before use
A39: RST-0036 | B39: Synthetic Hackfest Test Data | C39: ASG-0036 | D39: SYN-U036 | E39: O2C_senior_revenue_associate | F39: BP-009 | G39: SCH-009 | H39: 88 | I39: 75 | J39: No | K39: =IF(H39="","No Result",IF(AND(H39>=I39,J39<>"Yes"),"Pass","Fail")) -> Pass | L39: 4 | M39: Scored | N39: Synthetic score and current-level recommendation; SME may calibrate before use

Sheet User_Skill_Assessments
A1: User Skill Assessments
A3: user_skill_assessment_id | B3: data_label | C3: user_id | D3: role_id | E3: team_id | F3: skill_id | G3: skill | H3: capability | I3: target_level | J3: assessed_current_level | K3: assessment_status | L3: calibration_status | M3: source_result_id | N3: ai_confidence
A4: USA-00001 | B4: Synthetic Hackfest Test Data | C4: SYN-U001 | D4: R2R_banking_preparer_job_preparation_cash_posting | E4: TEAM-R2R-BANKING_PREP | F4: R2R_first_time_right_quality_sox_icfr_ready | G4: First Time Right (Quality, SOX/ICFR-ready) | I4: 3 | J4: 3 | K4: Assessed | L4: Calibrated | M4: RST-0001 | N4: 0.69
A5: USA-00002 | B5: Synthetic Hackfest Test Data | C5: SYN-U001 | D5: R2R_banking_preparer_job_preparation_cash_posting | E5: TEAM-R2R-BANKING_PREP | F5: R2R_attention_to_detail_sox_evidence_trail_documentation | G5: Attention to Detail (SOX evidence trail / documentation) | I5: 4 | J5: 1 | K5: Assessed | L5: Pending SME Calibration | M5: RST-0001 | N5: 0.7
A6: USA-00003 | B6: Synthetic Hackfest Test Data | C6: SYN-U001 | D6: R2R_banking_preparer_job_preparation_cash_posting | E6: TEAM-R2R-BANKING_PREP | F6: R2R_r2r_close_journals_us_gaap_ifrs | G6: R2R Close & Journals (US GAAP / IFRS) | I6: 3 | J6: 2 | K6: Assessed | L6: Calibrated | M6: RST-0001 | N6: 0.74
A7: USA-00004 | B7: Synthetic Hackfest Test Data | C7: SYN-U001 | D7: R2R_banking_preparer_job_preparation_cash_posting | E7: TEAM-R2R-BANKING_PREP | F7: R2R_reconciliations_clearing_sox_ipe_balance_sheet_recs | G7: Reconciliations & Clearing (SOX/IPE balance sheet recs) | I7: 4 | J7: 1 | K7: Assessed | L7: Calibrated | M7: RST-0001 | N7: 0.83
A8: USA-00005 | B8: Synthetic Hackfest Test Data | C8: SYN-U001 | D8: R2R_banking_preparer_job_preparation_cash_posting | E8: TEAM-R2R-BANKING_PREP | F8: R2R_fixed_assets_banking_ias_16_ias_36_asc_360 | G8: Fixed Assets & Banking (IAS 16 / IAS 36 / ASC 360) | I8: 3 | J8: 2 | K8: Assessed | L8: Pending SME Calibration | M8: RST-0001 | N8: 0.87
A9: USA-00006 | B9: Synthetic Hackfest Test Data | C9: SYN-U001 | D9: R2R_banking_preparer_job_preparation_cash_posting | E9: TEAM-R2R-BANKING_PREP | F9: R2R_time_management | G9: Time Management | I9: 4 | J9: 2 | K9: Assessed | L9: Calibrated | M9: RST-0001 | N9: 0.76
A10: USA-00007 | B10: Synthetic Hackfest Test Data | C10: SYN-U001 | D10: R2R_banking_preparer_job_preparation_cash_posting | E10: TEAM-R2R-BANKING_PREP | F10: R2R_productivity_tools_excel_ppt | G10: Productivity Tools (Excel/PPT) | I10: 4 | J10: 3 | K10: Assessed | L10: Calibrated | M10: RST-0001 | N10: 0.83
A11: USA-00008 | B11: Synthetic Hackfest Test Data | C11: SYN-U001 | D11: R2R_banking_preparer_job_preparation_cash_posting | E11: TEAM-R2R-BANKING_PREP | F11: R2R_erp_finance_tools_sap_oracle_blackline_onestream_sox_controls_in_systems | G11: ERP / Finance Tools (SAP/Oracle/BlackLine/OneStream) (SOX controls-in-systems) | I11: 4 | J11: 1 | K11: Assessed | L11: Calibrated | M11: RST-0001 | N11: 0.71
A12: USA-00009 | B12: Synthetic Hackfest Test Data | C12: SYN-U001 | D12: R2R_banking_preparer_job_preparation_cash_posting | E12: TEAM-R2R-BANKING_PREP | F12: R2R_professional_conduct | G12: Professional Conduct | I12: 4 | J12: 1 | K12: Assessed | L12: Calibrated | M12: RST-0001 | N12: 0.72
A13: USA-00010 | B13: Synthetic Hackfest Test Data | C13: SYN-U001 | D13: R2R_banking_preparer_job_preparation_cash_posting | E13: TEAM-R2R-BANKING_PREP | F13: R2R_teamwork_collaboration | G13: Teamwork / Collaboration | I13: 4 | J13: 2 | K13: Assessed | L13: Calibrated | M13: RST-0001 | N13: 0.85
A14: USA-00011 | B14: Synthetic Hackfest Test Data | C14: SYN-U002 | D14: R2R_banking_preparer_job_preparation_cash_posting | E14: TEAM-R2R-BANKING_PREP | F14: R2R_first_time_right_quality_sox_icfr_ready | G14: First Time Right (Quality, SOX/ICFR-ready) | I14: 3 | J14: 3 | K14: Assessed | L14: Calibrated | M14: RST-0002 | N14: 0.92
A15: USA-00012 | B15: Synthetic Hackfest Test Data | C15: SYN-U002 | D15: R2R_banking_preparer_job_preparation_cash_posting | E15: TEAM-R2R-BANKING_PREP | F15: R2R_attention_to_detail_sox_evidence_trail_documentation | G15: Attention to Detail (SOX evidence trail / documentation) | I15: 4 | J15: 3 | K15: Assessed | L15: Pending SME Calibration | M15: RST-0002 | N15: 0.82
... A23: USA-00020 | B23: Synthetic Hackfest Test Data | C23: SYN-U002 | D23: R2R_banking_preparer_job_preparation_cash_posting | E23: TEAM-R2R-BANKING_PREP | F23: R2R_teamwork_collaboration | G23: Teamwork / Collaboration | I23: 4 | J23: 2 | K23: Assessed | L23: Pending SME Calibration | M23: RST-0002 | N23: 0.71
A24: USA-00021 | B24: Synthetic Hackfest Test Data | C24: SYN-U003 | D24: R2R_banking_preparer_job_preparation_cash_posting | E24: TEAM-R2R-BANKING_PREP | F24: R2R_first_time_right_quality_sox_icfr_ready | G24: First Time Right (Quality, SOX/ICFR-ready) | I24: 3 | K24: Not Assessed | L24: Not applicable | M24: RST-0003
A25: USA-00022 | B25: Synthetic Hackfest Test Data | C25: SYN-U003 | D25: R2R_banking_preparer_job_preparation_cash_posting | E25: TEAM-R2R-BANKING_PREP | F25: R2R_attention_to_detail_sox_evidence_trail_documentation | G25: Attention to Detail (SOX evidence trail / documentation) | I25: 4 | K25: Not Assessed | L25: Not applicable | M25: RST-0003
A26: USA-00023 | B26: Synthetic Hackfest Test Data | C26: SYN-U003 | D26: R2R_banking_preparer_job_preparation_cash_posting | E26: TEAM-R2R-BANKING_PREP | F26: R2R_r2r_close_journals_us_gaap_ifrs | G26: R2R Close & Journals (US GAAP / IFRS) | I26: 3 | K26: Not Assessed | L26: Not applicable | M26: RST-0003
A27: USA-00024 | B27: Synthetic Hackfest Test Data | C27: SYN-U003 | D27: R2R_banking_preparer_job_preparation_cash_posting | E27: TEAM-R2R-BANKING_PREP | F27: R2R_reconciliations_clearing_sox_ipe_balance_sheet_recs | G27: Reconciliations & Clearing (SOX/IPE balance sheet recs) | I27: 4 | K27: Not Assessed | L27: Not applicable | M27: RST-0003
A28: USA-00025 | B28: Synthetic Hackfest Test Data | C28: SYN-U003 | D28: R2R_banking_preparer_job_preparation_cash_posting | E28: TEAM-R2R-BANKING_PREP | F28: R2R_fixed_assets_banking_ias_16_ias_36_asc_360 | G28: Fixed Assets & Banking (IAS 16 / IAS 36 / ASC 360) | I28: 3 | K28: Not Assessed | L28: Not applicable | M28: RST-0003
A29: USA-00026 | B29: Synthetic Hackfest Test Data | C29: SYN-U003 | D29: R2R_banking_preparer_job_preparation_cash_posting | E29: TEAM-R2R-BANKING_PREP | F29: R2R_time_management | G29: Time Management | I29: 4 | K29: Not Assessed | L29: Not applicable | M29: RST-0003
A30: USA-00027 | B30: Synthetic Hackfest Test Data | C30: SYN-U003 | D30: R2R_banking_preparer_job_preparation_cash_posting | E30: TEAM-R2R-BANKING_PREP | F30: R2R_productivity_tools_excel_ppt | G30: Productivity Tools (Excel/PPT) | I30: 4 | K30: Not Assessed | L30: Not applicable | M30: RST-0003
A31: USA-00028 | B31: Synthetic Hackfest Test Data | C31: SYN-U003 | D31: R2R_banking_preparer_job_preparation_cash_posting | E31: TEAM-R2R-BANKING_PREP | F31: R2R_erp_finance_tools_sap_oracle_blackline_onestream_sox_controls_in_systems | G31: ERP / Finance Tools (SAP/Oracle/BlackLine/OneStream) (SOX controls-in-systems) | I31: 4 | K31: Not Assessed | L31: Not applicable | M31: RST-0003
A32: USA-00029 | B32: Synthetic Hackfest Test Data | C32: SYN-U003 | D32: R2R_banking_preparer_job_preparation_cash_posting | E32: TEAM-R2R-BANKING_PREP | F32: R2R_professional_conduct | G32: Professional Conduct | I32: 4 | K32: Not Assessed | L32: Not applicable | M32: RST-0003
A33: USA-00030 | B33: Synthetic Hackfest Test Data | C33: SYN-U003 | D33: R2R_banking_preparer_job_preparation_cash_posting | E33: TEAM-R2R-BANKING_PREP | F33: R2R_teamwork_collaboration | G33: Teamwork / Collaboration | I33: 4 | K33: Not Assessed | L33: Not applicable | M33: RST-0003
A34: USA-00031 | B34: Synthetic Hackfest Test Data | C34: SYN-U004 | D34: R2R_banking_preparer_job_preparation_cash_posting | E34: TEAM-R2R-BANKING_PREP | F34: R2R_first_time_right_quality_sox_icfr_ready | G34: First Time Right (Quality, SOX/ICFR-ready) | I34: 3 | K34: Not Assessed | L34: Not applicable | M34: RST-0004
A35: USA-00032 | B35: Synthetic Hackfest Test Data | C35: SYN-U004 | D35: R2R_banking_preparer_job_preparation_cash_posting | E35: TEAM-R2R-BANKING_PREP | F35: R2R_attention_to_detail_sox_evidence_trail_documentation | G35: Attention to Detail (SOX evidence trail / documentation) | I35: 4 | K35: Not Assessed | L35: Not applicable | M35: RST-0004
... A43: USA-00040 | B43: Synthetic Hackfest Test Data | C43: SYN-U004 | D43: R2R_banking_preparer_job_preparation_cash_posting | E43: TEAM-R2R-BANKING_PREP | F43: R2R_teamwork_collaboration | G43: Teamwork / Collaboration | I43: 4 | K43: Not Assessed | L43: Not applicable | M43: RST-0004
A44: USA-00041 | B44: Synthetic Hackfest Test Data | C44: SYN-U005 | D44: R2R_ga_preparer_job_preparation_only | E44: TEAM-R2R-GA_PREPARER_ | F44: R2R_first_time_right_quality_sox_icfr_ready | G44: First Time Right (Quality, SOX/ICFR-ready) | I44: 3 | J44: 2 | K44: Assessed | L44: Calibrated | M44: RST-0005 | N44: 0.92
A45: USA-00042 | B45: Synthetic Hackfest Test Data | C45: SYN-U005 | D45: R2R_ga_preparer_job_preparation_only | E45: TEAM-R2R-GA_PREPARER_ | F45: R2R_attention_to_detail_sox_evidence_trail_documentation | G45: Attention to Detail (SOX evidence trail / documentation) | I45: 4 | J45: 2 | K45: Assessed | L45: Calibrated | M45: RST-0005 | N45: 0.91
A46: USA-00043 | B46: Synthetic Hackfest Test Data | C46: SYN-U005 | D46: R2R_ga_preparer_job_preparation_only | E46: TEAM-R2R-GA_PREPARER_ | F46: R2R_r2r_close_journals_us_gaap_ifrs | G46: R2R Close & Journals (US GAAP / IFRS) | I46: 3 | J46: 2 | K46: Assessed | L46: Calibrated | M46: RST-0005 | N46: 0.92
A47: USA-00044 | B47: Synthetic Hackfest Test Data | C47: SYN-U005 | D47: R2R_ga_preparer_job_preparation_only | E47: TEAM-R2R-GA_PREPARER_ | F47: R2R_reconciliations_clearing_sox_ipe_balance_sheet_recs | G47: Reconciliations & Clearing (SOX/IPE balance sheet recs) | I47: 4 | J47: 2 | K47: Assessed | L47: Calibrated | M47: RST-0005 | N47: 0.71
A48: USA-00045 | B48: Synthetic Hackfest Test Data | C48: SYN-U005 | D48: R2R_ga_preparer_job_preparation_only | E48: TEAM-R2R-GA_PREPARER_ | F48: R2R_ownership_delivery | G48: Ownership & Delivery | I48: 3 | J48: 2 | K48: Assessed | L48: Calibrated | M48: RST-0005 | N48: 0.8
A49: USA-00046 | B49: Synthetic Hackfest Test Data | C49: SYN-U005 | D49: R2R_ga_preparer_job_preparation_only | E49: TEAM-R2R-GA_PREPARER_ | F49: R2R_time_management | G49: Time Management | I49: 4 | J49: 2 | K49: Assessed | L49: Calibrated | M49: RST-0005 | N49: 0.78
A50: USA-00047 | B50: Synthetic Hackfest Test Data | C50: SYN-U005 | D50: R2R_ga_preparer_job_preparation_only | E50: TEAM-R2R-GA_PREPARER_ | F50: R2R_productivity_tools_excel_ppt | G50: Productivity Tools (Excel/PPT) | I50: 4 | J50: 1 | K50: Assessed | L50: Calibrated | M50: RST-0005 | N50: 0.85
A51: USA-00048 | B51: Synthetic Hackfest Test Data | C51: SYN-U005 | D51: R2R_ga_preparer_job_preparation_only | E51: TEAM-R2R-GA_PREPARER_ | F51: R2R_erp_finance_tools_sap_oracle_blackline_onestream_sox_controls_in_systems | G51: ERP / Finance Tools (SAP/Oracle/BlackLine/OneStream) (SOX controls-in-systems) | I51: 4 | J51: 3 | K51: Assessed | L51: Pending SME Calibration | M51: RST-0005 | N51: 0.91
A52: USA-00049 | B52: Synthetic Hackfest Test Data | C52: SYN-U005 | D52: R2R_ga_preparer_job_preparation_only | E52: TEAM-R2R-GA_PREPARER_ | F52: R2R_professional_conduct | G52: Professional Conduct | I52: 4 | J52: 2 | K52: Assessed | L52: Calibrated | M52: RST-0005 | N52: 0.69
A53: USA-00050 | B53: Synthetic Hackfest Test Data | C53: SYN-U005 | D53: R2R_ga_preparer_job_preparation_only | E53: TEAM-R2R-GA_PREPARER_ | F53: R2R_teamwork_collaboration | G53: Teamwork / Collaboration | I53: 4 | J53: 2 | K53: Assessed | L53: Calibrated | M53: RST-0005 | N53: 0.79
A54: USA-00051 | B54: Synthetic Hackfest Test Data | C54: SYN-U006 | D54: R2R_ga_preparer_job_preparation_only | E54: TEAM-R2R-GA_PREPARER_ | F54: R2R_first_time_right_quality_sox_icfr_ready | G54: First Time Right (Quality, SOX/ICFR-ready) | I54: 3 | J54: 3 | K54: Assessed | L54: Calibrated | M54: RST-0006 | N54: 0.75
A55: USA-00052 | B55: Synthetic Hackfest Test Data | C55: SYN-U006 | D55: R2R_ga_preparer_job_preparation_only | E55: TEAM-R2R-GA_PREPARER_ | F55: R2R_attention_to_detail_sox_evidence_trail_documentation | G55: Attention to Detail (SOX evidence trail / documentation) | I55: 4 | J55: 3 | K55: Assessed | L55: Calibrated | M55: RST-0006 | N55: 0.82
... A73: USA-00070 | B73: Synthetic Hackfest Test Data | C73: SYN-U007 | D73: R2R_ga_preparer_job_preparation_only | E73: TEAM-R2R-GA_PREPARER_ | F73: R2R_teamwork_collaboration | G73: Teamwork / Collaboration | I73: 4 | J73: 2 | K73: Assessed | L73: Calibrated | M73: RST-0007 | N73: 0.8
A74: USA-00071 | B74: Synthetic Hackfest Test Data | C74: SYN-U008 | D74: R2R_ga_preparer_job_preparation_only | E74: TEAM-R2R-GA_PREPARER_ | F74: R2R_first_time_right_quality_sox_icfr_ready | G74: First Time Right (Quality, SOX/ICFR-ready) | I74: 3 | K74: Not Assessed | L74: Not applicable | M74: RST-0008
A75: USA-00072 | B75: Synthetic Hackfest Test Data | C75: SYN-U008 | D75: R2R_ga_preparer_job_preparation_only | E75: TEAM-R2R-GA_PREPARER_ | F75: R2R_attention_to_detail_sox_evidence_trail_documentation | G75: Attention to Detail (SOX evidence trail / documentation) | I75: 4 | K75: Not Assessed | L75: Not applicable | M75: RST-0008
A76: USA-00073 | B76: Synthetic Hackfest Test Data | C76: SYN-U008 | D76: R2R_ga_preparer_job_preparation_only | E76: TEAM-R2R-GA_PREPARER_ | F76: R2R_r2r_close_journals_us_gaap_ifrs | G76: R2R Close & Journals (US GAAP / IFRS) | I76: 3 | K76: Not Assessed | L76: Not applicable | M76: RST-0008
A77: USA-00074 | B77: Synthetic Hackfest Test Data | C77: SYN-U008 | D77: R2R_ga_preparer_job_preparation_only | E77: TEAM-R2R-GA_PREPARER_ | F77: R2R_reconciliations_clearing_sox_ipe_balance_sheet_recs | G77: Reconciliations & Clearing (SOX/IPE balance sheet recs) | I77: 4 | K77: Not Assessed | L77: Not applicable | M77: RST-0008
A78: USA-00075 | B78: Synthetic Hackfest Test Data | C78: SYN-U008 | D78: R2R_ga_preparer_job_preparation_only | E78: TEAM-R2R-GA_PREPARER_ | F78: R2R_ownership_delivery | G78: Ownership & Delivery | I78: 3 | K78: Not Assessed | L78: Not applicable | M78: RST-0008
A79: USA-00076 | B79: Synthetic Hackfest Test Data | C79: SYN-U008 | D79: R2R_ga_preparer_job_preparation_only | E79: TEAM-R2R-GA_PREPARER_ | F79: R2R_time_management | G79: Time Management | I79: 4 | K79: Not Assessed | L79: Not applicable | M79: RST-0008
A80: USA-00077 | B80: Synthetic Hackfest Test Data | C80: SYN-U008 | D80: R2R_ga_preparer_job_preparation_only | E80: TEAM-R2R-GA_PREPARER_ | F80: R2R_productivity_tools_excel_ppt | G80: Productivity Tools (Excel/PPT) | I80: 4 | K80: Not Assessed | L80: Not applicable | M80: RST-0008
A81: USA-00078 | B81: Synthetic Hackfest Test Data | C81: SYN-U008 | D81: R2R_ga_preparer_job_preparation_only | E81: TEAM-R2R-GA_PREPARER_ | F81: R2R_erp_finance_tools_sap_oracle_blackline_onestream_sox_controls_in_systems | G81: ERP / Finance Tools (SAP/Oracle/BlackLine/OneStream) (SOX controls-in-systems) | I81: 4 | K81: Not Assessed | L81: Not applicable | M81: RST-0008
A82: USA-00079 | B82: Synthetic Hackfest Test Data | C82: SYN-U008 | D82: R2R_ga_preparer_job_preparation_only | E82: TEAM-R2R-GA_PREPARER_ | F82: R2R_professional_conduct | G82: Professional Conduct | I82: 4 | K82: Not Assessed | L82: Not applicable | M82: RST-0008
A83: USA-00080 | B83: Synthetic Hackfest Test Data | C83: SYN-U008 | D83: R2R_ga_preparer_job_preparation_only | E83: TEAM-R2R-GA_PREPARER_ | F83: R2R_teamwork_collaboration | G83: Teamwork / Collaboration | I83: 4 | K83: Not Assessed | L83: Not applicable | M83: RST-0008
A84: USA-00081 | B84: Synthetic Hackfest Test Data | C84: SYN-U009 | D84: R2R_consolidation_preparer_job_execution_pack_prep | E84: TEAM-R2R-CONSOLIDATIO | F84: R2R_first_time_right_quality_sox_icfr_ready | G84: First Time Right (Quality, SOX/ICFR-ready) | I84: 3 | J84: 2 | K84: Assessed | L84: Calibrated | M84: RST-0009 | N84: 0.88
A85: USA-00082 | B85: Synthetic Hackfest Test Data | C85: SYN-U009 | D85: R2R_consolidation_preparer_job_execution_pack_prep | E85: TEAM-R2R-CONSOLIDATIO | F85: R2R_attention_to_detail_sox_evidence_trail_documentation | G85: Attention to Detail (SOX evidence trail / documentation) | I85: 4 | J85: 2 | K85: Assessed | L85: Pending SME Calibration | M85: RST-0009 | N85: 0.75
A86: USA-00083 | B86: Synthetic Hackfest Test Data | C86: SYN-U009 | D86: R2R_consolidation_preparer_job_execution_pack_prep | E86: TEAM-R2R-CONSOLIDATIO | F86: R2R_reconciliations_clearing_sox_ipe_balance_sheet_recs | G86: Reconciliations & Clearing (SOX/IPE balance sheet recs) | I86: 4 | J86: 2 | K86: Assessed | L86: Calibrated | M86: RST-0009 | N86: 0.72
A87: USA-00084 | B87: Synthetic Hackfest Test Data | C87: SYN-U009 | D87: R2R_consolidation_preparer_job_execution_pack_prep | E87: TEAM-R2R-CONSOLIDATIO | F87: R2R_financial_reporting_ifrs_us_gaap | G87: Financial Reporting (IFRS / US GAAP) | I87: 4 | J87: 2 | K87: Assessed | L87: Calibrated | M87: RST-0009 | N87: 0.7
A88: USA-00085 | B88: Synthetic Hackfest Test Data | C88: SYN-U009 | D88: R2R_consolidation_preparer_job_execution_pack_prep | E88: TEAM-R2R-CONSOLIDATIO | F88: R2R_consolidation_ifrs_10_ifrs_3_ias_21_asc_810 | G88: Consolidation (IFRS 10 / IFRS 3 / IAS 21 / ASC 810) | I88: 4 | J88: 2 | K88: Assessed | L88: Calibrated | M88: RST-0009 | N88: 0.73
A89: USA-00086 | B89: Synthetic Hackfest Test Data | C89: SYN-U009 | D89: R2R_consolidation_preparer_job_execution_pack_prep | E89: TEAM-R2R-CONSOLIDATIO | F89: R2R_time_management | G89: Time Management | I89: 4 | J89: 2 | K89: Assessed | L89: Calibrated | M89: RST-0009 | N89: 0.86
A90: USA-00087 | B90: Synthetic Hackfest Test Data | C90: SYN-U009 | D90: R2R_consolidation_preparer_job_execution_pack_prep | E90: TEAM-R2R-CONSOLIDATIO | F90: R2R_productivity_tools_excel_ppt | G90: Productivity Tools (Excel/PPT) | I90: 4 | J90: 2 | K90: Assessed | L90: Calibrated | M90: RST-0009 | N90: 0.76
A91: USA-00088 | B91: Synthetic Hackfest Test Data | C91: SYN-U009 | D91: R2R_consolidation_preparer_job_execution_pack_prep | E91: TEAM-R2R-CONSOLIDATIO | F91: R2R_erp_finance_tools_sap_oracle_blackline_onestream_sox_controls_in_systems | G91: ERP / Finance Tools (SAP/Oracle/BlackLine/OneStream) (SOX controls-in-systems) | I91: 4 | J91: 2 | K91: Assessed | L91: Calibrated | M91: RST-0009 | N91: 0.89
A92: USA-00089 | B92: Synthetic Hackfest Test Data | C92: SYN-U009 | D92: R2R_consolidation_preparer_job_execution_pack_prep | E92: TEAM-R2R-CONSOLIDATIO | F92: R2R_professional_conduct | G92: Professional Conduct | I92: 4 | J92: 2 | K92: Assessed | L92: Calibrated | M92: RST-0009 | N92: 0.69
A93: USA-00090 | B93: Synthetic Hackfest Test Data | C93: SYN-U009 | D93: R2R_consolidation_preparer_job_execution_pack_prep | E93: TEAM-R2R-CONSOLIDATIO | F93: R2R_teamwork_collaboration | G93: Teamwork / Collaboration | I93: 4 | J93: 2 | K93: Assessed | L93: Calibrated | M93: RST-0009 | N93: 0.92
A94: USA-00091 | B94: Synthetic Hackfest Test Data | C94: SYN-U010 | D94: R2R_consolidation_preparer_job_execution_pack_prep | E94: TEAM-R2R-CONSOLIDATIO | F94: R2R_first_time_right_quality_sox_icfr_ready | G94: First Time Right (Quality, SOX/ICFR-ready) | I94: 3 | K94: Not Assessed | L94: Not applicable | M94: RST-0010
A95: USA-00092 | B95: Synthetic Hackfest Test Data | C95: SYN-U010 | D95: R2R_consolidation_preparer_job_execution_pack_prep | E95: TEAM-R2R-CONSOLIDATIO | F95: R2R_attention_to_detail_sox_evidence_trail_documentation | G95: Attention to Detail (SOX evidence trail / documentation) | I95: 4 | K95: Not Assessed | L95: Not applicable | M95: RST-0010
A96: USA-00093 | B96: Synthetic Hackfest Test Data | C96: SYN-U010 | D96: R2R_consolidation_preparer_job_execution_pack_prep | E96: TEAM-R2R-CONSOLIDATIO | F96: R2R_reconciliations_clearing_sox_ipe_balance_sheet_recs | G96: Reconciliations & Clearing (SOX/IPE balance sheet recs) | I96: 4 | K96: Not Assessed | L96: Not applicable | M96: RST-0010
A97: USA-00094 | B97: Synthetic Hackfest Test Data | C97: SYN-U010 | D97: R2R_consolidation_preparer_job_execution_pack_prep | E97: TEAM-R2R-CONSOLIDATIO | F97: R2R_financial_reporting_ifrs_us_gaap | G97: Financial Reporting (IFRS / US GAAP) | I97: 4 | K97: Not Assessed | L97: Not applicable | M97: RST-0010
A98: USA-00095 | B98: Synthetic Hackfest Test Data | C98: SYN-U010 | D98: R2R_consolidation_preparer_job_execution_pack_prep | E98: TEAM-R2R-CONSOLIDATIO | F98: R2R_consolidation_ifrs_10_ifrs_3_ias_21_asc_810 | G98: Consolidation (IFRS 10 / IFRS 3 / IAS 21 / ASC 810) | I98: 4 | K98: Not Assessed | L98: Not applicable | M98: RST-0010
A99: USA-00096 | B99: Synthetic Hackfest Test Data | C99: SYN-U010 | D99: R2R_consolidation_preparer_job_execution_pack_prep | E99: TEAM-R2R-CONSOLIDATIO | F99: R2R_time_management | G99: Time Management | I99: 4 | K99: Not Assessed | L99: Not applicable | M99: RST-0010
A100: USA-00097 | B100: Synthetic Hackfest Test Data | C100: SYN-U010 | D100: R2R_consolidation_preparer_job_execution_pack_prep | E100: TEAM-R2R-CONSOLIDATIO | F100: R2R_productivity_tools_excel_ppt | G100: Productivity Tools (Excel/PPT) | I100: 4 | K100: Not Assessed | L100: Not applicable | M100: RST-0010
A101: USA-00098 | B101: Synthetic Hackfest Test Data | C101: SYN-U010 | D101: R2R_consolidation_preparer_job_execution_pack_prep | E101: TEAM-R2R-CONSOLIDATIO | F101: R2R_erp_finance_tools_sap_oracle_blackline_onestream_sox_controls_in_systems | G101: ERP / Finance Tools (SAP/Oracle/BlackLine/OneStream) (SOX controls-in-systems) | I101: 4 | K101: Not Assessed | L101: Not applicable | M101: RST-0010
A102: USA-00099 | B102: Synthetic Hackfest Test Data | C102: SYN-U010 | D102: R2R_consolidation_preparer_job_execution_pack_prep | E102: TEAM-R2R-CONSOLIDATIO | F102: R2R_professional_conduct | G102: Professional Conduct | I102: 4 | K102: Not Assessed | L102: Not applicable | M102: RST-0010
A103: USA-00100 | B103: Synthetic Hackfest Test Data | C103: SYN-U010 | D103: R2R_consolidation_preparer_job_execution_pack_prep | E103: TEAM-R2R-CONSOLIDATIO | F103: R2R_teamwork_collaboration | G103: Teamwork / Collaboration | I103: 4 | K103: Not Assessed | L103: Not applicable | M103: RST-0010
A104: USA-00101 | B104: Synthetic Hackfest Test Data | C104: SYN-U011 | D104: R2R_consolidation_preparer_job_execution_pack_prep | E104: TEAM-R2R-CONSOLIDATIO | F104: R2R_first_time_right_quality_sox_icfr_ready | G104: First Time Right (Quality, SOX/ICFR-ready) | I104: 3 | K104: Not Assessed | L104: Not applicable | M104: RST-0011
A105: USA-00102 | B105: Synthetic Hackfest Test Data | C105: SYN-U011 | D105: R2R_consolidation_preparer_job_execution_pack_prep | E105: TEAM-R2R-CONSOLIDATIO | F105: R2R_attention_to_detail_sox_evidence_trail_documentation | G105: Attention to Detail (SOX evidence trail / documentation) | I105: 4 | K105: Not Assessed | L105: Not applicable | M105: RST-0011
... A113: USA-00110 | B113: Synthetic Hackfest Test Data | C113: SYN-U011 | D113: R2R_consolidation_preparer_job_execution_pack_prep | E113: TEAM-R2R-CONSOLIDATIO | F113: R2R_teamwork_collaboration | G113: Teamwork / Collaboration | I113: 4 | K113: Not Assessed | L113: Not applicable | M113: RST-0011
A114: USA-00111 | B114: Synthetic Hackfest Test Data | C114: SYN-U012 | D114: R2R_consolidation_preparer_job_execution_pack_prep | E114: TEAM-R2R-CONSOLIDATIO | F114: R2R_first_time_right_quality_sox_icfr_ready | G114: First Time Right (Quality, SOX/ICFR-ready) | I114: 3 | J114: 2 | K114: Assessed | L114: Calibrated | M114: RST-0012 | N114: 0.83
A115: USA-00112 | B115: Synthetic Hackfest Test Data | C115: SYN-U012 | D115: R2R_consolidation_preparer_job_execution_pack_prep | E115: TEAM-R2R-CONSOLIDATIO | F115: R2R_attention_to_detail_sox_evidence_trail_documentation | G115: Attention to Detail (SOX evidence trail / documentation) | I115: 4 | J115: 1 | K115: Assessed | L115: Pending SME Calibration | M115: RST-0012 | N115: 0.8
A116: USA-00113 | B116: Synthetic Hackfest Test Data | C116: SYN-U012 | D116: R2R_consolidation_preparer_job_execution_pack_prep | E116: TEAM-R2R-CONSOLIDATIO | F116: R2R_reconciliations_clearing_sox_ipe_balance_sheet_recs | G116: Reconciliations & Clearing (SOX/IPE balance sheet recs) | I116: 4 | J116: 2 | K116: Assessed | L116: Pending SME Calibration | M116: RST-0012 | N116: 0.76
A117: USA-00114 | B117: Synthetic Hackfest Test Data | C117: SYN-U012 | D117: R2R_consolidation_preparer_job_execution_pack_prep | E117: TEAM-R2R-CONSOLIDATIO | F117: R2R_financial_reporting_ifrs_us_gaap | G117: Financial Reporting (IFRS / US GAAP) | I117: 4 | J117: 2 | K117: Assessed | L117: Calibrated | M117: RST-0012 | N117: 0.75
A118: USA-00115 | B118: Synthetic Hackfest Test Data | C118: SYN-U012 | D118: R2R_consolidation_preparer_job_execution_pack_prep | E118: TEAM-R2R-CONSOLIDATIO | F118: R2R_consolidation_ifrs_10_ifrs_3_ias_21_asc_810 | G118: Consolidation (IFRS 10 / IFRS 3 / IAS 21 / ASC 810) | I118: 4 | J118: 3 | K118: Assessed | L118: Calibrated | M118: RST-0012 | N118: 0.94
A119: USA-00116 | B119: Synthetic Hackfest Test Data | C119: SYN-U012 | D119: R2R_consolidation_preparer_job_execution_pack_prep | E119: TEAM-R2R-CONSOLIDATIO | F119: R2R_time_management | G119: Time Management | I119: 4 | J119: 2 | K119: Assessed | L119: Calibrated | M119: RST-0012 | N119: 0.85
A120: USA-00117 | B120: Synthetic Hackfest Test Data | C120: SYN-U012 | D120: R2R_consolidation_preparer_job_execution_pack_prep | E120: TEAM-R2R-CONSOLIDATIO | F120: R2R_productivity_tools_excel_ppt | G120: Productivity Tools (Excel/PPT) | I120: 4 | J120: 3 | K120: Assessed | L120: Pending SME Calibration | M120: RST-0012 | N120: 0.72
A121: USA-00118 | B121: Synthetic Hackfest Test Data | C121: SYN-U012 | D121: R2R_consolidation_preparer_job_execution_pack_prep | E121: TEAM-R2R-CONSOLIDATIO | F121: R2R_erp_finance_tools_sap_oracle_blackline_onestream_sox_controls_in_systems | G121: ERP / Finance Tools (SAP/Oracle/BlackLine/OneStream) (SOX controls-in-systems) | I121: 4 | J121: 2 | K121: Assessed | L121: Calibrated | M121: RST-0012 | N121: 0.74
A122: USA-00119 | B122: Synthetic Hackfest Test Data | C122: SYN-U012 | D122: R2R_consolidation_preparer_job_execution_pack_prep | E122: TEAM-R2R-CONSOLIDATIO | F122: R2R_professional_conduct | G122: Professional Conduct | I122: 4 | J122: 2 | K122: Assessed | L122: Pending SME Calibration | M122: RST-0012 | N122: 0.84
A123: USA-00120 | B123: Synthetic Hackfest Test Data | C123: SYN-U012 | D123: R2R_consolidation_preparer_job_execution_pack_prep | E123: TEAM-R2R-CONSOLIDATIO | F123: R2R_teamwork_collaboration | G123: Teamwork / Collaboration | I123: 4 | J123: 1 | K123: Assessed | L123: Pending SME Calibration | M123: RST-0012 | N123: 0.76
A124: USA-00121 | B124: Synthetic Hackfest Test Data | C124: SYN-U013 | D124: AP_p2p_lead | E124: TEAM-AP-P2P_LEAD | F124: AP_first_time_right_quality | G124: First Time Right (Quality) | H124: Technical Expertise | I124: 3 | J124: 2 | K124: Assessed | L124: Calibrated | M124: RST-0013 | N124: 0.92
A125: USA-00122 | B125: Synthetic Hackfest Test Data | C125: SYN-U013 | D125: AP_p2p_lead | E125: TEAM-AP-P2P_LEAD | F125: AP_invoice_processing_po_non_po | G125: Invoice Processing (PO & Non-PO) | H125: Technical Expertise | I125: 3 | J125: 3 | K125: Assessed | L125: Pending SME Calibration | M125: RST-0013 | N125: 0.83
A126: USA-00123 | B126: Synthetic Hackfest Test Data | C126: SYN-U013 | D126: AP_p2p_lead | E126: TEAM-AP-P2P_LEAD | F126: AP_3_way_match_exception_handling | G126: 3-Way Match & Exception Handling | H126: Technical Expertise | I126: 3 | J126: 2 | K126: Assessed | L126: Calibrated | M126: RST-0013 | N126: 0.9
A127: USA-00124 | B127: Synthetic Hackfest Test Data | C127: SYN-U013 | D127: AP_p2p_lead | E127: TEAM-AP-P2P_LEAD | F127: AP_payments_execution_runs_methods | G127: Payments Execution (Runs/Methods) | H127: Technical Expertise | I127: 3 | J127: 2 | K127: Assessed | L127: Calibrated | M127: RST-0013 | N127: 0.69
A128: USA-00125 | B128: Synthetic Hackfest Test Data | C128: SYN-U013 | D128: AP_p2p_lead | E128: TEAM-AP-P2P_LEAD | F128: AP_tax_withholding_regulatory_basics | G128: Tax / Withholding & Regulatory Basics | H128: Technical Expertise | I128: 3 | J128: 3 | K128: Assessed | L128: Pending SME Calibration | M128: RST-0013 | N128: 0.85
A129: USA-00126 | B129: Synthetic Hackfest Test Data | C129: SYN-U013 | D129: AP_p2p_lead | E129: TEAM-AP-P2P_LEAD | F129: AP_ap_reconciliations_subledger_gl_vendor_statements | G129: AP Reconciliations (Subledger/GL, Vendor Statements) | H129: Technical Expertise | I129: 3 | J129: 3 | K129: Assessed | L129: Pending SME Calibration | M129: RST-0013 | N129: 0.93
A130: USA-00127 | B130: Synthetic Hackfest Test Data | C130: SYN-U013 | D130: AP_p2p_lead | E130: TEAM-AP-P2P_LEAD | F130: AP_close_activities_accruals_cutoff_gr_ir | G130: Close Activities (Accruals, Cutoff, GR/IR) | H130: Technical Expertise | I130: 3 | J130: 3 | K130: Assessed | L130: Calibrated | M130: RST-0013 | N130: 0.87
A131: USA-00128 | B131: Synthetic Hackfest Test Data | C131: SYN-U013 | D131: AP_p2p_lead | E131: TEAM-AP-P2P_LEAD | F131: AP_controls_compliance_audit_ap | G131: Controls / Compliance / Audit (AP) | H131: Technical Expertise | I131: 3 | J131: 3 | K131: Assessed | L131: Calibrated | M131: RST-0013 | N131: 0.88
A132: USA-00129 | B132: Synthetic Hackfest Test Data | C132: SYN-U013 | D132: AP_p2p_lead | E132: TEAM-AP-P2P_LEAD | F132: AP_ownership_delivery | G132: Ownership & Delivery | H132: Process Governance | I132: 3 | J132: 3 | K132: Assessed | L132: Calibrated | M132: RST-0013 | N132: 0.76
A133: USA-00130 | B133: Synthetic Hackfest Test Data | C133: SYN-U013 | D133: AP_p2p_lead | E133: TEAM-AP-P2P_LEAD | F133: AP_sla_governance_metrics | G133: SLA / Governance / Metrics | H133: Process Governance | I133: 3 | J133: 2 | K133: Assessed | L133: Calibrated | M133: RST-0013 | N133: 0.88
A134: USA-00131 | B134: Synthetic Hackfest Test Data | C134: SYN-U014 | D134: AP_p2p_lead | E134: TEAM-AP-P2P_LEAD | F134: AP_first_time_right_quality | G134: First Time Right (Quality) | H134: Technical Expertise | I134: 3 | J134: 3 | K134: Assessed | L134: Calibrated | M134: RST-0014 | N134: 0.81
A135: USA-00132 | B135: Synthetic Hackfest Test Data | C135: SYN-U014 | D135: AP_p2p_lead | E135: TEAM-AP-P2P_LEAD | F135: AP_invoice_processing_po_non_po | G135: Invoice Processing (PO & Non-PO) | H135: Technical Expertise | I135: 3 | J135: 2 | K135: Assessed | L135: Calibrated | M135: RST-0014 | N135: 0.75
... A143: USA-00140 | B143: Synthetic Hackfest Test Data | C143: SYN-U014 | D143: AP_p2p_lead | E143: TEAM-AP-P2P_LEAD | F143: AP_sla_governance_metrics | G143: SLA / Governance / Metrics | H143: Process Governance | I143: 3 | J143: 2 | K143: Assessed | L143: Calibrated | M143: RST-0014 | N143: 0.75
A144: USA-00141 | B144: Synthetic Hackfest Test Data | C144: SYN-U015 | D144: AP_p2p_lead | E144: TEAM-AP-P2P_LEAD | F144: AP_first_time_right_quality | G144: First Time Right (Quality) | H144: Technical Expertise | I144: 3 | K144: Not Assessed | L144: Not applicable | M144: RST-0015
A145: USA-00142 | B145: Synthetic Hackfest Test Data | C145: SYN-U015 | D145: AP_p2p_lead | E145: TEAM-AP-P2P_LEAD | F145: AP_invoice_processing_po_non_po | G145: Invoice Processing (PO & Non-PO) | H145: Technical Expertise | I145: 3 | K145: Not Assessed | L145: Not applicable | M145: RST-0015
A146: USA-00143 | B146: Synthetic Hackfest Test Data | C146: SYN-U015 | D146: AP_p2p_lead | E146: TEAM-AP-P2P_LEAD | F146: AP_3_way_match_exception_handling | G146: 3-Way Match & Exception Handling | H146: Technical Expertise | I146: 3 | K146: Not Assessed | L146: Not applicable | M146: RST-0015
...

Sheet Skill_Gaps_TNI
A1: Skill Gaps TNI
A3: gap_id | B3: data_label | C3: user_id | D3: role_id | E3: team_id | F3: skill_id | G3: skill | H3: capability | I3: target_level | J3: current_level | K3: gap_level_formula | L3: gap_severity | M3: recommended_course_id | N3: tni_recommendation | O3: cross_functional_recommendation
A4: GAP-00001 | B4: Synthetic Hackfest Test Data | C4: SYN-U001 | D4: R2R_banking_preparer_job_preparation_cash_posting | E4: TEAM-R2R-BANKING_PREP | F4: R2R_first_time_right_quality_sox_icfr_ready | G4: First Time Right (Quality, SOX/ICFR-ready) | I4: 3 | J4: 3 | K4: =IF(J4="","Assessment Pending",MAX(0,I4-J4)) -> 0 | L4: No gap | M4: TRN-0035 | N4: No action - at target
A5: GAP-00002 | B5: Synthetic Hackfest Test Data | C5: SYN-U001 | D5: R2R_banking_preparer_job_preparation_cash_posting | E5: TEAM-R2R-BANKING_PREP | F5: R2R_attention_to_detail_sox_evidence_trail_documentation | G5: Attention to Detail (SOX evidence trail / documentation) | I5: 4 | J5: 1 | K5: =IF(J5="","Assessment Pending",MAX(0,I5-J5)) -> 3 | L5: High | M5: TRN-0031 | N5: Assign mapped microlearning / scenario lab and reassess | O5: Potential cross-tower transferable skill
A6: GAP-00003 | B6: Synthetic Hackfest Test Data | C6: SYN-U001 | D6: R2R_banking_preparer_job_preparation_cash_posting | E6: TEAM-R2R-BANKING_PREP | F6: R2R_r2r_close_journals_us_gaap_ifrs | G6: R2R Close & Journals (US GAAP / IFRS) | I6: 3 | J6: 2 | K6: =IF(J6="","Assessment Pending",MAX(0,I6-J6)) -> 1 | L6: Moderate | M6: TRN-0040 | N6: Assign mapped microlearning / scenario lab and reassess
A7: GAP-00004 | B7: Synthetic Hackfest Test Data | C7: SYN-U001 | D7: R2R_banking_preparer_job_preparation_cash_posting | E7: TEAM-R2R-BANKING_PREP | F7: R2R_reconciliations_clearing_sox_ipe_balance_sheet_recs | G7: Reconciliations & Clearing (SOX/IPE balance sheet recs) | I7: 4 | J7: 1 | K7: =IF(J7="","Assessment Pending",MAX(0,I7-J7)) -> 3 | L7: High | M7: TRN-0041 | N7: Assign mapped microlearning / scenario lab and reassess
A8: GAP-00005 | B8: Synthetic Hackfest Test Data | C8: SYN-U001 | D8: R2R_banking_preparer_job_preparation_cash_posting | E8: TEAM-R2R-BANKING_PREP | F8: R2R_fixed_assets_banking_ias_16_ias_36_asc_360 | G8: Fixed Assets & Banking (IAS 16 / IAS 36 / ASC 360) | I8: 3 | J8: 2 | K8: =IF(J8="","Assessment Pending",MAX(0,I8-J8)) -> 1 | L8: Moderate | M8: TRN-0036 | N8: Assign mapped microlearning / scenario lab and reassess
A9: GAP-00006 | B9: Synthetic Hackfest Test Data | C9: SYN-U001 | D9: R2R_banking_preparer_job_preparation_cash_posting | E9: TEAM-R2R-BANKING_PREP | F9: R2R_time_management | G9: Time Management | I9: 4 | J9: 2 | K9: =IF(J9="","Assessment Pending",MAX(0,I9-J9)) -> 2 | L9: High | M9: TRN-0043 | N9: Assign mapped microlearning / scenario lab and reassess
A10: GAP-00007 | B10: Synthetic Hackfest Test Data | C10: SYN-U001 | D10: R2R_banking_preparer_job_preparation_cash_posting | E10: TEAM-R2R-BANKING_PREP | F10: R2R_productivity_tools_excel_ppt | G10: Productivity Tools (Excel/PPT) | I10: 4 | J10: 3 | K10: =IF(J10="","Assessment Pending",MAX(0,I10-J10)) -> 1 | L10: Moderate | M10: TRN-0038 | N10: Assign mapped microlearning / scenario lab and reassess
A11: GAP-00008 | B11: Synthetic Hackfest Test Data | C11: SYN-U001 | D11: R2R_banking_preparer_job_preparation_cash_posting | E11: TEAM-R2R-BANKING_PREP | F11: R2R_erp_finance_tools_sap_oracle_blackline_onestream_sox_controls_in_systems | G11: ERP / Finance Tools (SAP/Oracle/BlackLine/OneStream) (SOX controls-in-systems) | I11: 4 | J11: 1 | K11: =IF(J11="","Assessment Pending",MAX(0,I11-J11)) -> 3 | L11: High | M11: TRN-0033 | N11: Assign mapped microlearning / scenario lab and reassess
A12: GAP-00009 | B12: Synthetic Hackfest Test Data | C12: SYN-U001 | D12: R2R_banking_preparer_job_preparation_cash_posting | E12: TEAM-R2R-BANKING_PREP | F12: R2R_professional_conduct | G12: Professional Conduct | I12: 4 | J12: 1 | K12: =IF(J12="","Assessment Pending",MAX(0,I12-J12)) -> 3 | L12: High | M12: TRN-0039 | N12: Assign mapped microlearning / scenario lab and reassess
A13: GAP-00010 | B13: Synthetic Hackfest Test Data | C13: SYN-U001 | D13: R2R_banking_preparer_job_preparation_cash_posting | E13: TEAM-R2R-BANKING_PREP | F13: R2R_teamwork_collaboration | G13: Teamwork / Collaboration | I13: 4 | J13: 2 | K13: =IF(J13="","Assessment Pending",MAX(0,I13-J13)) -> 2 | L13: High | M13: TRN-0042 | N13: Assign mapped microlearning / scenario lab and reassess
A14: GAP-00011 | B14: Synthetic Hackfest Test Data | C14: SYN-U002 | D14: R2R_banking_preparer_job_preparation_cash_posting | E14: TEAM-R2R-BANKING_PREP | F14: R2R_first_time_right_quality_sox_icfr_ready | G14: First Time Right (Quality, SOX/ICFR-ready) | I14: 3 | J14: 3 | K14: =IF(J14="","Assessment Pending",MAX(0,I14-J14)) -> 0 | L14: No gap | M14: TRN-0035 | N14: No action - at target
A15: GAP-00012 | B15: Synthetic Hackfest Test Data | C15: SYN-U002 | D15: R2R_banking_preparer_job_preparation_cash_posting | E15: TEAM-R2R-BANKING_PREP | F15: R2R_attention_to_detail_sox_evidence_trail_documentation | G15: Attention to Detail (SOX evidence trail / documentation) | I15: 4 | J15: 3 | K15: =IF(J15="","Assessment Pending",MAX(0,I15-J15)) -> 1 | L15: Moderate | M15: TRN-0031 | N15: Assign mapped microlearning / scenario lab and reassess | O15: Potential cross-tower transferable skill
A16: GAP-00013 | B16: Synthetic Hackfest Test Data | C16: SYN-U002 | D16: R2R_banking_preparer_job_preparation_cash_posting | E16: TEAM-R2R-BANKING_PREP | F16: R2R_r2r_close_journals_us_gaap_ifrs | G16: R2R Close & Journals (US GAAP / IFRS) | I16: 3 | J16: 2 | K16: =IF(J16="","Assessment Pending",MAX(0,I16-J16)) -> 1 | L16: Moderate | M16: TRN-0040 | N16: Assign mapped microlearning / scenario lab and reassess
A17: GAP-00014 | B17: Synthetic Hackfest Test Data | C17: SYN-U002 | D17: R2R_banking_preparer_job_preparation_cash_posting | E17: TEAM-R2R-BANKING_PREP | F17: R2R_reconciliations_clearing_sox_ipe_balance_sheet_recs | G17: Reconciliations & Clearing (SOX/IPE balance sheet recs) | I17: 4 | J17: 2 | K17: =IF(J17="","Assessment Pending",MAX(0,I17-J17)) -> 2 | L17: High | M17: TRN-0041 | N17: Assign mapped microlearning / scenario lab and reassess
A18: GAP-00015 | B18: Synthetic Hackfest Test Data | C18: SYN-U002 | D18: R2R_banking_preparer_job_preparation_cash_posting | E18: TEAM-R2R-BANKING_PREP | F18: R2R_fixed_assets_banking_ias_16_ias_36_asc_360 | G18: Fixed Assets & Banking (IAS 16 / IAS 36 / ASC 360) | I18: 3 | J18: 1 | K18: =IF(J18="","Assessment Pending",MAX(0,I18-J18)) -> 2 | L18: High | M18: TRN-0036 | N18: Assign mapped microlearning / scenario lab and reassess
A19: GAP-00016 | B19: Synthetic Hackfest Test Data | C19: SYN-U002 | D19: R2R_banking_preparer_job_preparation_cash_posting | E19: TEAM-R2R-BANKING_PREP | F19: R2R_time_management | G19: Time Management | I19: 4 | J19: 2 | K19: =IF(J19="","Assessment Pending",MAX(0,I19-J19)) -> 2 | L19: High | M19: TRN-0043 | N19: Assign mapped microlearning / scenario lab and reassess
A20: GAP-00017 | B20: Synthetic Hackfest Test Data | C20: SYN-U002 | D20: R2R_banking_preparer_job_preparation_cash_posting | E20: TEAM-R2R-BANKING_PREP | F20: R2R_productivity_tools_excel_ppt | G20: Productivity Tools (Excel/PPT) | I20: 4 | J20: 2 | K20: =IF(J20="","Assessment Pending",MAX(0,I20-J20)) -> 2 | L20: High | M20: TRN-0038 | N20: Assign mapped microlearning / scenario lab and reassess
A21: GAP-00018 | B21: Synthetic Hackfest Test Data | C21: SYN-U002 | D21: R2R_banking_preparer_job_preparation_cash_posting | E21: TEAM-R2R-BANKING_PREP | F21: R2R_erp_finance_tools_sap_oracle_blackline_onestream_sox_controls_in_systems | G21: ERP / Finance Tools (SAP/Oracle/BlackLine/OneStream) (SOX controls-in-systems) | I21: 4 | J21: 2 | K21: =IF(J21="","Assessment Pending",MAX(0,I21-J21)) -> 2 | L21: High | M21: TRN-0033 | N21: Assign mapped microlearning / scenario lab and reassess
A22: GAP-00019 | B22: Synthetic Hackfest Test Data | C22: SYN-U002 | D22: R2R_banking_preparer_job_preparation_cash_posting | E22: TEAM-R2R-BANKING_PREP | F22: R2R_professional_conduct | G22: Professional Conduct | I22: 4 | J22: 3 | K22: =IF(J22="","Assessment Pending",MAX(0,I22-J22)) -> 1 | L22: Moderate | M22: TRN-0039 | N22: Assign mapped microlearning / scenario lab and reassess
A23: GAP-00020 | B23: Synthetic Hackfest Test Data | C23: SYN-U002 | D23: R2R_banking_preparer_job_preparation_cash_posting | E23: TEAM-R2R-BANKING_PREP | F23: R2R_teamwork_collaboration | G23: Teamwork / Collaboration | I23: 4 | J23: 2 | K23: =IF(J23="","Assessment Pending",MAX(0,I23-J23)) -> 2 | L23: High | M23: TRN-0042 | N23: Assign mapped microlearning / scenario lab and reassess
A24: GAP-00021 | B24: Synthetic Hackfest Test Data | C24: SYN-U003 | D24: R2R_banking_preparer_job_preparation_cash_posting | E24: TEAM-R2R-BANKING_PREP | F24: R2R_first_time_right_quality_sox_icfr_ready | G24: First Time Right (Quality, SOX/ICFR-ready) | I24: 3 | K24: =IF(J24="","Assessment Pending",MAX(0,I24-J24)) -> Assessment Pending | M24: TRN-0035 | N24: Assessment pending before TNI
A25: GAP-00022 | B25: Synthetic Hackfest Test Data | C25: SYN-U003 | D25: R2R_banking_preparer_job_preparation_cash_posting | E25: TEAM-R2R-BANKING_PREP | F25: R2R_attention_to_detail_sox_evidence_trail_documentation | G25: Attention to Detail (SOX evidence trail / documentation) | I25: 4 | K25: =IF(J25="","Assessment Pending",MAX(0,I25-J25)) -> Assessment Pending | M25: TRN-0031 | N25: Assessment pending before TNI | O25: Potential cross-tower transferable skill
A26: GAP-00023 | B26: Synthetic Hackfest Test Data | C26: SYN-U003 | D26: R2R_banking_preparer_job_preparation_cash_posting | E26: TEAM-R2R-BANKING_PREP | F26: R2R_r2r_close_journals_us_gaap_ifrs | G26: R2R Close & Journals (US GAAP / IFRS) | I26: 3 | K26: =IF(J26="","Assessment Pending",MAX(0,I26-J26)) -> Assessment Pending | M26: TRN-0040 | N26: Assessment pending before TNI
A27: GAP-00024 | B27: Synthetic Hackfest Test Data | C27: SYN-U003 | D27: R2R_banking_preparer_job_preparation_cash_posting | E27: TEAM-R2R-BANKING_PREP | F27: R2R_reconciliations_clearing_sox_ipe_balance_sheet_recs | G27: Reconciliations & Clearing (SOX/IPE balance sheet recs) | I27: 4 | K27: =IF(J27="","Assessment Pending",MAX(0,I27-J27)) -> Assessment Pending | M27: TRN-0041 | N27: Assessment pending before TNI
A28: GAP-00025 | B28: Synthetic Hackfest Test Data | C28: SYN-U003 | D28: R2R_banking_preparer_job_preparation_cash_posting | E28: TEAM-R2R-BANKING_PREP | F28: R2R_fixed_assets_banking_ias_16_ias_36_asc_360 | G28: Fixed Assets & Banking (IAS 16 / IAS 36 / ASC 360) | I28: 3 | K28: =IF(J28="","Assessment Pending",MAX(0,I28-J28)) -> Assessment Pending | M28: TRN-0036 | N28: Assessment pending before TNI
A29: GAP-00026 | B29: Synthetic Hackfest Test Data | C29: SYN-U003 | D29: R2R_banking_preparer_job_preparation_cash_posting | E29: TEAM-R2R-BANKING_PREP | F29: R2R_time_management | G29: Time Management | I29: 4 | K29: =IF(J29="","Assessment Pending",MAX(0,I29-J29)) -> Assessment Pending | M29: TRN-0043 | N29: Assessment pending before TNI
A30: GAP-00027 | B30: Synthetic Hackfest Test Data | C30: SYN-U003 | D30: R2R_banking_preparer_job_preparation_cash_posting | E30: TEAM-R2R-BANKING_PREP | F30: R2R_productivity_tools_excel_ppt | G30: Productivity Tools (Excel/PPT) | I30: 4 | K30: =IF(J30="","Assessment Pending",MAX(0,I30-J30)) -> Assessment Pending | M30: TRN-0038 | N30: Assessment pending before TNI
A31: GAP-00028 | B31: Synthetic Hackfest Test Data | C31: SYN-U003 | D31: R2R_banking_preparer_job_preparation_cash_posting | E31: TEAM-R2R-BANKING_PREP | F31: R2R_erp_finance_tools_sap_oracle_blackline_onestream_sox_controls_in_systems | G31: ERP / Finance Tools (SAP/Oracle/BlackLine/OneStream) (SOX controls-in-systems) | I31: 4 | K31: =IF(J31="","Assessment Pending",MAX(0,I31-J31)) -> Assessment Pending | M31: TRN-0033 | N31: Assessment pending before TNI
A32: GAP-00029 | B32: Synthetic Hackfest Test Data | C32: SYN-U003 | D32: R2R_banking_preparer_job_preparation_cash_posting | E32: TEAM-R2R-BANKING_PREP | F32: R2R_professional_conduct | G32: Professional Conduct | I32: 4 | K32: =IF(J32="","Assessment Pending",MAX(0,I32-J32)) -> Assessment Pending | M32: TRN-0039 | N32: Assessment pending before TNI
A33: GAP-00030 | B33: Synthetic Hackfest Test Data | C33: SYN-U003 | D33: R2R_banking_preparer_job_preparation_cash_posting | E33: TEAM-R2R-BANKING_PREP | F33: R2R_teamwork_collaboration | G33: Teamwork / Collaboration | I33: 4 | K33: =IF(J33="","Assessment Pending",MAX(0,I33-J33)) -> Assessment Pending | M33: TRN-0042 | N33: Assessment pending before TNI
A34: GAP-00031 | B34: Synthetic Hackfest Test Data | C34: SYN-U004 | D34: R2R_banking_preparer_job_preparation_cash_posting | E34: TEAM-R2R-BANKING_PREP | F34: R2R_first_time_right_quality_sox_icfr_ready | G34: First Time Right (Quality, SOX/ICFR-ready) | I34: 3 | K34: =IF(J34="","Assessment Pending",MAX(0,I34-J34)) -> Assessment Pending | M34: TRN-0035 | N34: Assessment pending before TNI
A35: GAP-00032 | B35: Synthetic Hackfest Test Data | C35: SYN-U004 | D35: R2R_banking_preparer_job_preparation_cash_posting | E35: TEAM-R2R-BANKING_PREP | F35: R2R_attention_to_detail_sox_evidence_trail_documentation | G35: Attention to Detail (SOX evidence trail / documentation) | I35: 4 | K35: =IF(J35="","Assessment Pending",MAX(0,I35-J35)) -> Assessment Pending | M35: TRN-0031 | N35: Assessment pending before TNI | O35: Potential cross-tower transferable skill
A36: GAP-00033 | B36: Synthetic Hackfest Test Data | C36: SYN-U004 | D36: R2R_banking_preparer_job_preparation_cash_posting | E36: TEAM-R2R-BANKING_PREP | F36: R2R_r2r_close_journals_us_gaap_ifrs | G36: R2R Close & Journals (US GAAP / IFRS) | I36: 3 | K36: =IF(J36="","Assessment Pending",MAX(0,I36-J36)) -> Assessment Pending | M36: TRN-0040 | N36: Assessment pending before TNI
A37: GAP-00034 | B37: Synthetic Hackfest Test Data | C37: SYN-U004 | D37: R2R_banking_preparer_job_preparation_cash_posting | E37: TEAM-R2R-BANKING_PREP | F37: R2R_reconciliations_clearing_sox_ipe_balance_sheet_recs | G37: Reconciliations & Clearing (SOX/IPE balance sheet recs) | I37: 4 | K37: =IF(J37="","Assessment Pending",MAX(0,I37-J37)) -> Assessment Pending | M37: TRN-0041 | N37: Assessment pending before TNI
A38: GAP-00035 | B38: Synthetic Hackfest Test Data | C38: SYN-U004 | D38: R2R_banking_preparer_job_preparation_cash_posting | E38: TEAM-R2R-BANKING_PREP | F38: R2R_fixed_assets_banking_ias_16_ias_36_asc_360 | G38: Fixed Assets & Banking (IAS 16 / IAS 36 / ASC 360) | I38: 3 | K38: =IF(J38="","Assessment Pending",MAX(0,I38-J38)) -> Assessment Pending | M38: TRN-0036 | N38: Assessment pending before TNI
A39: GAP-00036 | B39: Synthetic Hackfest Test Data | C39: SYN-U004 | D39: R2R_banking_preparer_job_preparation_cash_posting | E39: TEAM-R2R-BANKING_PREP | F39: R2R_time_management | G39: Time Management | I39: 4 | K39: =IF(J39="","Assessment Pending",MAX(0,I39-J39)) -> Assessment Pending | M39: TRN-0043 | N39: Assessment pending before TNI
A40: GAP-00037 | B40: Synthetic Hackfest Test Data | C40: SYN-U004 | D40: R2R_banking_preparer_job_preparation_cash_posting | E40: TEAM-R2R-BANKING_PREP | F40: R2R_productivity_tools_excel_ppt | G40: Productivity Tools (Excel/PPT) | I40: 4 | K40: =IF(J40="","Assessment Pending",MAX(0,I40-J40)) -> Assessment Pending | M40: TRN-0038 | N40: Assessment pending before TNI
A41: GAP-00038 | B41: Synthetic Hackfest Test Data | C41: SYN-U004 | D41: R2R_banking_preparer_job_preparation_cash_posting | E41: TEAM-R2R-BANKING_PREP | F41: R2R_erp_finance_tools_sap_oracle_blackline_onestream_sox_controls_in_systems | G41: ERP / Finance Tools (SAP/Oracle/BlackLine/OneStream) (SOX controls-in-systems) | I41: 4 | K41: =IF(J41="","Assessment Pending",MAX(0,I41-J41)) -> Assessment Pending | M41: TRN-0033 | N41: Assessment pending before TNI
A42: GAP-00039 | B42: Synthetic Hackfest Test Data | C42: SYN-U004 | D42: R2R_banking_preparer_job_preparation_cash_posting | E42: TEAM-R2R-BANKING_PREP | F42: R2R_professional_conduct | G42: Professional Conduct | I42: 4 | K42: =IF(J42="","Assessment Pending",MAX(0,I42-J42)) -> Assessment Pending | M42: TRN-0039 | N42: Assessment pending before TNI
A43: GAP-00040 | B43: Synthetic Hackfest Test Data | C43: SYN-U004 | D43: R2R_banking_preparer_job_preparation_cash_posting | E43: TEAM-R2R-BANKING_PREP | F43: R2R_teamwork_collaboration | G43: Teamwork / Collaboration | I43: 4 | K43: =IF(J43="","Assessment Pending",MAX(0,I43-J43)) -> Assessment Pending | M43: TRN-0042 | N43: Assessment pending before TNI
A44: GAP-00041 | B44: Synthetic Hackfest Test Data | C44: SYN-U005 | D44: R2R_ga_preparer_job_preparation_only | E44: TEAM-R2R-GA_PREPARER_ | F44: R2R_first_time_right_quality_sox_icfr_ready | G44: First Time Right (Quality, SOX/ICFR-ready) | I44: 3 | J44: 2 | K44: =IF(J44="","Assessment Pending",MAX(0,I44-J44)) -> 1 | L44: Moderate | M44: TRN-0035 | N44: Assign mapped microlearning / scenario lab and reassess
A45: GAP-00042 | B45: Synthetic Hackfest Test Data | C45: SYN-U005 | D45: R2R_ga_preparer_job_preparation_only | E45: TEAM-R2R-GA_PREPARER_ | F45: R2R_attention_to_detail_sox_evidence_trail_documentation | G45: Attention to Detail (SOX evidence trail / documentation) | I45: 4 | J45: 2 | K45: =IF(J45="","Assessment Pending",MAX(0,I45-J45)) -> 2 | L45: High | M45: TRN-0031 | N45: Assign mapped microlearning / scenario lab and reassess | O45: Potential cross-tower transferable skill
A46: GAP-00043 | B46: Synthetic Hackfest Test Data | C46: SYN-U005 | D46: R2R_ga_preparer_job_preparation_only | E46: TEAM-R2R-GA_PREPARER_ | F46: R2R_r2r_close_journals_us_gaap_ifrs | G46: R2R Close & Journals (US GAAP / IFRS) | I46: 3 | J46: 2 | K46: =IF(J46="","Assessment Pending",MAX(0,I46-J46)) -> 1 | L46: Moderate | M46: TRN-0040 | N46: Assign mapped microlearning / scenario lab and reassess
A47: GAP-00044 | B47: Synthetic Hackfest Test Data | C47: SYN-U005 | D47: R2R_ga_preparer_job_preparation_only | E47: TEAM-R2R-GA_PREPARER_ | F47: R2R_reconciliations_clearing_sox_ipe_balance_sheet_recs | G47: Reconciliations & Clearing (SOX/IPE balance sheet recs) | I47: 4 | J47: 2 | K47: =IF(J47="","Assessment Pending",MAX(0,I47-J47)) -> 2 | L47: High | M47: TRN-0041 | N47: Assign mapped microlearning / scenario lab and reassess
A48: GAP-00045 | B48: Synthetic Hackfest Test Data | C48: SYN-U005 | D48: R2R_ga_preparer_job_preparation_only | E48: TEAM-R2R-GA_PREPARER_ | F48: R2R_ownership_delivery | G48: Ownership & Delivery | I48: 3 | J48: 2 | K48: =IF(J48="","Assessment Pending",MAX(0,I48-J48)) -> 1 | L48: Moderate | M48: TRN-0037 | N48: Assign mapped microlearning / scenario lab and reassess
A49: GAP-00046 | B49: Synthetic Hackfest Test Data | C49: SYN-U005 | D49: R2R_ga_preparer_job_preparation_only | E49: TEAM-R2R-GA_PREPARER_ | F49: R2R_time_management | G49: Time Management | I49: 4 | J49: 2 | K49: =IF(J49="","Assessment Pending",MAX(0,I49-J49)) -> 2 | L49: High | M49: TRN-0043 | N49: Assign mapped microlearning / scenario lab and reassess
A50: GAP-00047 | B50: Synthetic Hackfest Test Data | C50: SYN-U005 | D50: R2R_ga_preparer_job_preparation_only | E50: TEAM-R2R-GA_PREPARER_ | F50: R2R_productivity_tools_excel_ppt | G50: Productivity Tools (Excel/PPT) | I50: 4 | J50: 1 | K50: =IF(J50="","Assessment Pending",MAX(0,I50-J50)) -> 3 | L50: High | M50: TRN-0038 | N50: Assign mapped microlearning / scenario lab and reassess
A51: GAP-00048 | B51: Synthetic Hackfest Test Data | C51: SYN-U005 | D51: R2R_ga_preparer_job_preparation_only | E51: TEAM-R2R-GA_PREPARER_ | F51: R2R_erp_finance_tools_sap_oracle_blackline_onestream_sox_controls_in_systems | G51: ERP / Finance Tools (SAP/Oracle/BlackLine/OneStream) (SOX controls-in-systems) | I51: 4 | J51: 3 | K51: =IF(J51="","Assessment Pending",MAX(0,I51-J51)) -> 1 | L51: Moderate | M51: TRN-0033 | N51: Assign mapped microlearning / scenario lab and reassess
A52: GAP-00049 | B52: Synthetic Hackfest Test Data | C52: SYN-U005 | D52: R2R_ga_preparer_job_preparation_only | E52: TEAM-R2R-GA_PREPARER_ | F52: R2R_professional_conduct | G52: Professional Conduct | I52: 4 | J52: 2 | K52: =IF(J52="","Assessment Pending",MAX(0,I52-J52)) -> 2 | L52: High | M52: TRN-0039 | N52: Assign mapped microlearning / scenario lab and reassess
A53: GAP-00050 | B53: Synthetic Hackfest Test Data | C53: SYN-U005 | D53: R2R_ga_preparer_job_preparation_only | E53: TEAM-R2R-GA_PREPARER_ | F53: R2R_teamwork_collaboration | G53: Teamwork / Collaboration | I53: 4 | J53: 2 | K53: =IF(J53="","Assessment Pending",MAX(0,I53-J53)) -> 2 | L53: High | M53: TRN-0042 | N53: Assign mapped microlearning / scenario lab and reassess
A54: GAP-00051 | B54: Synthetic Hackfest Test Data | C54: SYN-U006 | D54: R2R_ga_preparer_job_preparation_only | E54: TEAM-R2R-GA_PREPARER_ | F54: R2R_first_time_right_quality_sox_icfr_ready | G54: First Time Right (Quality, SOX/ICFR-ready) | I54: 3 | J54: 3 | K54: =IF(J54="","Assessment Pending",MAX(0,I54-J54)) -> 0 | L54: No gap | M54: TRN-0035 | N54: No action - at target
A55: GAP-00052 | B55: Synthetic Hackfest Test Data | C55: SYN-U006 | D55: R2R_ga_preparer_job_preparation_only | E55: TEAM-R2R-GA_PREPARER_ | F55: R2R_attention_to_detail_sox_evidence_trail_documentation | G55: Attention to Detail (SOX evidence trail / documentation) | I55: 4 | J55: 3 | K55: =IF(J55="","Assessment Pending",MAX(0,I55-J55)) -> 1 | L55: Moderate | M55: TRN-0031 | N55: Assign mapped microlearning / scenario lab and reassess | O55: Potential cross-tower transferable skill
A56: GAP-00053 | B56: Synthetic Hackfest Test Data | C56: SYN-U006 | D56: R2R_ga_preparer_job_preparation_only | E56: TEAM-R2R-GA_PREPARER_ | F56: R2R_r2r_close_journals_us_gaap_ifrs | G56: R2R Close & Journals (US GAAP / IFRS) | I56: 3 | J56: 3 | K56: =IF(J56="","Assessment Pending",MAX(0,I56-J56)) -> 0 | L56: No gap | M56: TRN-0040 | N56: No action - at target
A57: GAP-00054 | B57: Synthetic Hackfest Test Data | C57: SYN-U006 | D57: R2R_ga_preparer_job_preparation_only | E57: TEAM-R2R-GA_PREPARER_ | F57: R2R_reconciliations_clearing_sox_ipe_balance_sheet_recs | G57: Reconciliations & Clearing (SOX/IPE balance sheet recs) | I57: 4 | J57: 4 | K57: =IF(J57="","Assessment Pending",MAX(0,I57-J57)) -> 0 | L57: No gap | M57: TRN-0041 | N57: No action - at target
A58: GAP-00055 | B58: Synthetic Hackfest Test Data | C58: SYN-U006 | D58: R2R_ga_preparer_job_preparation_only | E58: TEAM-R2R-GA_PREPARER_ | F58: R2R_ownership_delivery | G58: Ownership & Delivery | I58: 3 | J58: 3 | K58: =IF(J58="","Assessment Pending",MAX(0,I58-J58)) -> 0 | L58: No gap | M58: TRN-0037 | N58: No action - at target
A59: GAP-00056 | B59: Synthetic Hackfest Test Data | C59: SYN-U006 | D59: R2R_ga_preparer_job_preparation_only | E59: TEAM-R2R-GA_PREPARER_ | F59: R2R_time_management | G59: Time Management | I59: 4 | J59: 3 | K59: =IF(J59="","Assessment Pending",MAX(0,I59-J59)) -> 1 | L59: Moderate | M59: TRN-0043 | N59: Assign mapped microlearning / scenario lab and reassess
A60: GAP-00057 | B60: Synthetic Hackfest Test Data | C60: SYN-U006 | D60: R2R_ga_preparer_job_preparation_only | E60: TEAM-R2R-GA_PREPARER_ | F60: R2R_productivity_tools_excel_ppt | G60: Productivity Tools (Excel/PPT) | I60: 4 | J60: 4 | K60: =IF(J60="","Assessment Pending",MAX(0,I60-J60)) -> 0 | L60: No gap | M60: TRN-0038 | N60: No action - at target
A61: GAP-00058 | B61: Synthetic Hackfest Test Data | C61: SYN-U006 | D61: R2R_ga_preparer_job_preparation_only | E61: TEAM-R2R-GA_PREPARER_ | F61: R2R_erp_finance_tools_sap_oracle_blackline_onestream_sox_controls_in_systems | G61: ERP / Finance Tools (SAP/Oracle/BlackLine/OneStream) (SOX controls-in-systems) | I61: 4 | J61: 4 | K61: =IF(J61="","Assessment Pending",MAX(0,I61-J61)) -> 0 | L61: No gap | M61: TRN-0033 | N61: No action - at target
A62: GAP-00059 | B62: Synthetic Hackfest Test Data | C62: SYN-U006 | D62: R2R_ga_preparer_job_preparation_only | E62: TEAM-R2R-GA_PREPARER_ | F62: R2R_professional_conduct | G62: Professional Conduct | I62: 4 | J62: 4 | K62: =IF(J62="","Assessment Pending",MAX(0,I62-J62)) -> 0 | L62: No gap | M62: TRN-0039 | N62: No action - at target
A63: GAP-00060 | B63: Synthetic Hackfest Test Data | C63: SYN-U006 | D63: R2R_ga_preparer_job_preparation_only | E63: TEAM-R2R-GA_PREPARER_ | F63: R2R_teamwork_collaboration | G63: Teamwork / Collaboration | I63: 4 | J63: 4 | K63: =IF(J63="","Assessment Pending",MAX(0,I63-J63)) -> 0 | L63: No gap | M63: TRN-0042 | N63: No action - at target
A64: GAP-00061 | B64: Synthetic Hackfest Test Data | C64: SYN-U007 | D64: R2R_ga_preparer_job_preparation_only | E64: TEAM-R2R-GA_PREPARER_ | F64: R2R_first_time_right_quality_sox_icfr_ready | G64: First Time Right (Quality, SOX/ICFR-ready) | I64: 3 | J64: 2 | K64: =IF(J64="","Assessment Pending",MAX(0,I64-J64)) -> 1 | L64: Moderate | M64: TRN-0035 | N64: Assign mapped microlearning / scenario lab and reassess
A65: GAP-00062 | B65: Synthetic Hackfest Test Data | C65: SYN-U007 | D65: R2R_ga_preparer_job_preparation_only | E65: TEAM-R2R-GA_PREPARER_ | F65: R2R_attention_to_detail_sox_evidence_trail_documentation | G65: Attention to Detail (SOX evidence trail / documentation) | I65: 4 | J65: 2 | K65: =IF(J65="","Assessment Pending",MAX(0,I65-J65)) -> 2 | L65: High | M65: TRN-0031 | N65: Assign mapped microlearning / scenario lab and reassess | O65: Potential cross-tower transferable skill
A66: GAP-00063 | B66: Synthetic Hackfest Test Data | C66: SYN-U007 | D66: R2R_ga_preparer_job_preparation_only | E66: TEAM-R2R-GA_PREPARER_ | F66: R2R_r2r_close_journals_us_gaap_ifrs | G66: R2R Close & Journals (US GAAP / IFRS) | I66: 3 | J66: 3 | K66: =IF(J66="","Assessment Pending",MAX(0,I66-J66)) -> 0 | L66: No gap | M66: TRN-0040 | N66: No action - at target
A67: GAP-00064 | B67: Synthetic Hackfest Test Data | C67: SYN-U007 | D67: R2R_ga_preparer_job_preparation_only | E67: TEAM-R2R-GA_PREPARER_ | F67: R2R_reconciliations_clearing_sox_ipe_balance_sheet_recs | G67: Reconciliations & Clearing (SOX/IPE balance sheet recs) | I67: 4 | J67: 3 | K67: =IF(J67="","Assessment Pending",MAX(0,I67-J67)) -> 1 | L67: Moderate | M67: TRN-0041 | N67: Assign mapped microlearning / scenario lab and reassess
A68: GAP-00065 | B68: Synthetic Hackfest Test Data | C68: SYN-U007 | D68: R2R_ga_preparer_job_preparation_only | E68: TEAM-R2R-GA_PREPARER_ | F68: R2R_ownership_delivery | G68: Ownership & Delivery | I68: 3 | J68: 2 | K68: =IF(J68="","Assessment Pending",MAX(0,I68-J68)) -> 1 | L68: Moderate | M68: TRN-0037 | N68: Assign mapped microlearning / scenario lab and reassess
A69: GAP-00066 | B69: Synthetic Hackfest Test Data | C69: SYN-U007 | D69: R2R_ga_preparer_job_preparation_only | E69: TEAM-R2R-GA_PREPARER_ | F69: R2R_time_management | G69: Time Management | I69: 4 | J69: 2 | K69: =IF(J69="","Assessment Pending",MAX(0,I69-J69)) -> 2 | L69: High | M69: TRN-0043 | N69: Assign mapped microlearning / scenario lab and reassess
A70: GAP-00067 | B70: Synthetic Hackfest Test Data | C70: SYN-U007 | D70: R2R_ga_preparer_job_preparation_only | E70: TEAM-R2R-GA_PREPARER_ | F70: R2R_productivity_tools_excel_ppt | G70: Productivity Tools (Excel/PPT) | I70: 4 | J70: 1 | K70: =IF(J70="","Assessment Pending",MAX(0,I70-J70)) -> 3 | L70: High | M70: TRN-0038 | N70: Assign mapped microlearning / scenario lab and reassess
A71: GAP-00068 | B71: Synthetic Hackfest Test Data | C71: SYN-U007 | D71: R2R_ga_preparer_job_preparation_only | E71: TEAM-R2R-GA_PREPARER_ | F71: R2R_erp_finance_tools_sap_oracle_blackline_onestream_sox_controls_in_systems | G71: ERP / Finance Tools (SAP/Oracle/BlackLine/OneStream) (SOX controls-in-systems) | I71: 4 | J71: 2 | K71: =IF(J71="","Assessment Pending",MAX(0,I71-J71)) -> 2 | L71: High | M71: TRN-0033 | N71: Assign mapped microlearning / scenario lab and reassess
A72: GAP-00069 | B72: Synthetic Hackfest Test Data | C72: SYN-U007 | D72: R2R_ga_preparer_job_preparation_only | E72: TEAM-R2R-GA_PREPARER_ | F72: R2R_professional_conduct | G72: Professional Conduct | I72: 4 | J72: 3 | K72: =IF(J72="","Assessment Pending",MAX(0,I72-J72)) -> 1 | L72: Moderate | M72: TRN-0039 | N72: Assign mapped microlearning / scenario lab and reassess
A73: GAP-00070 | B73: Synthetic Hackfest Test Data | C73: SYN-U007 | D73: R2R_ga_preparer_job_preparation_only | E73: TEAM-R2R-GA_PREPARER_ | F73: R2R_teamwork_collaboration | G73: Teamwork / Collaboration | I73: 4 | J73: 2 | K73: =IF(J73="","Assessment Pending",MAX(0,I73-J73)) -> 2 | L73: High | M73: TRN-0042 | N73: Assign mapped microlearning / scenario lab and reassess
A74: GAP-00071 | B74: Synthetic Hackfest Test Data | C74: SYN-U008 | D74: R2R_ga_preparer_job_preparation_only | E74: TEAM-R2R-GA_PREPARER_ | F74: R2R_first_time_right_quality_sox_icfr_ready | G74: First Time Right (Quality, SOX/ICFR-ready) | I74: 3 | K74: =IF(J74="","Assessment Pending",MAX(0,I74-J74)) -> Assessment Pending | M74: TRN-0035 | N74: Assessment pending before TNI
A75: GAP-00072 | B75: Synthetic Hackfest Test Data | C75: SYN-U008 | D75: R2R_ga_preparer_job_preparation_only | E75: TEAM-R2R-GA_PREPARER_ | F75: R2R_attention_to_detail_sox_evidence_trail_documentation | G75: Attention to Detail (SOX evidence trail / documentation) | I75: 4 | K75: =IF(J75="","Assessment Pending",MAX(0,I75-J75)) -> Assessment Pending | M75: TRN-0031 | N75: Assessment pending before TNI | O75: Potential cross-tower transferable skill
A76: GAP-00073 | B76: Synthetic Hackfest Test Data | C76: SYN-U008 | D76: R2R_ga_preparer_job_preparation_only | E76: TEAM-R2R-GA_PREPARER_ | F76: R2R_r2r_close_journals_us_gaap_ifrs | G76: R2R Close & Journals (US GAAP / IFRS) | I76: 3 | K76: =IF(J76="","Assessment Pending",MAX(0,I76-J76)) -> Assessment Pending | M76: TRN-0040 | N76: Assessment pending before TNI
A77: GAP-00074 | B77: Synthetic Hackfest Test Data | C77: SYN-U008 | D77: R2R_ga_preparer_job_preparation_only | E77: TEAM-R2R-GA_PREPARER_ | F77: R2R_reconciliations_clearing_sox_ipe_balance_sheet_recs | G77: Reconciliations & Clearing (SOX/IPE balance sheet recs) | I77: 4 | K77: =IF(J77="","Assessment Pending",MAX(0,I77-J77)) -> Assessment Pending | M77: TRN-0041 | N77: Assessment pending before TNI
A78: GAP-00075 | B78: Synthetic Hackfest Test Data | C78: SYN-U008 | D78: R2R_ga_preparer_job_preparation_only | E78: TEAM-R2R-GA_PREPARER_ | F78: R2R_ownership_delivery | G78: Ownership & Delivery | I78: 3 | K78: =IF(J78="","Assessment Pending",MAX(0,I78-J78)) -> Assessment Pending | M78: TRN-0037 | N78: Assessment pending before TNI
A79: GAP-00076 | B79: Synthetic Hackfest Test Data | C79: SYN-U008 | D79: R2R_ga_preparer_job_preparation_only | E79: TEAM-R2R-GA_PREPARER_ | F79: R2R_time_management | G79: Time Management | I79: 4 | K79: =IF(J79="","Assessment Pending",MAX(0,I79-J79)) -> Assessment Pending | M79: TRN-0043 | N79: Assessment pending before TNI
A80: GAP-00077 | B80: Synthetic Hackfest Test Data | C80: SYN-U008 | D80: R2R_ga_preparer_job_preparation_only | E80: TEAM-R2R-GA_PREPARER_ | F80: R2R_productivity_tools_excel_ppt | G80: Productivity Tools (Excel/PPT) | I80: 4 | K80: =IF(J80="","Assessment Pending",MAX(0,I80-J80)) -> Assessment Pending | M80: TRN-0038 | N80: Assessment pending before TNI
A81: GAP-00078 | B81: Synthetic Hackfest Test Data | C81: SYN-U008 | D81: R2R_ga_preparer_job_preparation_only | E81: TEAM-R2R-GA_PREPARER_ | F81: R2R_erp_finance_tools_sap_oracle_blackline_onestream_sox_controls_in_systems | G81: ERP / Finance Tools (SAP/Oracle/BlackLine/OneStream) (SOX controls-in-systems) | I81: 4 | K81: =IF(J81="","Assessment Pending",MAX(0,I81-J81)) -> Assessment Pending | M81: TRN-0033 | N81: Assessment pending before TNI
A82: GAP-00079 | B82: Synthetic Hackfest Test Data | C82: SYN-U008 | D82: R2R_ga_preparer_job_preparation_only | E82: TEAM-R2R-GA_PREPARER_ | F82: R2R_professional_conduct | G82: Professional Conduct | I82: 4 | K82: =IF(J82="","Assessment Pending",MAX(0,I82-J82)) -> Assessment Pending | M82: TRN-0039 | N82: Assessment pending before TNI
A83: GAP-00080 | B83: Synthetic Hackfest Test Data | C83: SYN-U008 | D83: R2R_ga_preparer_job_preparation_only | E83: TEAM-R2R-GA_PREPARER_ | F83: R2R_teamwork_collaboration | G83: Teamwork / Collaboration | I83: 4 | K83: =IF(J83="","Assessment Pending",MAX(0,I83-J83)) -> Assessment Pending | M83: TRN-0042 | N83: Assessment pending before TNI
A84: GAP-00081 | B84: Synthetic Hackfest Test Data | C84: SYN-U009 | D84: R2R_consolidation_preparer_job_execution_pack_prep | E84: TEAM-R2R-CONSOLIDATIO | F84: R2R_first_time_right_quality_sox_icfr_ready | G84: First Time Right (Quality, SOX/ICFR-ready) | I84: 3 | J84: 2 | K84: =IF(J84="","Assessment Pending",MAX(0,I84-J84)) -> 1 | L84: Moderate | M84: TRN-0035 | N84: Assign mapped microlearning / scenario lab and reassess
A85: GAP-00082 | B85: Synthetic Hackfest Test Data | C85: SYN-U009 | D85: R2R_consolidation_preparer_job_execution_pack_prep | E85: TEAM-R2R-CONSOLIDATIO | F85: R2R_attention_to_detail_sox_evidence_trail_documentation | G85: Attention to Detail (SOX evidence trail / documentation) | I85: 4 | J85: 2 | K85: =IF(J85="","Assessment Pending",MAX(0,I85-J85)) -> 2 | L85: High | M85: TRN-0031 | N85: Assign mapped microlearning / scenario lab and reassess | O85: Potential cross-tower transferable skill
A86: GAP-00083 | B86: Synthetic Hackfest Test Data | C86: SYN-U009 | D86: R2R_consolidation_preparer_job_execution_pack_prep | E86: TEAM-R2R-CONSOLIDATIO | F86: R2R_reconciliations_clearing_sox_ipe_balance_sheet_recs | G86: Reconciliations & Clearing (SOX/IPE balance sheet recs) | I86: 4 | J86: 2 | K86: =IF(J86="","Assessment Pending",MAX(0,I86-J86)) -> 2 | L86: High | M86: TRN-0041 | N86: Assign mapped microlearning / scenario lab and reassess
A87: GAP-00084 | B87: Synthetic Hackfest Test Data | C87: SYN-U009 | D87: R2R_consolidation_preparer_job_execution_pack_prep | E87: TEAM-R2R-CONSOLIDATIO | F87: R2R_financial_reporting_ifrs_us_gaap | G87: Financial Reporting (IFRS / US GAAP) | I87: 4 | J87: 2 | K87: =IF(J87="","Assessment Pending",MAX(0,I87-J87)) -> 2 | L87: High | M87: TRN-0034 | N87: Assign mapped microlearning / scenario lab and reassess
A88: GAP-00085 | B88: Synthetic Hackfest Test Data | C88: SYN-U009 | D88: R2R_consolidation_preparer_job_execution_pack_prep | E88: TEAM-R2R-CONSOLIDATIO | F88: R2R_consolidation_ifrs_10_ifrs_3_ias_21_asc_810 | G88: Consolidation (IFRS 10 / IFRS 3 / IAS 21 / ASC 810) | I88: 4 | J88: 2 | K88: =IF(J88="","Assessment Pending",MAX(0,I88-J88)) -> 2 | L88: High | M88: TRN-0032 | N88: Assign mapped microlearning / scenario lab and reassess
A89: GAP-00086 | B89: Synthetic Hackfest Test Data | C89: SYN-U009 | D89: R2R_consolidation_preparer_job_execution_pack_prep | E89: TEAM-R2R-CONSOLIDATIO | F89: R2R_time_management | G89: Time Management | I89: 4 | J89: 2 | K89: =IF(J89="","Assessment Pending",MAX(0,I89-J89)) -> 2 | L89: High | M89: TRN-0043 | N89: Assign mapped microlearning / scenario lab and reassess
A90: GAP-00087 | B90: Synthetic Hackfest Test Data | C90: SYN-U009 | D90: R2R_consolidation_preparer_job_execution_pack_prep | E90: TEAM-R2R-CONSOLIDATIO | F90: R2R_productivity_tools_excel_ppt | G90: Productivity Tools (Excel/PPT) | I90: 4 | J90: 2 | K90: =IF(J90="","Assessment Pending",MAX(0,I90-J90)) -> 2 | L90: High | M90: TRN-0038 | N90: Assign mapped microlearning / scenario lab and reassess
